Workbook
Name CC: #REF!
Name CC: #REF!
Name CC: #REF!
Name CC: #REF!
Name CC: #REF!
Name CC: #REF!
Name CC: #REF!
Name CC: #REF!
Name CC: #REF!
Name CC: #REF!
Name GABRIEL: #REF!
Name GABRIEL: #REF!
Name GABRIEL: #REF!
Name GABRIEL: #REF!
Name GABRIEL: #REF!
Name GABRIEL: #REF!
Name GABRIEL: #REF!
Name GABRIEL: #REF!
Name GABRIEL: #REF!
Name GABRIEL: #REF!

Sheet Cliente Custos
A1: MATERIAL | C1: PREÇO DO SACO | D1: PREÇO POR KG
A2: AREIA | C2: 1100 | D2: =C2/15000 -> 0.073333333
A3: CIMENTO | C3: 37 | D3: =C3/50 -> 0.74
A4: ADITIVO | C4: 850 | D4: =C4/25 -> 34
A5: EMBALAGEM | C5: 0.6 | D5: =C5 -> 0.6
D6: =C6 -> 0
D7: =C7 -> 0
A10: PRODUÇÃO
A11: ACII | B11: QTD SACOS | C11: Produtos | D11: QTD | I11: VALOR
D12: Batida | E12: % | F12: Qtd Unit/ Saco | G12: Qtd Total Scs | H12: Qtd Total Kgs | I12: Custo Saco 25Kg | J12: Custo Kg | K12: Custo Total | L12: % CUSTO
B13: 1000 | C13: AREIA | D13: 200 | E13: =D13/D18 -> 0.79872204 | F13: =(D18*E13)/C18 -> 11.980831 | G13: =H13/25 -> 479.23323 | H13: =B13*F13 -> 11980.831 | I13: =F13*$D$2 -> 0.87859425 | J13: =(I13+I14+I15+I16+I17)/25 -> 0.18038978 | K13: =$D$2*H13 -> 878.59425 | L13: =K13/$K$18 -> 0.1948213
C14: CIMENTO | D14: 50 | E14: =D14/D18 -> 0.19968051 | F14: =(D18*E14)/C18 -> 2.9952077 | G14: =H14/25 -> 119.80831 | H14: =B13*F14 -> 2995.2077 | I14: =F14*$D$3 -> 2.2164537 | K14: =$D$3*H14 -> 2216.4537 | L14: =K14/$K$18 -> 0.491481
C15: ADITIVO | D15: 0.4 | E15: =D15/D18 -> 0.0015974441 | F15: =(D18*E15)/C18 -> 0.023961661 | G15: =H15/20 -> 1.1980831 | H15: =B13*F15 -> 23.961661 | I15: =F15*$D$4 -> 0.81469649 | K15: =$D$4*H15 -> 814.69649 | L15: =K15/$K$18 -> 0.18065247
C16: EMBALAGEM | D16: 1 | F16: 1 | G16: =H16/1 -> 1000 | H16: =F16*B13 -> 1000 | I16: =F16*$D$5 -> 0.6 | K16: =$D$5*H16 -> 600 | L16: =K16/$K$18 -> 0.13304523
G17: =H17/1 -> 0 | H17: =F17*B13 -> 0 | I17: =F17*$D$6 -> 0 | K17: =$D$6*H17 -> 0 | L17: =K17/$K$18 -> 0
B18: TOTAL | C18: =D18/15 -> 16.693333 | D18: =SUM(D13:D15) -> 250.4 | E18: =SUM(E13:E15) -> 1 | F18: =SUM(F13:F15) -> 15 | H18: =SUM(H13:H15) -> 15000 | I18: =SUM(I13:I16) -> 4.5097444 | K18: =SUM(K13:K16) -> 4509.7444

Sheet Custo ARGAMASSA
B1: MATERIAL | D1: PREÇO POR KG | E1: valor | F1: qtd
B2: AREIA | D2: =E2/F2 -> 0.081481481 | E2: 1100 | F2: 13500
B3: SILEX | D3: =E3/F3 -> 1 | E3: 1 | F3: 1
B4: CIMENTO COMUM | D4: =E4/F4 -> 0.65 | E4: 32.5 | F4: 50
B5: CIMENTO BRANCO | D5: =E5/F5 -> 1 | E5: 1 | F5: 1
B6: CELULOSICO | D6: =E6/F6 -> 33.2 | E6: 830 | F6: 25 | K6: 1000 | L6: 15000 | M6: =K6/L6 -> 0.066666667
B7: POLIMERO | D7: =E7/F7 -> 12 | E7: 300 | F7: 25
B8: PIG PRETO | D8: =E8/F8 -> 1 | E8: 1 | F8: 1 | H8: 300g
B9: PIG AMARELO | D9: =E9/F9 -> 1 | E9: 1 | F9: 1 | H9: 1kg
B10: PIG AZUL | D10: =E10/F10 -> 1 | E10: 1 | F10: 1
B11: PIG VERMELHO | D11: =E11/F11 -> 1 | E11: 1 | F11: 1
B14: PRODUÇÃO
B15: AC II | C15: QTD SACOS | D15: Produtos | E15: QTD | I15: VALOR
E16: Batida | F16: % | G16: Qtd Unit/ Saco | H16: Qtd Total | I16: Custo Saco 15Kg | J16: Custo Kg | K16: Custo Total
C17: 26000 | D17: AREIA | E17: 175 | F17: =E17/E20 -> 0.77656978 | G17: =(E20*F17)/D20 -> 11.648547 | H17: =C17*G17 -> 302862.21 | I17: =G17*$D$2 -> 0.94914084 | J17: =I20/15 -> 0.25906039 | K17: =$D$2*H17 -> 24677.662
D18: CIMENTO | E18: 50 | F18: =E18/E20 -> 0.22187708 | G18: =(E20*F18)/D20 -> 3.3281562 | H18: =C17*G18 -> 86532.061 | I18: =G18*$D$4 -> 2.1633015 | K18: =$D$4*H18 -> 56245.84
D19: CELULOSICO | E19: 0.35 | F19: =E19/E20 -> 0.0015531396 | G19: =(E20*F19)/D20 -> 0.023297093 | H19: =C17*G19 -> 605.72443 | I19: =G19*$D$6 -> 0.7734635 | K19: =$D$6*H19 -> 20110.051
C20: TOTAL | D20: =E20/15 -> 15.023333 | E20: =SUM(E17:E19) -> 225.35 | F20: =SUM(F17:F19) -> 1 | G20: =SUM(G17:G19) -> 15 | H20: =SUM(H17:H19) -> 390000 | I20: =SUM(I17:I19) -> 3.8859059 | K20: =SUM(K17:K19) -> 101033.55
M21: 450 | N21: 25 | O21: =M21/N21 -> 18
B22: PRODUÇÃO
B23: ESPECIAL | C23: QTD SACOS | D23: Produtos | E23: QTD | I23: VALOR
E24: Batida | F24: % | G24: Qtd Unit/ Saco | H24: Qtd Total | I24: Custo Saco 15Kg | J24: Custo Kg | K24: Custo Total
C25: 4000 | D25: AREIA | E25: 175 | F25: =E25/E29 -> 0.76923077 | G25: =(E29*F25)/D29 -> 11.538462 | H25: =C25*G25 -> 46153.846 | I25: =G25*$D$2 -> 0.94017094 | J25: =I29/15 -> 0.38399674 | K25: =$D$2*H25 -> 3760.6838
D26: CIMENTO | E26: 50 | F26: =E26/E29 -> 0.21978022 | G26: =(E29*F26)/D29 -> 3.2967033 | H26: =C25*G26 -> 13186.813 | I26: =G26*$D$4 -> 2.1428571 | K26: =$D$4*H26 -> 8571.4286
D27: CELULOSICO | E27: 0.5 | F27: =E27/E29 -> 0.0021978022 | G27: =(E29*F27)/D29 -> 0.032967033 | H27: =C25*G27 -> 131.86813 | I27: =G27*$D$6 -> 1.0945055 | K27: =$D$6*H27 -> 4378.022
D28: POLÍMERO | E28: 2 | F28: =E28/E29 -> 0.0087912088 | G28: =(E29*F28)/D29 -> 0.13186813 | H28: =C25*G28 -> 527.47253 | I28: =G28*$D$7 -> 1.5824176 | K28: =$D$7*H28 -> 6329.6703
C29: TOTAL | D29: =E29/15 -> 15.166667 | E29: =SUM(E25:E28) -> 227.5 | F29: =SUM(F25:F27) -> 0.99120879 | G29: =SUM(G25:G28) -> 15 | H29: =SUM(H25:H27) -> 59472.527 | I29: =SUM(I25:I28) -> 5.7599512 | K29: =SUM(K25:K28) -> 23039.805
B31: ACIII | C31: QTD SACOS | D31: Produtos | E31: QTD | I31: VALOR
E32: Batida | F32: % | G32: Qtd Unit/ Saco | H32: Qtd Total | I32: Custo Saco 15Kg | J32: Custo Kg | K32: Custo Total
C33: =E37/15 -> 68.833333 | D33: AREIA | E33: 770 | F33: =E33/E37 -> 0.74576271 | G33: =(E37*F33)/D37 -> 11.186441 | H33: =C33*G33 -> 770 | I33: =G33*$D$2 -> 0.91148776 | J33: =I37/15 -> 0.41476101 | K33: =$D$2*H33 -> 62.740741
D34: CIMENTO | E34: 250 | F34: =E34/E37 -> 0.24213075 | G34: =(E37*F34)/D37 -> 3.6319613 | H34: =C33*G34 -> 250 | I34: =G34*$D$4 -> 2.3607748 | K34: =$D$4*H34 -> 162.5
D35: CELULOSICO | E35: 2.5 | F35: =E35/E37 -> 0.0024213075 | G35: =(E37*F35)/D37 -> 0.036319613 | H35: =C33*G35 -> 2.5 | I35: =G35*$D$6 -> 1.2058111 | K35: =$D$6*H35 -> 83
D36: POLIMERO | E36: 10 | F36: =E36/E37 -> 0.00968523 | G36: =(E37*F36)/D37 -> 0.14527845 | H36: =C33*G36 -> 10 | I36: =G36*$D$7 -> 1.7433414 | K36: =$D$7*H36 -> 120
C37: TOTAL | D37: =E37/15 -> 68.833333 | E37: =SUM(E33:E36) -> 1032.5 | F37: =SUM(F33:F36) -> 1 | G37: =SUM(G33:G36) -> 15 | H37: =SUM(H33:H36) -> 1032.5 | I37: =SUM(I33:I36) -> 6.2214151 | K37: =SUM(K33:K36) -> 428.24074
B39: ACIII E | C39: QTD SACOS | D39: Produtos | E39: QTD | I39: VALOR
E40: Batida | F40: % | G40: Qtd Unit/ Saco | H40: Qtd Total | I40: Custo Saco 15Kg | J40: Custo Kg | K40: Custo Total
C41: 69 | D41: AREIA | E41: 770 | F41: =E41/E46 -> 0.74432093 | G41: =(E46*F41)/D46 -> 11.164814 | H41: =C41*G41 -> 770.37216 | I41: =G41*$D$2 -> 0.90972558 | J41: =I46/15 -> 0.43715876 | K41: =$D$2*H41 -> 62.771065
D42: CIMENTO | E42: 250 | F42: =E42/E46 -> 0.24166264 | G42: =(E46*F42)/D46 -> 3.6249396 | H42: =C41*G42 -> 250.12083 | I42: =G42*$D$4 -> 2.3562107 | K42: =$D$4*H42 -> 162.57854
D43: CELULOSICO | E43: 2.5 | F43: =E43/E46 -> 0.0024166264 | G43: =(E46*F43)/D46 -> 0.036249396 | H43: =C41*G43 -> 2.5012083 | I43: =G43*$D$6 -> 1.2034799 | K43: =$D$6*H43 -> 83.040116
D44: POLIMERO | E44: 12 | F44: =E44/E46 -> 0.011599807 | G44: =(E46*F44)/D46 -> 0.1739971 | H44: =C41*G44 -> 12.0058 | I44: =G44*$D$7 -> 2.0879652 | K44: =$D$7*H44 -> 144.0696
D45: FORMIATO | F45: =E45/E46 -> 0 | G45: =(E46*F45)/D46 -> 0 | H45: =C41*G45 -> 0 | I45: =G45*$D$3 -> 0 | K45: =$D$3*H45 -> 0
C46: TOTAL | D46: =E46/15 -> 68.966667 | E46: =SUM(E41:E45) -> 1034.5 | F46: =SUM(F41:F45) -> 1 | G46: =SUM(G41:G45) -> 15 | H46: =SUM(H41:H45) -> 1035 | I46: =SUM(I41:I45) -> 6.5573815 | K46: =SUM(K41:K45) -> 452.45932
B49: ACIII E BRANCA PARA PLASTILHA DE VIDRO | C49: QTD SACOS | D49: Produtos | E49: QTD | I49: VALOR
E50: Batida | F50: % | G50: Qtd Unit/ Saco | H50: Qtd Total | I50: Custo Saco 15Kg | J50: Custo Kg | K50: Custo Total
C51: 13 | D51: SILEX | E51: 150 | F51: =E51/E56 -> 0.73746313 | G51: =(E56*F51)/D56 -> 11.061947 | H51: =C51*G51 -> 143.80531 | I51: =G51*$D$3 -> 11.061947 | J51: =I56/15 -> 1.2255654 | K51: =$D$3*H51 -> 143.80531
D52: CIMENTO BRANCO | E52: 50 | F52: =E52/E56 -> 0.24582104 | G52: =(E56*F52)/D56 -> 3.6873156 | H52: =C51*G52 -> 47.935103 | I52: =G52*$D$5 -> 3.6873156 | K52: =$D$5*H52 -> 47.935103
D53: CELULOSICO | E53: 0.4 | F53: =E53/E56 -> 0.0019665683 | G53: =(E56*F53)/D56 -> 0.029498525 | H53: =C51*G53 -> 0.38348083 | I53: =G53*$D$6 -> 0.97935103 | K53: =$D$6*H53 -> 12.731563
D54: POLIMERO | E54: 3 | F54: =E54/E56 -> 0.014749263 | G54: =(E56*F54)/D56 -> 0.22123894 | H54: =C51*G54 -> 2.8761062 | I54: =G54*$D$7 -> 2.6548673 | K54: =$D$7*H54 -> 34.513274
D55: FORMIATO | F55: =E55/E56 -> 0 | G55: =(E56*F55)/D56 -> 0 | H55: =C51*G55 -> 0 | I55: =G55*$D$3 -> 0 | K55: =$D$3*H55 -> 0
C56: TOTAL | D56: =E56/15 -> 13.56 | E56: =SUM(E51:E55) -> 203.4 | F56: =SUM(F51:F55) -> 1 | G56: =SUM(G51:G55) -> 15 | H56: =SUM(H51:H55) -> 195 | I56: =SUM(I51:I55) -> 18.383481 | K56: =SUM(K51:K55) -> 238.98525
B58: RJ CINZA | C58: QTD SACOS | D58: Produtos | E58: QTD | I58: VALOR
E59: Batida | F59: % | G59: Qtd Unit/ Saco | H59: Qtd Total | I59: Custo Kg | J59: Custo Total
C60: 200 | D60: SILEX | E60: 150 | F60: =E60/E64 -> 0.74552684 | G60: =(E64*F60)/D64 -> 0.74552684 | H60: =C60*G60 -> 149.10537 | I60: =G60*$D$3 -> 0.74552684 | J60: =$D$3*H60 -> 149.10537
D61: CIMENTO COMUM | E61: 50 | F61: =E61/E64 -> 0.24850895 | G61: =(E64*F61)/D64 -> 0.24850895 | H61: =C60*G61 -> 49.701789 | I61: =G61*$D$4 -> 0.16153082 | J61: =$D$4*H61 -> 32.306163
D62: CELULOSICO | E62: 0,100 | F62: =E62/E64 -> 0.00049701789 | G62: =(E64*F62)/D64 -> 0.00049701789 | H62: =C60*G62 -> 0.099403579 | I62: =G62*$D$6 -> 0.016500994 | J62: =$D$6*H62 -> 3.3001988
D63: POLIMERO | E63: 1.2 | F63: =E63/E64 -> 0.0059642147 | G63: =(E64*F63)/D64 -> 0.0059642147 | H63: =C60*G63 -> 1.1928429 | I63: =G63*$D$7 -> 0.071570577 | J63: =$D$7*H63 -> 14.314115
C64: TOTAL | D64: =E64/1 -> 201.2 | E64: =SUM(E60:E63) -> 201.2 | F64: =SUM(F60:F63) -> 1.000497 | G64: =SUM(G60:G63) -> 1.000497 | H64: =SUM(H60:H63) -> 200.0994 | I64: =SUM(I60:I63) -> 0.99512922 | J64: =SUM(J60:J63) -> 199.02584
B66: RJ CINZA PLATINA | C66: QTD SACOS | D66: Produtos | E66: QTD | I66: VALOR
E67: Batida | F67: % | G67: Qtd Unit/ Saco | H67: Qtd Total | I67: Custo Kg | J67: Custo Total
C68: 200 | D68: SILEX | E68: 150 | F68: =E68/E74 -> 0.74331021 | G68: =(E74*F68)/D74 -> 0.74331021 | H68: =C68*G68 -> 148.66204 | I68: =G68*$D$3 -> 0.74331021 | J68: =$D$3*H68 -> 148.66204
D69: CIMENTO COMUM | E69: 15 | F69: =E69/E74 -> 0.074331021 | G69: =(E74*F69)/D74 -> 0.074331021 | H69: =C68*G69 -> 14.866204 | I69: =G69*$D$4 -> 0.048315164 | J69: =$D$4*H69 -> 9.6630327
D70: CIMENTO BRANCO | E70: 35 | F70: =E70/E74 -> 0.17343905 | G70: =(E74*F70)/D74 -> 0.17343905 | H70: =C68*G70 -> 34.68781 | I70: =G70*$D$5 -> 0.17343905 | J70: =$D$5*H70 -> 34.68781
D71: CELULOSICO | E71: 0.1 | F71: =E71/E74 -> 0.00049554014 | G71: =(E74*F71)/D74 -> 0.00049554014 | H71: =C68*G71 -> 0.099108028 | I71: =G71*$D$6 -> 0.016451933 | J71: =$D$6*H71 -> 3.2903865
D72: POLIMERO | E72: 1.2 | F72: =E72/E74 -> 0.0059464817 | G72: =(E74*F72)/D74 -> 0.0059464817 | H72: =C68*G72 -> 1.1892963 | I72: =G72*$D$7 -> 0.07135778 | J72: =$D$7*H72 -> 14.271556
D73: PIG AZUL | E73: 0.5 | F73: =E73/E74 -> 0.0024777007 | G73: =(E74*F73)/D74 -> 0.0024777007 | H73: =C68*G73 -> 0.49554014 | I73: =G73*D10 -> 0.0024777007 | J73: =#REF!*H73 -> #REF!
C74: TOTAL | D74: =E74/1 -> 201.8 | E74: =SUM(E68:E73) -> 201.8 | F74: =SUM(F68:F73) -> 1 | G74: =SUM(G68:G73) -> 1 | H74: =SUM(H68:H73) -> 200 | I74: =SUM(I68:I73) -> 1.0553518 | J74: =SUM(J68:J73) -> #REF!
B76: RJ PRETO | C76: QTD SACOS | D76: Produtos | E76: QTD | I76: VALOR
E77: Batida | F77: % | G77: Qtd Unit/ Saco | H77: Qtd Total | I77: Custo Kg | J77: Custo Total
C78: 200 | D78: SILEX | E78: 150 | F78: =E78/E83 -> 0.72011522 | G78: =(E83*F78)/D83 -> 0.72011522 | H78: =G78*C78 -> 144.02304 | I78: =G78*$D$3 -> 0.72011522 | J78: =$D$3*H78 -> 144.02304
D79: CIMENTO COMUM | E79: 50 | F79: =E79/E83 -> 0.24003841 | G79: =(E83*F79)/D83 -> 0.24003841 | H79: =C78*G79 -> 48.007681 | I79: =G79*$D$4 -> 0.15602496 | J79: =$D$4*H79 -> 31.204993
D80: CELULOSICO | E80: 0.1 | F80: =E80/E83 -> 0.00048007681 | G80: =(E83*F80)/D83 -> 0.00048007681 | H80: =C78*G80 -> 0.096015362 | I80: =G80*$D$6 -> 0.01593855 | J80: =$D$6*H80 -> 3.18771
D81: POLIMERO | E81: 1.2 | F81: =E81/E83 -> 0.0057609217 | G81: =(E83*F81)/D83 -> 0.0057609217 | H81: =C78*G81 -> 1.1521843 | I81: =G81*$D$7 -> 0.069131061 | J81: =$D$7*H81 -> 13.826212
D82: PIG PRETO | E82: 7 | F82: =E82/E83 -> 0.033605377 | G82: =(E83*F82)/D83 -> 0.033605377 | H82: =C78*G82 -> 6.7210754 | I82: =G82*$D$8 -> 0.033605377 | J82: =$D$8*H82 -> 6.7210754
C83: TOTAL | D83: =E83/1 -> 208.3 | E83: =SUM(E78:E82) -> 208.3 | F83: =SUM(F78:F82) -> 1 | G83: =SUM(G78:G82) -> 1 | H83: =SUM(H78:H82) -> 200 | I83: =SUM(I78:I82) -> 0.99481517 | J83: =SUM(J78:J82) -> 198.96303
B85: RJ BRANCO | C85: QTD SACOS | D85: Produtos | E85: QTD | I85: VALOR
E86: Batida | F86: % | G86: Qtd Unit/ Saco | H86: Qtd Total | I86: Custo Kg | J86: Custo Total
C87: 200 | D87: SILEX | E87: 150 | F87: =E87/E91 -> 0.74515648 | G87: =(E91*F87)/D91 -> 0.74515648 | H87: =C87*G87 -> 149.0313 | I87: =G87*$D$3 -> 0.74515648 | J87: =$D$3*H87 -> 149.0313
D88: CIMENTO BRANCO | E88: 50 | F88: =E88/E91 -> 0.24838549 | G88: =(E91*F88)/D91 -> 0.24838549 | H88: =C87*G88 -> 49.677099 | I88: =G88*$D$5 -> 0.24838549 | J88: =$D$5*H88 -> 49.677099
D89: CELULOSICO | E89: 0.1 | F89: =E89/E91 -> 0.00049677099 | G89: =(E91*F89)/D91 -> 0.00049677099 | H89: =C87*G89 -> 0.099354198 | I89: =G89*$D$6 -> 0.016492797 | J89: =$D$6*H89 -> 3.2985594
D90: POLIMERO | E90: 1.2 | F90: =E90/E91 -> 0.0059612519 | G90: =(E91*F90)/D91 -> 0.0059612519 | H90: =C87*G90 -> 1.1922504 | I90: =G90*$D$7 -> 0.071535022 | J90: =$D$7*H90 -> 14.307004
C91: TOTAL | D91: =E91/1 -> 201.3 | E91: =SUM(E87:E90) -> 201.3 | F91: =SUM(F87:F90) -> 1 | G91: =SUM(G87:G90) -> 1 | H91: =SUM(H87:H90) -> 200 | I91: =SUM(I87:I90) -> 1.0815698 | J91: =SUM(J87:J90) -> 216.31396
B93: RJ MARFIM | C93: QTD SACOS | D93: Produtos | E93: QTD | I93: VALOR
E94: Batida | F94: % | G94: Qtd Unit/ Saco | H94: Qtd Total | I94: Custo Kg | J94: Custo Total
C95: 200 | D95: SILEX | E95: 150 | F95: =E95/E100 -> 0.74441687 | G95: =(E100*F95)/D100 -> 0.74441687 | H95: =C95*G95 -> 148.88337 | I95: =G95*$D$3 -> 0.74441687 | J95: =$D$3*H95 -> 148.88337
D96: CIMENTO BRANCO | E96: 50 | F96: =E96/E100 -> 0.24813896 | G96: =(E100*F96)/D100 -> 0.24813896 | H96: =C95*G96 -> 49.627792 | I96: =G96*$D$5 -> 0.24813896 | J96: =$D$5*H96 -> 49.627792
D97: CELULOSICO | E97: 0.1 | F97: =E97/E100 -> 0.00049627792 | G97: =(E100*F97)/D100 -> 0.00049627792 | H97: =C95*G97 -> 0.099255583 | I97: =G97*$D$6 -> 0.016476427 | J97: =$D$6*H97 -> 3.2952854
D98: POLIMERO | E98: 1.2 | F98: =E98/E100 -> 0.005955335 | G98: =(E100*F98)/D100 -> 0.005955335 | H98: =C95*G98 -> 1.191067 | I98: =G98*$D$7 -> 0.07146402 | J98: =$D$7*H98 -> 14.292804
D99: PIG AMARELO | E99: 0.2 | F99: =E99/E100 -> 0.00099255583 | G99: =(E100*F99)/D100 -> 0.00099255583 | H99: =C95*G99 -> 0.19851117 | I99: =G99*$D$9 -> 0.00099255583 | J99: =$D$9*H99 -> 0.19851117
C100: TOTAL | D100: =E100/1 -> 201.5 | E100: =SUM(E95:E99) -> 201.5 | F100: =SUM(F95:F99) -> 1 | G100: =SUM(G95:G99) -> 1 | H100: =SUM(H95:H99) -> 200 | I100: =SUM(I95:I99) -> 1.0814888 | J100: =SUM(J95:J99) -> 216.29777
B102: RJ BEGE | C102: QTD SACOS | D102: Produtos | E102: QTD | I102: VALOR
E103: Batida | F103: % | G103: Qtd Unit/ Saco | H103: Qtd Total | I103: Custo Kg | J103: Custo Total
C104: 200 | D104: SILEX | E104: 150 | F104: =E104/E111 -> 0.7390983 | G104: =(E111*F104)/D111 -> 0.7390983 | H104: =C104*G104 -> 147.81966 | I104: =G104*$D$3 -> 0.7390983 | J104: =$D$3*H104 -> 147.81966
D105: CIMENTO COMUM | E105: 25 | F105: =E105/E111 -> 0.12318305 | G105: =(E111*F105)/D111 -> 0.12318305 | H105: =C104*G105 -> 24.63661 | I105: =G105*$D$4 -> 0.080068983 | J105: =$D$4*H105 -> 16.013797
D106: CIMENTO BRANCO | E106: 25 | F106: =E106/E111 -> 0.12318305 | G106: =(E111*F106)/D111 -> 0.12318305 | H106: =C104*G106 -> 24.63661 | I106: =G106*$D$5 -> 0.12318305 | J106: =$D$5*H106 -> 24.63661
D107: CELULOSICO | E107: 0.1 | F107: =E107/E111 -> 0.0004927322 | G107: =(E111*F107)/D111 -> 0.0004927322 | H107: =C104*G107 -> 0.09854644 | I107: =G107*$D$6 -> 0.016358709 | J107: =$D$6*H107 -> 3.2717418
D108: POLIMERO | E108: 1.2 | F108: =E108/E111 -> 0.0059127864 | G108: =(E111*F108)/D111 -> 0.0059127864 | H108: =C104*G108 -> 1.1825573 | I108: =G108*$D$7 -> 0.070953437 | J108: =$D$7*H108 -> 14.190687
D109: PIG AMARELO | E109: 1.5 | F109: =E109/E111 -> 0.007390983 | G109: =(E111*F109)/D111 -> 0.007390983 | H109: =C104*G109 -> 1.4781966 | I109: =G109*$D$9 -> 0.007390983 | J109: =$D$9*H109 -> 1.4781966
D110: PIG VERMELHO | E110: 0.15 | F110: =E110/E111 -> 0.0007390983 | G110: =(E111*F110)/D111 -> 0.0007390983 | H110: =C104*G110 -> 0.14781966 | I110: =G110*D11 -> 0.0007390983 | J110: =$D$9*H110 -> 0.14781966
C111: TOTAL | D111: =E111/1 -> 202.95 | E111: =SUM(E104:E110) -> 202.95 | F111: =SUM(F104:F110) -> 1 | G111: =SUM(G104:G110) -> 1 | H111: =SUM(H104:H110) -> 200 | I111: =SUM(I104:I110) -> 1.0377926 | J111: =SUM(J104:J110) -> 207.55851
B113: RJ GRAFITE | C113: QTD SACOS | D113: Produtos | E113: QTD | I113: VALOR
...

Sheet Custo Prod.
B1: MATERIAL | D1: PREÇO DO SACO | E1: PREÇO POR KG | G1: 727 | J1: kg/dolar | K1: kg/dolar + 3,25% | L1: (kg/dolar + 5%)* dolar | M1: 25kg | W1: PEDIDO 1 | AA1: PEDIDO 2 | AE1: PEDIDO 3 | AI1: PEDIDO 4 | AM1: MEDIA | AN1: MESES | AO1: PM COMPRA | AP1: PM VENDA
B2: Celulosico (MP) 25kg | D2: =G2+H2 -> 693 | E2: =D2/25 -> 27.72 | G2: 658 | H2: 35 | J2: 6.21 | K2: =J2*1.0325 -> 6.411825 | L2: =K2*5.06 -> 32.443834 | M2: =L2*25 -> 811.09586 | Q2: LUCRO DOS 80 | R2: =500-J20 -> 4.52 | S2: =R2*80 -> 361.6 | W2: venc | X2: valor total | Y2: qtd total | Z2: und | AA2: venc | AB2: valor total | AC2: qtd total | AD2: und | AE2: venc | AF2: valor total | AG2: qtd total | AH2: und | AI2: venc | AJ2: valor total | AK2: qtd total | AL2: und | AO2: 900 | AP2: 870
B3: Celugel 25kg | D3: =G3+H3 -> 214.1 | E3: =D3/25 -> 8.564 | F3: 7.3 | G3: =F3*25 -> 182.5 | H3: 31.6 | I3: 609.5 | T3: XXX | V3: 44896 | W3: 44909 | X3: 26478.5 | Y3: 30 | Z3: =X3/Y3 -> 882.61667 | AA3: 44923 | AB3: 35346.65 | AC3: 40 | AD3: =AB3/AC3 -> 883.66625 | AH3: =AF3/AG3 -> #DIV/0! | AL3: =AJ3/AK3 -> #DIV/0! | AM3: =(X3+AB3+AF3+AJ3)/(Y3+AC3+AG3+AK3) -> 883.21643 | AN3: 44531 | AO3: =1- ($AO$2/AM3) -> -0.019002784 | AP3: =$AP$2+($AP$2*AO3) -> 853.46758
B4: Fibra 20kg | D4: =G4+H4 -> 300.6 | E4: =D4/20 -> 15.03 | F4: 13.45 | G4: =F4*20 -> 269 | H4: 31.6 | J4: 526 | V4: 44927 | W4: 44942 | X4: 35166.8 | Y4: 40 | Z4: =X4/Y4 -> 879.17 | AA4: 44960 | AB4: 25980.4 | AC4: 30 | AD4: =AB4/AC4 -> 866.01333 | AH4: =AF4/AG4 -> #DIV/0! | AL4: =AJ4/AK4 -> #DIV/0! | AM4: =(X4+AB4+AF4+AJ4)/(Y4+AC4+AG4+AK4) -> 873.53143 | AN4: 44927 | AO4: =1- ($AO$2/AM4) -> -0.030300652 | AP4: =$AP$2+($AP$2*AO4) -> 843.63843
B5: Polimero (MP) 25kg | D5: =G5+H5 -> 0 | E5: =D5/25 -> 0 | V5: 44958 | W5: 44977 | X5: 33332.5 | Y5: 40 | Z5: =X5/Y5 -> 833.3125 | AA5: 44993 | AB5: 24859.4 | AC5: 30 | AD5: =AB5/AC5 -> 828.64667 | AH5: =AF5/AG5 -> #DIV/0! | AL5: =AJ5/AK5 -> #DIV/0! | AM5: =(X5+AB5+AF5+AJ5)/(Y5+AC5+AG5+AK5) -> 831.31286 | AN5: 44958 | AO5: =1- ($AO$2/AM5) -> -0.082624901 | AP5: =$AP$2+($AP$2*AO5) -> 798.11634
B6: Embalagem | D6: =G6+H6 -> 8.1 | E6: =D6 -> 8.1 | G6: 7.1 | H6: 1 | V6: 44986 | W6: 45009 | X6: 32911.9 | Y6: 40 | Z6: =X6/Y6 -> 822.7975 | AA6: 45022 | AB6: 32948.45 | AC6: 40 | AD6: =AB6/AC6 -> 823.71125 | AH6: =AF6/AG6 -> #DIV/0! | AL6: =AJ6/AK6 -> #DIV/0! | AM6: =(X6+AB6+AF6+AJ6)/(Y6+AC6+AG6+AK6) -> 823.25438 | AN6: 44986 | AO6: =1- ($AO$2/AM6) -> -0.09322225 | AP6: =$AP$2+($AP$2*AO6) -> 788.89664
B7: Adesivo | D7: =G7 -> 1.5 | E7: =D7 -> 1.5 | G7: 1.5 | V7: 45017 | X7: 33626.15 | Y7: 40 | Z7: =X7/Y7 -> 840.65375 | AD7: =AB7/AC7 -> #DIV/0! | AH7: =AF7/AG7 -> #DIV/0! | AL7: =AJ7/AK7 -> #DIV/0! | AM7: =(X7+AB7+AF7+AJ7)/(Y7+AC7+AG7+AK7) -> 840.65375 | AN7: 45017 | AO7: =1- ($AO$2/AM7) -> -0.070595355 | AP7: =$AP$2+($AP$2*AO7) -> 808.58204
B8: ??? | E8: =D8 -> 0 | V8: 45047 | W8: 45062 | X8: 24051.75 | Y8: 30 | Z8: =X8/Y8 -> 801.725 | AA8: 45079 | AB8: 30809.03 | AC8: 40 | AD8: =AB8/AC8 -> 770.22575 | AE8: 45092 | AF8: 30438.55 | AG8: 40 | AH8: =AF8/AG8 -> 760.96375 | AL8: =AJ8/AK8 -> #DIV/0! | AM8: =(X8+AB8+AF8+AJ8)/(Y8+AC8+AG8+AK8) -> 775.44845 | AN8: 45047 | AO8: =1- ($AO$2/AM8) -> -0.16061873 | AP8: =$AP$2+($AP$2*AO8) -> 730.26171
S9: =SUM(S3:S7) -> 0 | T9: TOTAL | V9: 45078 | W9: 45110 | X9: 38483.65 | Y9: 50 | Z9: =X9/Y9 -> 769.673 | AA9: 45121 | AB9: 30175.64 | AC9: 40 | AD9: =AB9/AC9 -> 754.391 | AH9: =AF9/AG9 -> #DIV/0! | AL9: =AJ9/AK9 -> #DIV/0! | AM9: =(X9+AB9+AF9+AJ9)/(Y9+AC9+AG9+AK9) -> 762.881 | AN9: 45078 | AO9: =1- ($AO$2/AM9) -> -0.17973839 | AP9: =$AP$2+($AP$2*AO9) -> 713.6276
S10: =S2-S9 -> 361.6 | V10: 45108 | W10: 45133 | X10: 29445.2 | Y10: 40 | Z10: =X10/Y10 -> 736.13 | AA10: 45135 | AB10: 7333.65 | AC10: 10 | AD10: =AB10/AC10 -> 733.365 | AE10: 45146 | AF10: 36765.05 | AG10: 50 | AH10: =AF10/AG10 -> 735.301 | AL10: =AJ10/AK10 -> #DIV/0! | AM10: =(X10+AB10+AF10+AJ10)/(Y10+AC10+AG10+AK10) -> 735.439 | AN10: 45108 | AO10: =1- ($AO$2/AM10) -> -0.22375887 | AP10: =$AP$2+($AP$2*AO10) -> 675.32978
B11: PRODUÇÃO | V11: 45139 | W11: 45163 | X11: 36774.25 | Y11: 50 | Z11: =X11/Y11 -> 735.485 | AA11: 45174 | AB11: 41710.5 | AC11: 60 | AD11: =AB11/AC11 -> 695.175 | AH11: =AF11/AG11 -> #DIV/0! | AL11: =AJ11/AK11 -> #DIV/0! | AM11: =(X11+AB11+AF11+AJ11)/(Y11+AC11+AG11+AK11) -> 713.49773 | AN11: 45139 | AO11: =1- ($AO$2/AM11) -> -0.26139154 | AP11: =$AP$2+($AP$2*AO11) -> 642.58936
B12: CELULOSICO | C12: QTD SACOS | D12: Produtos | E12: QTD | J12: VALOR | V12: 45170 | W12: 45187 | X12: 43032.7 | Y12: 60 | Z12: =X12/Y12 -> 717.21167 | AA12: 45202 | AB12: 43050.27 | AC12: 60 | AD12: =AB12/AC12 -> 717.5045 | AH12: =AF12/AG12 -> #DIV/0! | AL12: =AJ12/AK12 -> #DIV/0! | AM12: =(X12+AB12+AF12+AJ12)/(Y12+AC12+AG12+AK12) -> 717.35808 | AN12: 45170 | AO12: =1- ($AO$2/AM12) -> -0.25460355 | AP12: =$AP$2+($AP$2*AO12) -> 648.49491
E13: Batida | F13: % | G13: Qtd Unit/ Saco | H13: Qtd Total Scs | I13: Qtd Total Kgs | J13: Custo Saco 25Kg | K13: Custo Kg | L13: Custo Total | V13: 45200 | W13: 45222 | X13: 40644.4 | Y13: 60 | Z13: =X13/Y13 -> 677.40667 | AD13: =AB13/AC13 -> #DIV/0! | AH13: =AF13/AG13 -> #DIV/0! | AL13: =AJ13/AK13 -> #DIV/0! | AM13: =(X13+AB13+AF13+AJ13)/(Y13+AC13+AG13+AK13) -> 677.40667 | AN13: 45200 | AO13: =1- ($AO$2/AM13) -> -0.32859631 | AP13: =$AP$2+($AP$2*AO13) -> 584.12121
C14: 90 | D14: CELULOSICO | E14: 50 | F14: =E14/E20 -> 0.5 | G14: =(E20*F14)/D20 -> 12.5 | H14: =I14/25 -> 45 | I14: =C14*G14 -> 1125 | J14: =G14*$E$2 -> 346.5 | K14: =(J14+J15+J16+J17+J19)/25 -> 19.7592 | L14: =$E$2*I14 -> 31185 | V14: 45231 | W14: 45244 | X14: 43129.54 | Y14: 60 | Z14: =X14/Y14 -> 718.82567 | AA14: 45272 | AB14: 40828.9 | AC14: 60 | AD14: =AB14/AC14 -> 680.48167 | AH14: =AF14/AG14 -> #DIV/0! | AL14: =AJ14/AK14 -> #DIV/0! | AM14: =(X14+AB14+AF14+AJ14)/(Y14+AC14+AG14+AK14) -> 699.65367 | AN14: 45231 | AO14: =1- ($AO$2/AM14) -> -0.28635072 | AP14: =$AP$2+($AP$2*AO14) -> 620.87487
D15: CELUGEL | E15: 30 | F15: =E15/E20 -> 0.3 | G15: =(E20*F15)/D20 -> 7.5 | H15: =I15/25 -> 27 | I15: =C14*G15 -> 675 | J15: =G15*$E$3 -> 64.23 | L15: =$E$3*I15 -> 5780.7 | V15: 45261 | W15: 45282 | X15: 40549.25 | Y15: 60 | Z15: =X15/Y15 -> 675.82083 | AA15: 44934 | AB15: 38320.72 | AC15: 60 | AD15: =AB15/AC15 -> 638.67867 | AH15: =AF15/AG15 -> #DIV/0! | AL15: =AJ15/AK15 -> #DIV/0! | AM15: =(X15+AB15+AF15+AJ15)/(Y15+AC15+AG15+AK15) -> 657.24975 | AN15: 45261 | AO15: =1- ($AO$2/AM15) -> -0.36934248 | AP15: =$AP$2+($AP$2*AO15) -> 548.67205
D16: FIBRA | E16: 20 | F16: =E16/E20 -> 0.2 | G16: =(E20*F16)/D20 -> 5 | H16: =I16/20 -> 22.5 | I16: =C14*G16 -> 450 | J16: =G16*$E$4 -> 75.15 | L16: =I16*$E$4 -> 6763.5 | V16: 45292 | W16: 44957 | X16: 37679.69 | Y16: 60 | Z16: =X16/Y16 -> 627.99483 | AD16: =AB16/AC16 -> #DIV/0! | AH16: =AF16/AG16 -> #DIV/0! | AL16: =AJ16/AK16 -> #DIV/0! | AM16: =(X16+AB16+AF16+AJ16)/(Y16+AC16+AG16+AK16) -> 627.99483 | AN16: 45292 | AO16: =1- ($AO$2/AM16) -> -0.43313281 | AP16: =$AP$2+($AP$2*AO16) -> 493.17446
D17: EMBALAGEM | E17: 1 | G17: 1 | H17: =I17/1 -> 90 | I17: =G17*$C$14 -> 90 | J17: =G17*$E$6 -> 8.1 | L17: =I17*$E$6 -> 729 | AM17: =AVERAGE(AM3:AM16) -> 758.49272
D18: ADESIVO | E18: 1 | G18: 1 | H18: =I18/1 -> 90 | I18: =G18*$C$14 -> 90 | J18: =G18*$E$7 -> 1.5 | L18: =I18*$E$7 -> 135
D19: ??? | E19: 1 | G19: 1 | H19: =I19/1 -> 90 | I19: =G19*$C$14 -> 90 | J19: =G19*$E$8 -> 0 | L19: =I19*$E$8 -> 0
C20: TOTAL | D20: =E20/25 -> 4 | E20: =SUM(E14:E16) -> 100 | F20: =SUM(F14:F16) -> 1 | G20: =SUM(G14:G16) -> 25 | I20: =SUM(I14:I16) -> 2250 | J20: =SUM(J14:J19) -> 495.48 | L20: =SUM(L14:L19) -> 44593.2 | V20: 44896 | W20: 883.21643
I21: Imposto A2 2% | J21: =J20*2% -> 9.9096 | V21: 44927 | W21: 873.53143
I22: Custo Total | J22: =J20+J21 -> 505.3896 | V22: 44958 | W22: 831.31286
V23: 44986 | W23: 823.25438
V24: 45017 | W24: 840.65375
B25: PRODUÇÃO | V25: 45047 | W25: 775.44845
B26: POLIMERO | C26: QTD SACOS | D26: Produtos | E26: QTD | J26: VALOR | V26: 45078 | W26: 762.881
E27: Batida | F27: % | G27: Qtd Unit/ Saco | H27: Qtd Total Scs | I27: Qtd Total Kgs | J27: Custo Saco 15Kg | K27: Custo Kg | L27: Custo Total | V27: 45108 | W27: 735.439
C28: 12 | D28: POLIMERO | E28: 100 | F28: =E28/E32 -> 0.66666667 | G28: =(E32*F28)/D32 -> 16.666667 | H28: =I28/25 -> 8 | I28: =C28*G28 -> 200 | J28: =G28*$E$5 -> 0 | K28: =(J28+J29+J30+J31)/25 -> 2.76 | L28: =$E$5*I28 -> 0 | V28: 45139 | W28: 713.49773
D29: ARAGON | E29: 50 | F29: =E29/E32 -> 0.33333333 | G29: =(E32*F29)/D32 -> 8.3333333 | H29: =I29/25 -> 4 | I29: =C28*G29 -> 100 | J29: =G29*$E$6 -> 67.5 | L29: =$E$6*I29 -> 810 | V29: 45170 | W29: 717.35808
D30: EMBALAGEM | E30: 1 | G30: 1 | H30: =I30/1 -> 12 | I30: =G30*C28 -> 12 | J30: =G30*$E$7 -> 1.5 | L30: =I30*$E$7 -> 18 | V30: 45200 | W30: 677.40667
D31: ADESIVO | E31: 1 | G31: 1 | H31: =I31/1 -> 12 | I31: =G31*C28 -> 12 | J31: =G31*$E$8 -> 0 | L31: =I31*$E$7 -> 18 | V31: 45231 | W31: 699.65367
C32: TOTAL | D32: =E32/25 -> 6 | E32: =SUM(E28:E29) -> 150 | F32: =SUM(F28:F29) -> 1 | G32: =SUM(G28:G29) -> 25 | I32: =SUM(I28:I29) -> 300 | J32: =SUM(J28:J30) -> 69 | L32: =SUM(L28:L30) -> 828 | V32: 45261 | W32: 657.24975
V33: 45292 | W33: 627.99483
V34: MEDIA | W34: 758.49272
E36: PREÇO CECILIA | F36: CUSTO AD | G36: CUSTO TOTAL | H36: SOBRA ADM
E37: 770 | F37: 545 | G37: =F37+200 -> 745 | H37: =800-G37 -> 55 | J37: =(810-E37)/2 -> 20
E38: 780 | F38: 550 | G38: =F38+200 -> 750 | H38: =800-G38 -> 50 | J38: =(810-E38)/2 -> 15
E39: 790 | F39: 555 | G39: =F39+200 -> 755 | H39: =800-G39 -> 45 | J39: =(810-E39)/2 -> 10
E40: 800 | F40: 560 | G40: =F40+200 -> 760 | H40: =800-G40 -> 40 | J40: =(810-E40)/2 -> 5
E41: 810 | F41: 565 | G41: =F41+200 -> 765 | H41: =800-G41 -> 35 | J41: =(810-E41)/2 -> 0
E42: 820 | F42: 570 | G42: =F42+200 -> 770 | H42: =800-G42 -> 30 | J42: =(810-E42)/2 -> -5
E43: 830 | F43: 575 | G43: =F43+200 -> 775 | H43: =800-G43 -> 25 | J43: =(810-E43)/2 -> -10
E44: 840 | F44: 580 | G44: =F44+200 -> 780 | H44: =800-G44 -> 20 | J44: =(810-E44)/2 -> -15
E45: 850 | F45: 585 | G45: =F45+200 -> 785 | H45: =800-G45 -> 15 | J45: =(810-E45)/2 -> -20
D59: MÊS | E59: SOBRA | F59: QTD SCS
D60: 43831 | E60: 0 | F60: 51 | H60: MESES | I60: MEDIA | J60: PM COMPRA | K60: PM SUGERIDO VENDA | L60: CUSTO SACO
D61: 43862 | E61: 0 | F61: 43 | J61: 810 | K61: 800
D62: 43891 | E62: 0 | F62: 42 | H62: 44044 | I62: 815.98011 | J62: 0.0073287492 | K62: 805.863
D63: 43922 | E63: 0 | F63: 65 | H63: 44075 | I63: 831.98662 | J63: 0.026426657 | K63: 821.14133
D64: 43952 | E64: 2300 | F64: 80 | H64: 44105 | I64: 838.28563 | J64: 0.033742228 | K64: 826.99378
D65: 43983 | E65: 7100 | F65: 148 | H65: 44136 | I65: 843.33583 | J65: 0.039528539 | K65: 831.62283
D66: 44013 | E66: 8500 | F66: 164 | H66: 44166 | I66: 809.74113 | J66: -0.0003196922 | K66: 799.74425
D67: 44044 | E67: 5300 | F67: 155 | H67: 44197 | I67: 778.37313 | J67: -0.040632011 | K67: 767.49439 | L67: 537
D68: 44075 | E68: 3100 | F68: 144 | H68: 44228 | I68: 809.04 | J68: -0.0011865915 | K68: 799.05073 | L68: 553
D69: 44105 | E69: 3900 | F69: 149 | H69: 44256 | I69: 815.24625 | J69: 0.0064351722 | K69: 805.14814 | L69: 555
D70: 44136 | E70: 2400 | F70: 120 | H70: 44287 | I70: 827.20875 | J70: 0.020803395 | K70: 816.64272 | L70: 561
D71: 44166 | E71: 3500 | F71: 120 | H71: 44317 | I71: 849.53375 | J71: 0.04653582 | K71: 837.22866 | L71: 573
D72: TOTAL | E72: =SUM(E60:E71) -> 36100 | F72: 107 | H72: 44348 | I72: 785.91083 | J72: -0.030651272 | K72: 775.47898 | L72: 540
H73: 44378 | I73: 757.37917 | J73: -0.069477529 | K73: 744.41798 | L73: 526
H74: 44409 | I74: 769.028 | J74: -0.053277644 | K74: 757.37788 | L74: 545
D75: MÊS | E75: SOBRA | F75: QTD SCS | H75: 44440 | I75: 798.13 | J75: -0.014872264 | K75: 788.10219 | L75: 560
D76: 44197 | E76: 3000 | F76: 100 | H76: 44470 | I76: 811.009 | J76: 0.0012441292 | K76: 800.9953 | L76: 567
D77: 44228 | E77: 600 | F77: 75 | H77: 44501 | I77: 838.50167 | J77: 0.033991187 | K77: 827.19295 | L77: 580
D78: 44256 | E78: 800 | F78: 80 | H78: 44531 | I78: 861.94111 | J78: 0.060260626 | K78: 848.2085 | L78: 593
D79: 44287 | E79: 0 | F79: 75 | H79: MEDIA | I79: =AVERAGE(I62:I78) -> 814.15476
D80: 44317 | E80: 0 | F80: 90
D81: 44348 | E81: 0 | F81: 105 | H81: 44562 | I81: 960 | J81: 0.156 | K81: 925 | L81: 625
D82: 44378 | E82: 0 | F82: 120
D83: 44409 | E83: 500 | F83: 120
D84: 44440 | E84: 500 | F84: 120
D85: 44470 | E85: 0 | F85: 125
D86: 44501 | E86: 0 | F86: 120
D87: 44531 | E87: 0 | F87: 140
D88: TOTAL | E88: =SUM(E76:E87) -> 5400 | F88: 106

Sheet Entrada de materiais
A1: Entrada
C3: TOTAL | D3: Mês anterior | E3: 43831 | F3: 43862 | G3: 43891 | H3: 43922 | I3: 43952 | J3: 43983 | K3: 44013 | L3: 44044 | M3: 44075 | N3: 44105 | O3: 44136 | P3: 44166
A4: PRODUTO ACABADO
A5: CELULOSICO 25kg | B5: UN | C5: =SUM(E5:AF5) -> 2180 | E5: 140 | F5: 140 | G5: 160 | H5: 140 | I5: 160 | J5: 180 | K5: 200 | L5: 220 | M5: 240 | N5: 240 | O5: 120 | P5: 240
A6: POLIMERO 25kg | B6: UN | C6: =SUM(E6:AF6) -> 0
C7: =SUM(E7:AF7) -> 0
C9: TOTAL | D9: Mês anterior | E9: 43831 | F9: 43862 | G9: 43891 | H9: 43922 | I9: 43952 | J9: 43983 | K9: 44013 | L9: 44044 | M9: 44075 | N9: 44105 | O9: 44136 | P9: 44166
A10: MATÉRIA-PRIMA
A11: Celulosico (MP) 25kg | B11: KG | C11: =SUM(D11:AI11) -> 27250 | E11: 1750 | F11: 1750 | G11: 2000 | H11: 1750 | I11: 2000 | J11: 2250 | K11: 2500 | L11: 2750 | M11: 3000 | N11: 3000 | O11: 1500 | P11: 3000
A12: Celugel 25kg | B12: KG | C12: =SUM(D12:AI12) -> 18150 | D12: 3000 | G12: 2100 | I12: 1950 | J12: 2250 | L12: 2250 | M12: 1950 | N12: 1950 | P12: 2700
A13: Fibra 20kg | B13: KG | C13: =SUM(D13:AI13) -> 12100 | D13: 2000 | G13: 1400 | I13: 1300 | J13: 1500 | L13: 1500 | M13: 1300 | N13: 1300 | P13: 1800
A14: Polimero (MP) 25kg | B14: KG | C14: =SUM(D14:AI14) -> 0
A15: Aragon 25kg | B15: KG | C15: =SUM(D15:AI15) -> 0
A16: Embalagem | B16: KG | C16: =SUM(D16:AI16) -> 2460 | D16: 410 | G16: 300 | I16: 300 | J16: 300 | L16: 300 | M16: 250 | N16: 250 | P16: 350
A17: Adesivo | C17: =SUM(D17:AI17) -> 2460 | D17: 420 | G17: 300 | I17: 300 | J17: 300 | L17: 300 | M17: 180 | N17: 310 | P17: 350

Sheet Saída de materiais
A1: Saída
C3: TOTAL | D3: 43831 | E3: 43862 | F3: 43891 | G3: 43922 | H3: 43952 | I3: 43983 | J3: 44013 | K3: 44044 | L3: 44075 | M3: 44105 | N3: 44136 | O3: 44166
A4: PRODUTO ACABADO
A5: CELULOSICO 25kg | B5: UN | C5: =SUM(D5:AH5) -> 2100 | D5: 140 | E5: 120 | F5: 149 | G5: 121 | H5: 183 | I5: 182 | J5: 222 | K5: 243 | L5: 153 | M5: 201 | N5: 196 | O5: 190
A6: POLIMERO 25kg | B6: UN | C6: =SUM(D6:AH6) -> 0
C7: =SUM(D7:AH7) -> 0
C8: =SUM(D8:AF8) -> 0
A10: MATÉRIA-PRIMA | C10: TOTAL | D10: 43831 | E10: 43862 | F10: 43891 | G10: 43922 | H10: 43952 | I10: 43983 | J10: 44013 | K10: 44044 | L10: 44075 | M10: 44105 | N10: 44136 | O10: 44166
A11: Celulosico (MP) 25kg | B11: SC | C11: =SUM(D11:AH11) -> 27250 | D11: =('Entrada de materiais'!E5*'Custo Prod.'!$G$14) -> 1750 | E11: =('Entrada de materiais'!F5*'Custo Prod.'!$G$14) -> 1750 | F11: =('Entrada de materiais'!G5*'Custo Prod.'!$G$14) -> 2000 | G11: =('Entrada de materiais'!H5*'Custo Prod.'!$G$14) -> 1750 | H11: =('Entrada de materiais'!I5*'Custo Prod.'!$G$14) -> 2000 | I11: =('Entrada de materiais'!J5*'Custo Prod.'!$G$14) -> 2250 | J11: =('Entrada de materiais'!K5*'Custo Prod.'!$G$14) -> 2500 | K11: =('Entrada de materiais'!L5*'Custo Prod.'!$G$14) -> 2750 | ... AH11: =('Entrada de materiais'!AI5*'Custo Prod.'!$G$14) -> 0
A12: Celugel 25kg | B12: SC | C12: =SUM(D12:AH12) -> 16350 | D12: =('Entrada de materiais'!E5*'Custo Prod.'!$G$15) -> 1050 | E12: =('Entrada de materiais'!F5*'Custo Prod.'!$G$15) -> 1050 | F12: =('Entrada de materiais'!G5*'Custo Prod.'!$G$15) -> 1200 | G12: =('Entrada de materiais'!H5*'Custo Prod.'!$G$15) -> 1050 | H12: =('Entrada de materiais'!I5*'Custo Prod.'!$G$15) -> 1200 | I12: =('Entrada de materiais'!J5*'Custo Prod.'!$G$15) -> 1350 | J12: =('Entrada de materiais'!K5*'Custo Prod.'!$G$15) -> 1500 | K12: =('Entrada de materiais'!L5*'Custo Prod.'!$G$15) -> 1650 | ... AH12: =('Entrada de materiais'!AI5*'Custo Prod.'!$G$15) -> 0
A13: Fibra 20kg | B13: SC | C13: =SUM(D13:AH13) -> 10900 | D13: =('Entrada de materiais'!E5*'Custo Prod.'!$G$16) -> 700 | E13: =('Entrada de materiais'!F5*'Custo Prod.'!$G$16) -> 700 | F13: =('Entrada de materiais'!G5*'Custo Prod.'!$G$16) -> 800 | G13: =('Entrada de materiais'!H5*'Custo Prod.'!$G$16) -> 700 | H13: =('Entrada de materiais'!I5*'Custo Prod.'!$G$16) -> 800 | I13: =('Entrada de materiais'!J5*'Custo Prod.'!$G$16) -> 900 | J13: =('Entrada de materiais'!K5*'Custo Prod.'!$G$16) -> 1000 | K13: =('Entrada de materiais'!L5*'Custo Prod.'!$G$16) -> 1100 | ... AH13: =('Entrada de materiais'!AI5*'Custo Prod.'!$G$16) -> 0
A14: Polimero (MP) 25kg | B14: SC | C14: =SUM(D14:AH14) -> 0 | D14: =('Entrada de materiais'!E6*'Custo Prod.'!$G$28) -> 0 | E14: =('Entrada de materiais'!F6*'Custo Prod.'!$G$28) -> 0 | F14: =('Entrada de materiais'!G6*'Custo Prod.'!$G$28) -> 0 | G14: =('Entrada de materiais'!H6*'Custo Prod.'!$G$28) -> 0 | H14: =('Entrada de materiais'!I6*'Custo Prod.'!$G$28) -> 0 | I14: =('Entrada de materiais'!J6*'Custo Prod.'!$G$28) -> 0 | J14: =('Entrada de materiais'!K6*'Custo Prod.'!$G$28) -> 0 | K14: =('Entrada de materiais'!L6*'Custo Prod.'!$G$28) -> 0 | ... AH14: =('Entrada de materiais'!AI6*'Custo Prod.'!$G$28) -> 0
A15: Aragon 25kg | B15: SC | C15: =SUM(D15:AH15) -> 0 | D15: =('Entrada de materiais'!E6*'Custo Prod.'!$G$29) -> 0 | E15: =('Entrada de materiais'!F6*'Custo Prod.'!$G$29) -> 0 | F15: =('Entrada de materiais'!G6*'Custo Prod.'!$G$29) -> 0 | G15: =('Entrada de materiais'!H6*'Custo Prod.'!$G$29) -> 0 | H15: =('Entrada de materiais'!I6*'Custo Prod.'!$G$29) -> 0 | I15: =('Entrada de materiais'!J6*'Custo Prod.'!$G$29) -> 0 | J15: =('Entrada de materiais'!K6*'Custo Prod.'!$G$29) -> 0 | K15: =('Entrada de materiais'!L6*'Custo Prod.'!$G$29) -> 0 | ... AH15: =('Entrada de materiais'!AI6*'Custo Prod.'!$G$29) -> 0
A16: Embalagem | B16: UN | C16: =SUM(D16:AH16) -> 2180 | D16: =('Entrada de materiais'!E5*'Custo Prod.'!$G$17)+('Entrada de materiais'!E6*'Custo Prod.'!$G$30) -> 140 | E16: =('Entrada de materiais'!F5*'Custo Prod.'!$G$17)+('Entrada de materiais'!F6*'Custo Prod.'!$G$30) -> 140 | F16: =('Entrada de materiais'!G5*'Custo Prod.'!$G$17)+('Entrada de materiais'!G6*'Custo Prod.'!$G$30) -> 160 | G16: =('Entrada de materiais'!H5*'Custo Prod.'!$G$17)+('Entrada de materiais'!H6*'Custo Prod.'!$G$30) -> 140 | H16: =('Entrada de materiais'!I5*'Custo Prod.'!$G$17)+('Entrada de materiais'!I6*'Custo Prod.'!$G$30) -> 160 | I16: =('Entrada de materiais'!J5*'Custo Prod.'!$G$17)+('Entrada de materiais'!J6*'Custo Prod.'!$G$30) -> 180 | J16: =('Entrada de materiais'!K5*'Custo Prod.'!$G$17)+('Entrada de materiais'!K6*'Custo Prod.'!$G$30) -> 200 | K16: =('Entrada de materiais'!L5*'Custo Prod.'!$G$17)+('Entrada de materiais'!L6*'Custo Prod.'!$G$30) -> 220 | ... AH16: =('Entrada de materiais'!AI5*'Custo Prod.'!$G$17)+('Entrada de materiais'!AI6*'Custo Prod.'!$G$30) -> 0
A17: Adesivo | B17: UN | C17: =SUM(D17:AH17) -> 2180 | D17: =('Entrada de materiais'!E5*'Custo Prod.'!$G$19)+('Entrada de materiais'!E6*'Custo Prod.'!$G$31) -> 140 | E17: =('Entrada de materiais'!F5*'Custo Prod.'!$G$19)+('Entrada de materiais'!F6*'Custo Prod.'!$G$31) -> 140 | F17: =('Entrada de materiais'!G5*'Custo Prod.'!$G$19)+('Entrada de materiais'!G6*'Custo Prod.'!$G$31) -> 160 | G17: =('Entrada de materiais'!H5*'Custo Prod.'!$G$19)+('Entrada de materiais'!H6*'Custo Prod.'!$G$31) -> 140 | H17: =('Entrada de materiais'!I5*'Custo Prod.'!$G$19)+('Entrada de materiais'!I6*'Custo Prod.'!$G$31) -> 160 | I17: =('Entrada de materiais'!J5*'Custo Prod.'!$G$19)+('Entrada de materiais'!J6*'Custo Prod.'!$G$31) -> 180 | J17: =('Entrada de materiais'!K5*'Custo Prod.'!$G$19)+('Entrada de materiais'!K6*'Custo Prod.'!$G$31) -> 200 | K17: =('Entrada de materiais'!L5*'Custo Prod.'!$G$19)+('Entrada de materiais'!L6*'Custo Prod.'!$G$31) -> 220 | ... AH17: =('Entrada de materiais'!AI5*'Custo Prod.'!$G$19)+('Entrada de materiais'!AI6*'Custo Prod.'!$G$31) -> 0

Sheet Estoque
B1: Controle de estoque | F1: =TODAY() -> 46202
B3: PRODUTOS ACABADOS
B5: Código | C5: Descrição | D5: Unid. | E5: Est Uchoa | F5: Est Conteiner | G5: CUSTO Unit | H5: CUSTO Total | I5: VENDA Unit | J5: VENDA Total
B6: 10 | C6: CELULOSICO 25kg | D6: UN | E6: 10 | F6: =SUM('Entrada de materiais'!D5:AJ5)-SUM('Saída de materiais'!D5:AH5) -> 80 | G6: ='Custo Prod.'!J20 -> 495.48 | H6: =IF(F6>0,SUM(F6*G6)," ") -> 39638.4 | I6: 840 | J6: =SUM((F6+E6)*I6) -> 75600
B7: 20 | C7: POLIMERO 25kg | D7: UN | G7: ='Custo Prod.'!J32 -> 69 | H7: =IF(F7>0,SUM(F7*G7)," ") | I7: 400 | J7: =SUM((F7+E7)*I7) -> 0
H8: =SUM(H6:H7) -> 39638.4 | J8: =SUM(J6:J7) -> 75600
B10: MATÉRIA-PRIMA
B12: Código | C12: Descrição | D12: Unid. | E12: Qtd Sacos | F12: Qtd Kg | G12: Valor Unit. | H12: Valor Total | I12: MP faz "X" Sacos
B13: 130 | C13: Celulosico (MP) 25kg | D13: SACO | E13: =F13/25 -> 0 | F13: =('Entrada de materiais'!C11-'Saída de materiais'!C11) -> 0 | G13: ='Custo Prod.'!D2 -> 693 | H13: =IF(E13>0,SUM(E13*G13)," ") | I13: =F13/12.5 -> 0
B14: 140 | C14: Celugel 25kg | D14: SACO | E14: =F14/25 -> 72 | F14: =('Entrada de materiais'!C12-'Saída de materiais'!C12) -> 1800 | G14: ='Custo Prod.'!D3 -> 214.1 | H14: =IF(E14>0,SUM(E14*G14)," ") -> 15415.2 | I14: =F14/7.5 -> 240
B15: 150 | C15: Fibra 20kg | D15: SACO | E15: =F15/20 -> 60 | F15: =('Entrada de materiais'!C13-'Saída de materiais'!C13) -> 1200 | G15: ='Custo Prod.'!D4 -> 300.6 | H15: =IF(E15>0,SUM(E15*G15)," ") -> 18036 | I15: =F15/5 -> 240
B16: 160 | C16: Polimero (MP) 25kg | D16: SACO | E16: =F16/25 -> 0 | F16: =('Entrada de materiais'!C14-'Saída de materiais'!C14) -> 0 | G16: ='Custo Prod.'!D6 -> 8.1 | H16: =IF(E16>0,SUM(E16*G16)," ")
B17: 170 | C17: Aragon 25kg | D17: SACO | E17: =F17/25 -> 0 | F17: =('Entrada de materiais'!C15-'Saída de materiais'!C15) -> 0 | G17: ='Custo Prod.'!D5 -> 0 | H17: =IF(E17>0,SUM(E17*G17)," ")
B18: 180 | C18: Embalagem | D18: UN | E18: =F18/1 -> 280 | F18: =('Entrada de materiais'!C16-'Saída de materiais'!C16) -> 280 | G18: ='Custo Prod.'!D7 -> 1.5 | H18: =IF(E18>0,SUM(E18*G18)," ") -> 420
B19: 190 | C19: Adesivos | D19: UN | E19: =F19/1 -> 280 | F19: =('Entrada de materiais'!C17-'Saída de materiais'!C17) -> 280 | G19: ='Custo Prod.'!D8 -> 0 | H19: =IF(E19>0,SUM(E19*G19)," ") -> 0
H20: =SUM(H14:H18) -> 33871.2

Sheet Caixa
A1: Resultado | B1: =(B3-B12) -> -2300 | C1: =(C3-C12) -> -11985.51 | D1: =(D3-D12) -> -39105.32 | E1: =(E3-E12) -> 25353.83 | F1: =(F3-F12) -> 18286.72 | G1: =(G3-G12) -> 43270.48 | H1: =(H3-H12) -> -41580.86 | I1: =(I3-I12) -> 33201.06 | ... N1: =(N3-N12) -> 22356.67
A2: MESES | C2: 43831 | D2: 43862 | E2: 43891 | F2: 43922 | G2: 43952 | H2: 43983 | I2: 44013 | J2: 44044 | K2: 44075 | L2: 44105 | M2: 44136 | N2: 44166
A3: Entradas | B3: =SUM(B4:B11) -> 1834560 | C3: =SUM(C4:C11) -> 189580 | D3: =SUM(D4:D11) -> 104150 | E3: =SUM(E4:E11) -> 126290 | F3: =SUM(F4:F11) -> 107660 | G3: =SUM(G4:G11) -> 169030 | H3: =SUM(H4:H11) -> 154510 | I3: =SUM(I4:I11) -> 181620 | ... AF3: =SUM(AF4:AF11) -> 0
A4: SALDO ANO 2021 | B4: =SUM(C4:AF4) -> 82250 | C4: 67650 | G4: 14600
A5: Vendas A Vista | B5: =SUM(C5:AF5) -> 1752310 | C5: ='Vendas - JAN'!G101 -> 121930 | D5: ='Vendas - FEV'!G101 -> 104150 | E5: ='Vendas - MAR'!G101 -> 126290 | F5: ='Vendas - ABR'!G101 -> 107660 | G5: ='Vendas - MAI'!G101 -> 154430 | H5: ='Vendas - JUN'!G101 -> 154510 | I5: ='Vendas - JUL'!G101 -> 181620 | J5: ='Vendas - AGO'!G101 -> 202040 | K5: ='Vendas - SET'!G101 -> 123550 | L5: ='Vendas - OUT'!G101 -> 156160 | M5: ='Vendas - NOV'!G101 -> 172610 | N5: ='Vendas - DEZ'!G101 -> 147360
A6: Saco Extra | B6: =SUM(C6:AF6) -> 0
A7: Capital | B7: =SUM(C7:AF7) -> 0
A8: Emprestimo | B8: =SUM(C8:AF8) -> 0
B9: =SUM(C9:AF9) -> 0
B10: =SUM(C10:AF10) -> 0
B11: =SUM(C11:AF11) -> 0
A12: Saidas | B12: =SUM(C12:AF12) -> 1836860 | C12: =SUM(C13+C47,C78+C62+C56+C74+C110) -> 201565.51 | D12: =SUM(,D47,D78+D62+D13+D56+D74+D110) -> 143255.32 | E12: =SUM(,E47,E78+E62+E13+E56+E74+E110) -> 100936.17 | F12: =SUM(,F47,F78+F62+F13+F56+F74+F110) -> 89373.28 | G12: =SUM(,G47,G78+G62+G13+G56+G74+G110) -> 125759.52 | H12: =SUM(,H47,H78+H62+H13+H56+H74+H110) -> 196090.86 | I12: =SUM(,I47,I78+I62+I13+I56+I74+I110) -> 148418.94 | J12: =SUM(,J47,J78+J62+J13+J56+J74+J110) -> 166561.02 | K12: =SUM(,K47,K78+K62+K13+K56+K74+K110) -> 168969.44 | ... AF12: =SUM(,AF47,AF78+AF62+AF13+AF56+AF74+AF110) -> 0
A13: Caixa | B13: =SUM(C13:AF13) -> 92703.32 | C13: =SUM(C14:C46) -> 42868.73 | D13: =SUM(D14:D46) -> 10822.5 | E13: =SUM(E14:E46) -> -5810 | F13: =SUM(F14:F46) -> 3850 | G13: =SUM(G14:G46) -> 1400 | H13: =SUM(H14:H46) -> 2000 | I13: =SUM(I14:I46) -> -4460 | J13: =SUM(J14:J46) -> 150 | ... AF13: =SUM(AF14:AF46) -> 0
A14: BB Rodrigo | B14: =SUM(C14:AF14) -> 496.29 | N14: 496.29
A15: Uchoa | B15: =SUM(C15:AF15) -> 0
A16: Dinheiro | B16: =SUM(C16:AF16) -> 910 | M16: 710 | N16: 200
A17: Paloma | B17: =SUM(C17:AF17) -> 17540 | M17: 10270 | N17: 7270
A18: Tio Fernando | B18: =SUM(C18:AF18) -> -1000 | N18: -16000 | O18: 15000
B19: =SUM(C19:AF19) -> 0
A20: Marcilio, Odilanio, Mustang Rod, Mustang Roberto, Marcio, Luis nubank, taxi Paloma, taxi Leilane, Fernadinho, Juarez, Obra, Ferradura e racao, Baxin, Feira | B20: =SUM(C20:AF20) -> 33455.99 | C20: 1030.19 | D20: 800 | E20: 2000 | F20: 3000 | G20: 1000 | H20: 1000 | I20: 540 | J20: 150 | K20: 1000 | L20: 5500 | M20: 6020.8 | N20: 550 | O20: 10000 | P20: 865
A21: Arkad, Cred Diversos, Combustivel | B21: =SUM(C21:AF21) -> -3550 | C21: -410 | D21: -3010 | E21: -130
A22: Gastos, Cha, Jacinta, Juros junior, Doação, Geladeira, salario | B22: =SUM(C22:AF22) -> 4485 | C22: 4735 | D22: 1500 | E22: 1000 | F22: 850 | G22: 400 | H22: 1000 | I22: -5000
A23: Lilian Matricula | B23: =SUM(C23:AF23) -> 88.21 | C23: 88.21
A24: rodrigo | B24: =SUM(C24:AF24) -> -36000 | C24: -36000
A25: cartao porto | B25: =SUM(C25:AF25) -> 10785.33 | C25: 10785.33
B26: =SUM(C26:AF26) -> 0
B27: =SUM(C27:AF27) -> 2.5 | D27: 2.5
A28: ??? | B28: =SUM(C28:AF28) -> 800 | C28: 800
A29: FELIPE | B29: =SUM(C29:AF29) -> 850 | C29: 850
A30: IRINEU | B30: =SUM(C30:AF30) -> 850 | C30: 850
A31: JULIO | B31: =SUM(C31:AF31) -> 4500 | C31: 4500
A32: FORTMASSA | B32: =SUM(C32:AF32) -> 1700 | C32: 850 | D32: 850
A33: GETULIO | B33: =SUM(C33:AF33) -> 2550 | C33: 2550
B34: =SUM(C34:AF34) -> 0
A35: CLAUDIO MOSSORO | B35: =SUM(C35:AF35) -> 6640 | C35: 3320 | E35: 3320
A36: LOURIMAR | B36: =SUM(C36:AF36) -> 3360 | C36: 3360
A37: CHICO PEREIRA | B37: =SUM(C37:AF37) -> 1640 | C37: 1640
A38: MULTCOLA | B38: =SUM(C38:AF38) -> 1600 | C38: 1600
A39: TODA OBRA | B39: =SUM(C39:AF39) -> 9840 | C39: 9840
A40: DEMETRIU | B40: =SUM(C40:AF40) -> 6360 | C40: 4680 | D40: 1680
A41: AREMIX | B41: =SUM(C41:AF41) -> 1200 | C41: 1200
B42: =SUM(C42:AF42) -> 0
A43: marcel vale do juquia | B43: =SUM(C43:AF43) -> 14600 | C43: 14600
A44: 13° uchoa | B44: =SUM(C44:AF44) -> 9000 | C44: 12000 | D44: 9000 | E44: -12000
B45: =SUM(C45:AF45) -> 0
A46: EMBALAGEM | B46: =SUM(C46:AF46) -> 0
A47: Vale do Juquia | B47: =SUM(C47:AF47) -> 339396.78 | C47: =SUM(C48:C55) -> 56740 | D47: =SUM(D48:D55) -> 37893.62 | E47: =SUM(E48:E55) -> 0 | F47: =SUM(F48:F55) -> 14600 | G47: =SUM(G48:G55) -> 22094.26 | H47: =SUM(H48:H55) -> 41372.24 | I47: =SUM(I48:I55) -> 19684.4 | J47: =SUM(J48:J55) -> 22540.61 | ... AF47: =SUM(AF48:AF55) -> 0
A48: Vale do Juquia 1 | B48: =SUM(C48:AF48) -> 131352.5 | C48: 20940 | D48: 14600 | F48: 14600 | H48: 16060 | I48: 16790 | K48: 14600 | L48: 14600 | M48: 19162.5
A49: Frete 1 | B49: =SUM(C49:AF49) -> 22835.04 | C49: 3600 | D49: 2526.1 | G49: 2526.1 | H49: 2771.63 | I49: 2894.4 | K49: 2576.83 | L49: 2576.83 | M49: 3363.15
A50: Flukocel Jonas | B50: =SUM(C50:AF50) -> 163821 | C50: 26900 | D50: 18561 | G50: 17485 | H50: 20175 | J50: 20175 | K50: 17485 | L50: 17485 | M50: 25555
A51: Frete 2 | B51: =SUM(C51:AF51) -> 19088.24 | C51: 3000 | D51: 2206.52 | G51: 2083.16 | H51: 2365.61 | J51: 2365.61 | K51: 2078.95 | L51: 2078.95 | M51: 2909.44
A52: Vale do Juquia 3 PREZUIZO | B52: =SUM(C52:AF52) -> 2300 | C52: 2300
A53: Frete 3 | B53: =SUM(C53:AF53) -> 0
B54: =SUM(C54:AF54) -> 0
B55: =SUM(C55:AF55) -> 0
A56: Vipel | B56: =SUM(C56:AF56) -> 22156.3 | C56: =SUM(C57:C61) -> 3720 | D56: =SUM(D57:D61) -> 2130 | E56: =SUM(E57:E61) -> 572.04 | F56: =SUM(F57:F61) -> 2130 | G56: =SUM(G57:G61) -> 572.04 | H56: =SUM(H57:H61) -> 2758.06 | I56: =SUM(I57:I61) -> 2100 | J56: =SUM(J57:J61) -> 572.04 | ... AF56: =SUM(AF57:AF61) -> 0
A57: Embalagem | B57: =SUM(C57:AF57) -> 17530 | C57: 3120 | D57: 2130 | F57: 2130 | H57: 2100 | I57: 2100 | K57: 1750 | L57: 1750 | M57: 2450
A58: Frete | B58: =SUM(C58:AF58) -> 1290.3 | E58: 172.04 | G58: 172.04 | H58: 258.06 | J58: 172.04 | K58: 172.04 | L58: 172.04 | M58: 172.04
A59: Adesivos | B59: =SUM(C59:AF59) -> 3336 | C59: 600 | E59: 400 | G59: 400 | H59: 400 | J59: 400 | K59: 240 | L59: 416 | N59: 480
B60: =SUM(C60:AF60) -> 0
B61: =SUM(C61:AF61) -> 0
A62: Aditivos | B62: =SUM(C62:AF62) -> 851080.34 | C62: =SUM(C63:C73) -> 63596.78 | D62: =SUM(D63:D73) -> 60619.2 | E62: =SUM(E63:E73) -> 68614.13 | F62: =SUM(F63:F73) -> 35008.28 | G62: =SUM(G63:G73) -> 57263.02 | H62: =SUM(H63:H73) -> 103499.72 | I62: =SUM(I63:I73) -> 76946.83 | J62: =SUM(J63:J73) -> 82140.01 | ... AF62: =SUM(AF63:AF73) -> 0
A63: Mc Quimica 1 | B63: =SUM(C63:AF63) -> 420802.61 | C63: 35166.9 | D63: 33332.55 | E63: 32911.9 | F63: 33626.15 | G63: 24051.8 | H63: 30438.65 | I63: 29445.2 | J63: 36774.25 | K63: 43032.66 | L63: 40644.4 | M63: 40828.9 | N63: 40549.25
A64: Frete 1 | B64: =SUM(C64:AF64) -> 18856.64 | C64: 1393.72 | D64: 1379.92 | E64: 1376.75 | F64: 1382.13 | G64: 1041.25 | H64: 1358.14 | I64: 1350.67 | J64: 1674.65 | K64: 1990.57 | L64: 1972.59 | M64: 1973.98 | N64: 1962.27
A65: Mc Quimica 2 | B65: =SUM(C65:AF65) -> 326625.73 | C65: 25980.4 | D65: 24859.4 | E65: 32948.45 | G65: 30809.03 | H65: 38483.65 | I65: 7333.65 | J65: 41710.5 | K65: 43050.35 | L65: 43129.5 | N65: 38320.8
A66: Frete 2 | B66: =SUM(C66:AF66) -> 14824.07 | C66: 1055.76 | D66: 1047.33 | E66: 1377.03 | G66: 1360.94 | H66: 1687.52 | I66: 377.78 | J66: 1980.61 | K66: 1990.7 | L66: 1991.3 | N66: 1955.1
A67: Mc Quimica 3 | B67: =SUM(C67:AF67) -> 66940.55 | H67: 30175.6 | I67: 36764.95
A68: Frete 3 | B68: =SUM(C68:AF68) -> 3030.74 | H68: 1356.16 | I68: 1674.58
A69: Mc Quimica 4 | B69: =SUM(C69:AF69) -> 0
A70: Frete 4 | B70: =SUM(C70:AF70) -> 0
A71: Mc Quimica 5 | B71: =SUM(C71:AF71) -> 0
A72: Frete 5 | B72: =SUM(C72:AF72) -> 0
A73: Quantiq | B73: =SUM(C73:AF73) -> 0
A74: Retiradas | B74: =SUM(C74:AF74) -> 418000 | C74: =SUM(C75:C77) -> 28000 | D74: =SUM(D75:D77) -> 24000 | E74: =SUM(E75:E77) -> 29000 | F74: =SUM(F75:F77) -> 25000 | G74: =SUM(G75:G77) -> 36000 | H74: =SUM(H75:H77) -> 37000 | I74: =SUM(I75:I77) -> 44000 | J74: =SUM(J75:J77) -> 49000 | ... AF74: =SUM(AF75:AF77) -> 0
A75: Joao Uchoa | B75: =SUM(C75:AF75) -> 209000 | C75: 14000 | D75: 12000 | E75: 14500 | F75: 12500 | G75: 18000 | H75: 18500 | I75: 22000 | J75: 24500 | K75: 15000 | L75: 19000 | M75: 21000 | N75: 18000
A76: Paloma Eugenio | B76: =SUM(C76:AF76) -> 209000 | C76: 14000 | D76: 12000 | E76: 14500 | F76: 12500 | G76: 18000 | H76: 18500 | I76: 22000 | J76: 24500 | K76: 15000 | L76: 19000 | M76: 21000 | N76: 18000
B77: =SUM(C77:AF77) -> 0
A78: Despesa | B78: =SUM(C78:AF78) -> 95172.2 | C78: =SUM(C79:C109) -> 6640 | D78: =SUM(D79:D109) -> 7790 | E78: =SUM(E79:E109) -> 8560 | F78: =SUM(F79:F109) -> 6935 | G78: =SUM(G79:G109) -> 6997.2 | H78: =SUM(H79:H109) -> 7150 | I78: =SUM(I79:I109) -> 7720 | J78: =SUM(J79:J109) -> 8710 | ... AF78: =SUM(AF79:AF109) -> 0
A79: Diversos | B79: =SUM(C79:AF79) -> 417.75 | C79: 38.7 | D79: 26.5 | E79: 22.62 | F79: 33.95 | G79: 66.34 | H79: 17.84 | I79: 44.5 | J79: 32.23 | K79: 27.03 | L79: 38.51 | M79: 9.09 | N79: 60.44
A80: Tarifa Bancaria | B80: =SUM(C80:AF80) -> 34.8 | C80: 34.8
A81: Mecon | B81: =SUM(C81:AF81) -> 13498.59 | C81: 860.07 | D81: 829.8 | E81: 758.48 | F81: 552.09 | G81: 935.14 | H81: 1001.23 | I81: 926.08 | J81: 1186.6 | K81: 1432.22 | L81: 2111.41 | M81: 1198.21 | N81: 1707.26
A82: A2 | B82: =SUM(C82:AF82) -> 0
A83: Quimicon | B83: =SUM(C83:AF83) -> 1980 | F83: 380 | G83: 200 | H83: 200 | I83: 200 | J83: 200 | K83: 200 | L83: 200 | M83: 200 | N83: 200
A84: Funcionario | B84: =SUM(C84:AF84) -> 8560 | C84: 480 | D84: 610 | E84: 460 | F84: 460 | G84: 530 | H84: 710 | I84: 700 | J84: 740 | K84: 900 | L84: 900 | M84: 770 | N84: 1300
A85: Aplicação | B85: =SUM(C85:AF85) -> 0
A86: Uber / Gasolina / Frete | B86: =SUM(C86:AF86) -> 1476 | D86: 136 | F86: 50 | H86: 20 | J86: 700 | K86: 80 | M86: 150 | N86: 340
A87: Previ Antigo 5x1000 | B87: =SUM(C87:AF87) -> 5900 | C87: 1200 | D87: 1200 | E87: 1200 | F87: 1200 | G87: 1100
A88: Previ Novo 36x 2180 (term 05/26) | B88: =SUM(C88:AF88) -> 7350 | H88: 1050 | I88: 1050 | J88: 1050 | K88: 1050 | L88: 1050 | M88: 1050 | N88: 1050
A89: Jardins do Lago Max 15/60 | B89: =SUM(C89:AF89) -> 13847.22 | C89: 1133.99 | D89: 1133.99 | E89: 1204.13 | F89: 1133.99 | G89: 1133.99 | H89: 1133.99 | I89: 1133.99 | J89: 1133.99 | K89: 1133.99 | L89: 1190.39 | M89: 1190.39 | N89: 1190.39
A90: Material Escritorio | B90: =SUM(C90:AF90) -> 1796.9 | E90: 216.9 | F90: 300 | G90: 300 | H90: 300 | I90: 380 | J90: 300
A91: Impostos Mecon d 20 | B91: =SUM(C91:AF91) -> 2660.01 | C91: 99 | D91: 225.01 | E91: 619.1 | F91: 135 | G91: 144 | H91: 185.85 | I91: 147.92 | J91: 203.67 | K91: 167.93 | L91: 185.85 | M91: 165.47 | N91: 381.21
A92: Parcelamento Simples 1/26 d30 | B92: =SUM(C92:AF92) -> 4119.03 | C92: 325.34 | D92: 328.7 | E92: 334.97 | F92: 334.97 | G92: 337.73 | H92: 341.09 | I92: 347.51 | J92: 347.51 | K92: 350.93 | L92: 353.84 | M92: 356.84 | N92: 359.6
A93: Agrados | B93: =SUM(C93:AF93) -> 3087.8 | E93: 143.8 | J93: 200 | K93: 82.9 | M93: 100 | N93: 2561.1
A94: Serviços Extras | B94: =SUM(C94:AF94) -> 1663.1 | C94: 468.1 | D94: 240 | E94: 85 | F94: 80 | H94: 40 | I94: 420 | J94: 100 | K94: 140 | L94: 90
A95: Prejuizos | B95: =SUM(C95:AF95) -> 800 | J95: 200 | K95: 540 | N95: 60
A96: Viagens | B96: =SUM(C96:AF96) -> 3130 | D96: 1000 | E96: 1495 | F96: 255 | G96: 250 | H96: 130
B97: =SUM(C97:AF97) -> 0
A98: Retirada Paloma | B98: =SUM(C98:AF98) -> 425.5 | D98: 30 | E98: 10 | F98: 10 | H98: 10 | I98: 185 | J98: 158 | K98: 22.5
A99: Retirada Uchoa | B99: =SUM(C99:AF99) -> 425.5 | D99: 30 | E99: 10 | F99: 10 | H99: 10 | I99: 185 | J99: 158 | K99: 22.5
B100: =SUM(C100:AF100) -> 0
...

Sheet Vendas - JAN
A1: VENDAS | B1: VENDAS | D1: =D102 -> 140
A2: DATA | B2: VENDEDOR | C2: Clientes | D2: CELULOSE | H2: POLÍMERO | K2: DESCONTO CHEQUE | L2: TOTAL | M2: PARCIAL | N2: DEVENDO | O2: CHEQUES / PAGAMENTOS A MAIS OU A MENOS | T2: Forma de Pagamento | U2: Prazo | V2: Frete CIF / FOB | W2: OBSERVAÇÃO | X2: OBSERVAÇÃO
D3: PALOMA | E3: UCHOA | F3: PREÇO | G3: TOTAL | H3: QTD | I3: PREÇO TAB | J3: TOTAL | O3: VALOR VENDA | P3: COBRAMOS % | Q3: PAGAMOS % | R3: SALDO/DEBITO CLIENTE | S3: LUCRO/PREJ JUROS
A4: 44930 | C4: CHICO PEREIRA | E4: 2 | F4: 880 | G4: =(F4*D4)+(E4*F4) -> 1760 | J4: =H4*I4 -> 0 | L4: =(J4+G4)-K4 -> 1760 | N4: =IF(M4>0,SUM(L4-M4)," ") | R4: =IF(O4>0,SUM(O4-(L4+P4))," ") | T4: A VISTA | U4: 0 | V4: FOB
A5: 44930 | C5: LUIZ PI | E5: 2 | F5: 880 | G5: =(F5*D5)+(E5*F5) -> 1760 | J5: =H5*I5 -> 0 | L5: =(J5+G5)-K5 -> 1760 | N5: =IF(M5>0,SUM(L5-M5)," ") | R5: =IF(O5>0,SUM(O5-(L5+P5))," ") | T5: A VISTA | U5: 0 | V5: FOB
A6: 44930 | C6: GETULIO | E6: 2 | F6: 880 | G6: =(F6*D6)+(E6*F6) -> 1760 | J6: =H6*I6 -> 0 | L6: =(J6+G6)-K6 -> 1760 | N6: =IF(M6>0,SUM(L6-M6)," ") | R6: =IF(O6>0,SUM(O6-(L6+P6))," ") | T6: A VISTA | U6: 0 | V6: FOB
A7: 44930 | C7: TOPMASSA | E7: 1 | F7: 900 | G7: =(F7*D7)+(E7*F7) -> 900 | J7: =H7*I7 -> 0 | L7: =(J7+G7)-K7 -> 900 | N7: =IF(M7>0,SUM(L7-M7)," ") | R7: =IF(O7>0,SUM(O7-(L7+P7))," ") | T7: A VISTA | U7: 0 | V7: FOB
A8: 44931 | C8: MULTCOLA | E8: 3 | F8: 860 | G8: =(F8*D8)+(E8*F8) -> 2580 | J8: =H8*I8 -> 0 | L8: =(J8+G8)-K8 -> 2580 | N8: =IF(M8>0,SUM(L8-M8)," ") | O8: 1400 | R8: =IF(O8>0,SUM(O8-(L8+P8))," ") -> -1180 | T8: CHEQUE/R$ | U8: 0 | V8: FOB | W8: 1100 + 300 | Y8: VALOR | Z8: QTD | AA8: =G101 -> 121930
A9: 44931 | C9: DEMETRIU | E9: 6 | F9: 860 | G9: =(F9*D9)+(E9*F9) -> 5160 | J9: =H9*I9 -> 0 | L9: =(J9+G9)-K9 -> 5160 | N9: =IF(M9>0,SUM(L9-M9)," ") | R9: =IF(O9>0,SUM(O9-(L9+P9))," ") | T9: A VISTA | U9: 0 | V9: FOB | Y9: 720 | AA9: =Y9*Z9 -> 0
A10: 44931 | C10: JOSIEL | D10: 1 | F10: 900 | G10: =(F10*D10)+(E10*F10) -> 900 | J10: =H10*I10 -> 0 | L10: =(J10+G10)-K10 -> 900 | N10: =IF(M10>0,SUM(L10-M10)," ") | R10: =IF(O10>0,SUM(O10-(L10+P10))," ") | T10: A VISTA | U10: 0 | V10: FOB | Y10: 750 | AA10: =Y10*Z10 -> 0
A11: 44931 | C11: FELIPE | D11: 1 | F11: 900 | G11: =(F11*D11)+(E11*F11) -> 900 | J11: =H11*I11 -> 0 | L11: =(J11+G11)-K11 -> 900 | N11: =IF(M11>0,SUM(L11-M11)," ") | R11: =IF(O11>0,SUM(O11-(L11+P11))," ") | T11: A VISTA | U11: 0 | V11: FOB | Y11: 780 | AA11: =Y11*Z11 -> 0
A12: 44931 | C12: FORTMASSA | D12: 1 | F12: 880 | G12: =(F12*D12)+(E12*F12) -> 880 | J12: =H12*I12 -> 0 | L12: =(J12+G12)-K12 -> 880 | N12: =IF(M12>0,SUM(L12-M12)," ") | R12: =IF(O12>0,SUM(O12-(L12+P12))," ") | T12: A VISTA | U12: 0 | V12: FOB | Y12: 800 | AA12: =Y12*Z12 -> 0
A13: 44932 | C13: CLAUDIO MOSSORO | D13: 8 | F13: 860 | G13: =(F13*D13)+(E13*F13) -> 6880 | J13: =H13*I13 -> 0 | L13: =(J13+G13)-K13 -> 6880 | N13: =IF(M13>0,SUM(L13-M13)," ") | O13: 440 | R13: =IF(O13>0,SUM(O13-(L13+P13))," ") -> -6440 | S13: =P13-Q13 -> 0 | T13: A VISTA | U13: 30 | V13: FOB | W13: QUITACAO CREDITO | AA13: =AA8-(SUM(AA9:AA12)) -> 121930
A14: 44934 | C14: ROBERTO LAGOA DO BANANA | E14: 1 | F14: 880 | G14: =(F14*D14)+(E14*F14) -> 880 | J14: =H14*I14 -> 0 | L14: =(J14+G14)-K14 -> 880 | N14: =IF(M14>0,SUM(L14-M14)," ") | R14: =IF(O14>0,SUM(O14-(L14+P14))," ")
A15: 44935 | C15: ANDRE | D15: 1 | F15: 900 | G15: =(F15*D15)+(E15*F15) -> 900 | J15: =H15*I15 -> 0 | L15: =(J15+G15)-K15 -> 900 | N15: =IF(M15>0,SUM(L15-M15)," ") | R15: =IF(O15>0,SUM(O15-(L15+P15))," ")
A16: 44935 | C16: IRINEU | D16: 1 | F16: 880 | G16: =(F16*D16)+(E16*F16) -> 880 | J16: =H16*I16 -> 0 | L16: =(J16+G16)-K16 -> 880 | N16: =IF(M16>0,SUM(L16-M16)," ") | R16: =IF(O16>0,SUM(O16-(L16+P16))," ")
A17: 44935 | C17: LOURIMAR | E17: 4 | F17: 900 | G17: =(F17*D17)+(E17*F17) -> 3600 | J17: =H17*I17 -> 0 | L17: =(J17+G17)-K17 -> 3600 | N17: =IF(M17>0,SUM(L17-M17)," ") | R17: =IF(O17>0,SUM(O17-(L17+P17))," ")
A18: 44935 | C18: FORTMASSA | D18: 1 | F18: 880 | G18: =(F18*D18)+(E18*F18) -> 880 | J18: =H18*I18 -> 0 | L18: =(J18+G18)-K18 -> 880 | N18: =IF(M18>0,SUM(L18-M18)," ") | R18: =IF(O18>0,SUM(O18-(L18+P18))," ")
A19: 44937 | C19: PAVIMARI | D19: 1 | F19: 900 | G19: =(F19*D19)+(E19*F19) -> 900 | J19: =H19*I19 -> 0 | L19: =(J19+G19)-K19 -> 900 | N19: =IF(M19>0,SUM(L19-M19)," ") | R19: =IF(O19>0,SUM(O19-(L19+P19))," ")
A20: 44937 | C20: CEARAMIX | E20: 1 | F20: 900 | G20: =(F20*D20)+(E20*F20) -> 900 | J20: =H20*I20 -> 0 | L20: =(J20+G20)-K20 -> 900 | N20: =IF(M20>0,SUM(L20-M20)," ") | R20: =IF(O20>0,SUM(O20-(L20+P20))," ")
A21: 44938 | C21: FORTMASSA | E21: 1 | F21: 880 | G21: =(F21*D21)+(E21*F21) -> 880 | J21: =H21*I21 -> 0 | L21: =(J21+G21)-K21 -> 880 | N21: =IF(M21>0,SUM(L21-M21)," ") | R21: =IF(O21>0,SUM(O21-(L21+P21))," ")
A22: 44938 | C22: AREMIX | E22: 10 | F22: 850 | G22: =(F22*D22)+(E22*F22) -> 8500 | J22: =H22*I22 -> 0 | L22: =(J22+G22)-K22 -> 8500 | N22: =IF(M22>0,SUM(L22-M22)," ") | R22: =IF(O22>0,SUM(O22-(L22+P22))," ")
A23: 44938 | C23: FELIPE | D23: 2 | F23: 900 | G23: =(F23*D23)+(E23*F23) -> 1800 | J23: =H23*I23 -> 0 | L23: =(J23+G23)-K23 -> 1800 | N23: =IF(M23>0,SUM(L23-M23)," ") | R23: =IF(O23>0,SUM(O23-(L23+P23))," ")
A24: 44938 | C24: GETULIO | D24: 2 | F24: 880 | G24: =(F24*D24)+(E24*F24) -> 1760 | J24: =H24*I24 -> 0 | L24: =(J24+G24)-K24 -> 1760 | N24: =IF(M24>0,SUM(L24-M24)," ") | R24: =IF(O24>0,SUM(O24-(L24+P24))," ")
A25: 44939 | C25: DEMETRIU | D25: 6 | F25: 860 | G25: =(F25*D25)+(E25*F25) -> 5160 | J25: =H25*I25 -> 0 | L25: =(J25+G25)-K25 -> 5160 | N25: =IF(M25>0,SUM(L25-M25)," ") | R25: =IF(O25>0,SUM(O25-(L25+P25))," ")
A26: 44939 | C26: ARG ROMA | D26: 4 | F26: 860 | G26: =(F26*D26)+(E26*F26) -> 3440 | J26: =H26*I26 -> 0 | L26: =(J26+G26)-K26 -> 3440 | N26: =IF(M26>0,SUM(L26-M26)," ") | R26: =IF(O26>0,SUM(O26-(L26+P26))," ")
A27: 44939 | C27: FORTMASSA | D27: 1 | F27: 880 | G27: =(F27*D27)+(E27*F27) -> 880 | J27: =H27*I27 -> 0 | L27: =(J27+G27)-K27 -> 880 | N27: =IF(M27>0,SUM(L27-M27)," ") | R27: =IF(O27>0,SUM(O27-(L27+P27))," ")
A28: 44942 | C28: IRINEU | D28: 1 | F28: 880 | G28: =(F28*D28)+(E28*F28) -> 880 | J28: =H28*I28 -> 0 | L28: =(J28+G28)-K28 -> 880 | N28: =IF(M28>0,SUM(L28-M28)," ") | R28: =IF(O28>0,SUM(O28-(L28+P28))," ")
A29: 44943 | C29: MEBIO | E29: 1 | F29: 870 | G29: =(F29*D29)+(E29*F29) -> 870 | J29: =H29*I29 -> 0 | L29: =(J29+G29)-K29 -> 870 | N29: =IF(M29>0,SUM(L29-M29)," ") | R29: =IF(O29>0,SUM(O29-(L29+P29))," ")
A30: 44943 | C30: CHICO PEREIRA | E30: 2 | F30: 880 | G30: =(F30*D30)+(E30*F30) -> 1760 | J30: =H30*I30 -> 0 | L30: =(J30+G30)-K30 -> 1760 | N30: =IF(M30>0,SUM(L30-M30)," ") | R30: =IF(O30>0,SUM(O30-(L30+P30))," ")
A31: 44944 | C31: FORTMASSA | D31: 1 | F31: 880 | G31: =(F31*D31)+(E31*F31) -> 880 | J31: =H31*I31 -> 0 | L31: =(J31+G31)-K31 -> 880 | N31: =IF(M31>0,SUM(L31-M31)," ") | R31: =IF(O31>0,SUM(O31-(L31+P31))," ")
A32: 44944 | C32: LOURIMAR | E32: 4 | F32: 900 | G32: =(F32*D32)+(E32*F32) -> 3600 | J32: =H32*I32 -> 0 | L32: =(J32+G32)-K32 -> 3600 | N32: =IF(M32>0,SUM(L32-M32)," ") | R32: =IF(O32>0,SUM(O32-(L32+P32))," ")
A33: 44945 | C33: MULTCOLA | E33: 4 | F33: 860 | G33: =(F33*D33)+(E33*F33) -> 3440 | J33: =H33*I33 -> 0 | L33: =(J33+G33)-K33 -> 3440 | N33: =IF(M33>0,SUM(L33-M33)," ") | R33: =IF(O33>0,SUM(O33-(L33+P33))," ")
A34: 44945 | C34: IRINEU | D34: 1 | F34: 880 | G34: =(F34*D34)+(E34*F34) -> 880 | J34: =H34*I34 -> 0 | L34: =(J34+G34)-K34 -> 880 | N34: =IF(M34>0,SUM(L34-M34)," ") | R34: =IF(O34>0,SUM(O34-(L34+P34))," ")
A35: 44946 | C35: FORTMASSA | D35: 1 | F35: 880 | G35: =(F35*D35)+(E35*F35) -> 880 | J35: =H35*I35 -> 0 | L35: =(J35+G35)-K35 -> 880 | N35: =IF(M35>0,SUM(L35-M35)," ") | R35: =IF(O35>0,SUM(O35-(L35+P35))," ")
A36: 44946 | C36: DEMETRIU | D36: 6 | F36: 860 | G36: =(F36*D36)+(E36*F36) -> 5160 | J36: =H36*I36 -> 0 | L36: =(J36+G36)-K36 -> 5160 | N36: =IF(M36>0,SUM(L36-M36)," ") | R36: =IF(O36>0,SUM(O36-(L36+P36))," ")
A37: 44946 | C37: ROBERTO LAGOA DO BANANA | D37: 1 | F37: 880 | G37: =(F37*D37)+(E37*F37) -> 880 | J37: =H37*I37 -> 0 | L37: =(J37+G37)-K37 -> 880 | N37: =IF(M37>0,SUM(L37-M37)," ") | R37: =IF(O37>0,SUM(O37-(L37+P37))," ")
A38: 44947 | C38: GETULIO | D38: 2 | F38: 880 | G38: =(F38*D38)+(E38*F38) -> 1760 | J38: =H38*I38 -> 0 | L38: =(J38+G38)-K38 -> 1760 | N38: =IF(M38>0,SUM(L38-M38)," ") | R38: =IF(O38>0,SUM(O38-(L38+P38))," ")
A39: 44949 | C39: FORTMASSA | D39: 1 | F39: 880 | G39: =(F39*D39)+(E39*F39) -> 880 | J39: =H39*I39 -> 0 | L39: =(J39+G39)-K39 -> 880 | N39: =IF(M39>0,SUM(L39-M39)," ") | R39: =IF(O39>0,SUM(O39-(L39+P39))," ")
A40: 44950 | C40: CLAUDIO MOSSORO | D40: 8 | F40: 860 | G40: =(F40*D40)+(E40*F40) -> 6880 | J40: =H40*I40 -> 0 | L40: =(J40+G40)-K40 -> 6880 | N40: =IF(M40>0,SUM(L40-M40)," ") | R40: =IF(O40>0,SUM(O40-(L40+P40))," ")
A41: 44950 | C41: TODA OBRA | E41: 4 | F41: 880 | G41: =(F41*D41)+(E41*F41) -> 3520 | J41: =H41*I41 -> 0 | L41: =(J41+G41)-K41 -> 3520 | N41: =IF(M41>0,SUM(L41-M41)," ") | R41: =IF(O41>0,SUM(O41-(L41+P41))," ")
A42: 44951 | C42: FORTMASSA | D42: 1 | F42: 880 | G42: =(F42*D42)+(E42*F42) -> 880 | J42: =H42*I42 -> 0 | L42: =(J42+G42)-K42 -> 880 | N42: =IF(M42>0,SUM(L42-M42)," ") | R42: =IF(O42>0,SUM(O42-(L42+P42))," ")
A43: 44951 | C43: IRINEU | D43: 1 | F43: 880 | G43: =(F43*D43)+(E43*F43) -> 880 | J43: =H43*I43 -> 0 | L43: =(J43+G43)-K43 -> 880 | N43: =IF(M43>0,SUM(L43-M43)," ") | R43: =IF(O43>0,SUM(O43-(L43+P43))," ")
A44: 44951 | C44: FELIPE | D44: 2 | F44: 900 | G44: =(F44*D44)+(E44*F44) -> 1800 | J44: =H44*I44 -> 0 | L44: =(J44+G44)-K44 -> 1800 | N44: =IF(M44>0,SUM(L44-M44)," ") | R44: =IF(O44>0,SUM(O44-(L44+P44))," ")
A45: 44952 | C45: DEMETRIU | D45: 6 | F45: 860 | G45: =(F45*D45)+(E45*F45) -> 5160 | J45: =H45*I45 -> 0 | L45: =(J45+G45)-K45 -> 5160 | N45: =IF(M45>0,SUM(L45-M45)," ") | R45: =IF(O45>0,SUM(O45-(L45+P45))," ")
A46: 44954 | C46: ARG ROMA | D46: 4 | F46: 860 | G46: =(F46*D46)+(E46*F46) -> 3440 | J46: =H46*I46 -> 0 | L46: =(J46+G46)-K46 -> 3440 | N46: =IF(M46>0,SUM(L46-M46)," ") | R46: =IF(O46>0,SUM(O46-(L46+P46))," ")
A47: 44954 | C47: GETULIO | D47: 3 | F47: 880 | G47: =(F47*D47)+(E47*F47) -> 2640 | J47: =H47*I47 -> 0 | L47: =(J47+G47)-K47 -> 2640 | N47: =IF(M47>0,SUM(L47-M47)," ") | R47: =IF(O47>0,SUM(O47-(L47+P47))," ")
A48: 44954 | C48: THIAGO TIANGUA | E48: 1 | F48: 900 | G48: =(F48*D48)+(E48*F48) -> 900 | J48: =H48*I48 -> 0 | L48: =(J48+G48)-K48 -> 900 | N48: =IF(M48>0,SUM(L48-M48)," ") | R48: =IF(O48>0,SUM(O48-(L48+P48))," ")
A49: 44954 | C49: LUIZ PI | E49: 2 | F49: 880 | G49: =(F49*D49)+(E49*F49) -> 1760 | J49: =H49*I49 -> 0 | L49: =(J49+G49)-K49 -> 1760 | N49: =IF(M49>0,SUM(L49-M49)," ") | R49: =IF(O49>0,SUM(O49-(L49+P49))," ")
A50: 44954 | C50: AREMIX | E50: 10 | F50: 850 | G50: =(F50*D50)+(E50*F50) -> 8500 | J50: =H50*I50 -> 0 | L50: =(J50+G50)-K50 -> 8500 | N50: =IF(M50>0,SUM(L50-M50)," ") | R50: =IF(O50>0,SUM(O50-(L50+P50))," ")
A51: 44954 | C51: HENRIQUE | D51: 1 | F51: 880 | G51: =(F51*D51)+(E51*F51) -> 880 | J51: =H51*I51 -> 0 | L51: =(J51+G51)-K51 -> 880 | N51: =IF(M51>0,SUM(L51-M51)," ") | R51: =IF(O51>0,SUM(O51-(L51+P51))," ")
A52: 44957 | C52: DEDE DO ARROZ | D52: 1 | F52: 880 | G52: =(F52*D52)+(E52*F52) -> 880 | J52: =H52*I52 -> 0 | L52: =(J52+G52)-K52 -> 880 | N52: =IF(M52>0,SUM(L52-M52)," ") | R52: =IF(O52>0,SUM(O52-(L52+P52))," ")
A53: 44957 | C53: ANDRE | D53: 1 | F53: 900 | G53: =(F53*D53)+(E53*F53) -> 900 | J53: =H53*I53 -> 0 | L53: =(J53+G53)-K53 -> 900 | N53: =IF(M53>0,SUM(L53-M53)," ") | R53: =IF(O53>0,SUM(O53-(L53+P53))," ")
A54: 44957 | C54: IRINEU | D54: 1 | F54: 880 | G54: =(F54*D54)+(E54*F54) -> 880 | J54: =H54*I54 -> 0 | L54: =(J54+G54)-K54 -> 880 | N54: =IF(M54>0,SUM(L54-M54)," ") | R54: =IF(O54>0,SUM(O54-(L54+P54))," ")
A55: 44957 | C55: LOURIMAR | E55: 4 | F55: 900 | G55: =(F55*D55)+(E55*F55) -> 3600 | J55: =H55*I55 -> 0 | L55: =(J55+G55)-K55 -> 3600 | N55: =IF(M55>0,SUM(L55-M55)," ") | R55: =IF(O55>0,SUM(O55-(L55+P55))," ")
A56: 44959 | C56: DEMETRIU | D56: 2 | F56: 860 | G56: =(F56*D56)+(E56*F56) -> 1720 | J56: =H56*I56 -> 0 | L56: =(J56+G56)-K56 -> 1720 | N56: =IF(M56>0,SUM(L56-M56)," ") | R56: =IF(O56>0,SUM(O56-(L56+P56))," ")
F57: 880 | G57: =(F57*D57)+(E57*F57) -> 0 | J57: =H57*I57 -> 0 | L57: =(J57+G57)-K57 -> 0 | N57: =IF(M57>0,SUM(L57-M57)," ") | R57: =IF(O57>0,SUM(O57-(L57+P57))," ")
F58: 800 | G58: =(F58*D58)+(E58*F58) -> 0 | J58: =H58*I58 -> 0 | L58: =(J58+G58)-K58 -> 0 | N58: =IF(M58>0,SUM(L58-M58)," ") | R58: =IF(O58>0,SUM(O58-(L58+P58))," ")
F59: 800 | G59: =(F59*D59)+(E59*F59) -> 0 | J59: =H59*I59 -> 0 | L59: =(J59+G59)-K59 -> 0 | N59: =IF(M59>0,SUM(L59-M59)," ") | R59: =IF(O59>0,SUM(O59-(L59+P59))," ")
F60: 800 | G60: =(F60*D60)+(E60*F60) -> 0 | J60: =H60*I60 -> 0 | L60: =(J60+G60)-K60 -> 0 | N60: =IF(M60>0,SUM(L60-M60)," ") | R60: =IF(O60>0,SUM(O60-(L60+P60))," ")
F61: 800 | G61: =(F61*D61)+(E61*F61) -> 0 | J61: =H61*I61 -> 0 | L61: =(J61+G61)-K61 -> 0 | N61: =IF(M61>0,SUM(L61-M61)," ") | R61: =IF(O61>0,SUM(O61-(L61+P61))," ")
F62: 880 | G62: =(F62*D62)+(E62*F62) -> 0 | J62: =H62*I62 -> 0 | L62: =(J62+G62)-K62 -> 0 | N62: =IF(M62>0,SUM(L62-M62)," ") | R62: =IF(O62>0,SUM(O62-(L62+P62))," ")
F63: 880 | G63: =(F63*D63)+(E63*F63) -> 0 | J63: =H63*I63 -> 0 | L63: =(J63+G63)-K63 -> 0 | N63: =IF(M63>0,SUM(L63-M63)," ") | R63: =IF(O63>0,SUM(O63-(L63+P63))," ")
F64: 880 | G64: =(F64*D64)+(E64*F64) -> 0 | J64: =H64*I64 -> 0 | L64: =(J64+G64)-K64 -> 0 | N64: =IF(M64>0,SUM(L64-M64)," ") | R64: =IF(O64>0,SUM(O64-(L64+P64))," ")
F65: 900 | G65: =(F65*D65)+(E65*F65) -> 0 | J65: =H65*I65 -> 0 | L65: =(J65+G65)-K65 -> 0 | N65: =IF(M65>0,SUM(L65-M65)," ") | R65: =IF(O65>0,SUM(O65-(L65+P65))," ")
F66: 860 | G66: =(F66*D66)+(E66*F66) -> 0 | J66: =H66*I66 -> 0 | L66: =(J66+G66)-K66 -> 0 | N66: =IF(M66>0,SUM(L66-M66)," ") | R66: =IF(O66>0,SUM(O66-(L66+P66))," ")
F67: 860 | G67: =(F67*D67)+(E67*F67) -> 0 | J67: =H67*I67 -> 0 | L67: =(J67+G67)-K67 -> 0 | N67: =IF(M67>0,SUM(L67-M67)," ") | R67: =IF(O67>0,SUM(O67-(L67+P67))," ")
F68: 900 | G68: =(F68*D68)+(E68*F68) -> 0 | J68: =H68*I68 -> 0 | L68: =(J68+G68)-K68 -> 0 | N68: =IF(M68>0,SUM(L68-M68)," ") | R68: =IF(O68>0,SUM(O68-(L68+P68))," ")
... F100: 800 | G100: =(F100*D100)+(E100*F100) -> 0 | J100: =H100*I100 -> 0 | L100: =(J100+G100)-K100 -> 0 | N100: =IF(M100>0,SUM(L100-M100)," ") | R100: =IF(O100>0,SUM(O100-(L100+P100))," ")
D101: =SUM(D4:D100) -> 75 | E101: =SUM(E4:E100) -> 65 | G101: =SUM(G4:G100) -> 121930 | H101: =SUM(H4:H100) -> 0 | J101: =SUM(J4:J100) -> 0 | L101: =SUM(L4:L100) -> 121930 | N101: =IF(M101>0,SUM(L101-M101)," ") | O101: =SUM(O4:O100) -> 1840 | P101: =SUM(P4:P100) -> 0 | Q101: =SUM(Q4:Q100) -> 0 | R101: =SUM(R4:R100) -> -7620 | S101: =SUM(S4:S100) -> 0
D102: =D101+E101 -> 140
C108: CLEZIO - DURAPLIK
C109: DEMETRIUS - ULTRAMASSA
C110: CLEZIO - DURAPLIK
C111: RAPOSÃO - MASSA FORTE
C112: GETULIA - JOSE WALTER
C113: CLAUDIO - MOSSORO
C114: CLEZIO - DURAPLIK
C115: CLEZIO - DURAPLIK
C116: CLEZIO - DURAPLIK
C117: DEMETRIUS - ULTRAMASSA
C120: AREMIX
C121: THIAGO - TIANGUA
... C138: DEMETRIUS - ULTRAMASSA

Sheet Vendas - FEV
A1: VENDAS | B1: VENDAS | D1: =D102 -> 120
A2: DATA | B2: VENDEDOR | C2: Clientes | D2: CELULOSE | H2: POLÍMERO | K2: DESCONTO CHEQUE | L2: TOTAL | M2: PARCIAL | N2: DEVENDO | O2: CHEQUES / PAGAMENTOS A MAIS OU A MENOS | T2: Forma de Pagamento | U2: Prazo | V2: Frete CIF / FOB | W2: OBSERVAÇÃO | X2: OBSERVAÇÃO
D3: PALOMA | E3: UCHOA | F3: PREÇO | G3: TOTAL | H3: QTD | I3: PREÇO TAB | J3: TOTAL | O3: VALOR VENDA | P3: COBRAMOS % | Q3: PAGAMOS % | R3: SALDO/DEBITO CLIENTE | S3: LUCRO/PREJ JUROS
F4: 880 | G4: =(F4*D4)+(E4*F4) -> 0 | J4: =H4*I4 -> 0 | L4: =(J4+G4)-K4 -> 0 | N4: =IF(M4>0,SUM(L4-M4)," ") | R4: =IF(O4>0,SUM(O4-(L4+P4))," ") | T4: A VISTA | U4: 0 | V4: FOB
F5: 850 | G5: =(F5*D5)+(E5*F5) -> 0 | J5: =H5*I5 -> 0 | L5: =(J5+G5)-K5 -> 0 | N5: =IF(M5>0,SUM(L5-M5)," ") | R5: =IF(O5>0,SUM(O5-(L5+P5))," ") | T5: A VISTA | U5: 0 | V5: FOB
F6: 880 | G6: =(F6*D6)+(E6*F6) -> 0 | J6: =H6*I6 -> 0 | L6: =(J6+G6)-K6 -> 0 | N6: =IF(M6>0,SUM(L6-M6)," ") | R6: =IF(O6>0,SUM(O6-(L6+P6))," ") | T6: A VISTA | U6: 0 | V6: FOB
F7: 860 | G7: =(F7*D7)+(E7*F7) -> 0 | J7: =H7*I7 -> 0 | L7: =(J7+G7)-K7 -> 0 | N7: =IF(M7>0,SUM(L7-M7)," ") | R7: =IF(O7>0,SUM(O7-(L7+P7))," ") | T7: A VISTA | U7: 0 | V7: FOB
F8: 880 | G8: =(F8*D8)+(E8*F8) -> 0 | J8: =H8*I8 -> 0 | L8: =(J8+G8)-K8 -> 0 | N8: =IF(M8>0,SUM(L8-M8)," ") | O8: 1400 | R8: =IF(O8>0,SUM(O8-(L8+P8))," ") -> 1400 | T8: CHEQUE/R$ | U8: 0 | V8: FOB | W8: 1100 + 300 | Y8: VALOR | Z8: QTD | AA8: =G101 -> 104150
A9: 44959 | C9: DEMETRIU | D9: 3 | F9: 860 | G9: =(F9*D9)+(E9*F9) -> 2580 | J9: =H9*I9 -> 0 | L9: =(J9+G9)-K9 -> 2580 | N9: =IF(M9>0,SUM(L9-M9)," ") | R9: =IF(O9>0,SUM(O9-(L9+P9))," ") | T9: A VISTA | U9: 0 | V9: FOB | Y9: 720 | AA9: =Y9*Z9 -> 0
A10: 44960 | C10: ELIEL | E10: 1 | F10: 870 | G10: =(F10*D10)+(E10*F10) -> 870 | J10: =H10*I10 -> 0 | L10: =(J10+G10)-K10 -> 870 | N10: =IF(M10>0,SUM(L10-M10)," ") | R10: =IF(O10>0,SUM(O10-(L10+P10))," ") | T10: A VISTA | U10: 0 | V10: FOB | Y10: 750 | AA10: =Y10*Z10 -> 0
A11: 44960 | C11: ROBERTO LAGOA DO BANANA | E11: 1 | F11: 880 | G11: =(F11*D11)+(E11*F11) -> 880 | J11: =H11*I11 -> 0 | L11: =(J11+G11)-K11 -> 880 | N11: =IF(M11>0,SUM(L11-M11)," ") | R11: =IF(O11>0,SUM(O11-(L11+P11))," ") | T11: A VISTA | U11: 0 | V11: FOB | Y11: 780 | AA11: =Y11*Z11 -> 0
A12: 44960 | C12: IRINEU | D12: 2 | F12: 880 | G12: =(F12*D12)+(E12*F12) -> 1760 | J12: =H12*I12 -> 0 | L12: =(J12+G12)-K12 -> 1760 | N12: =IF(M12>0,SUM(L12-M12)," ") | R12: =IF(O12>0,SUM(O12-(L12+P12))," ") | T12: A VISTA | U12: 0 | V12: FOB | Y12: 800 | AA12: =Y12*Z12 -> 0
A13: 44961 | C13: ARG ROMA | D13: 4 | F13: 860 | G13: =(F13*D13)+(E13*F13) -> 3440 | J13: =H13*I13 -> 0 | L13: =(J13+G13)-K13 -> 3440 | N13: =IF(M13>0,SUM(L13-M13)," ") | O13: 440 | R13: =IF(O13>0,SUM(O13-(L13+P13))," ") -> -3000 | S13: =P13-Q13 -> 0 | T13: A VISTA | U13: 30 | V13: FOB | W13: QUITACAO CREDITO | AA13: =AA8-(SUM(AA9:AA12)) -> 104150
A14: 44961 | C14: GETULIO | D14: 2 | F14: 880 | G14: =(F14*D14)+(E14*F14) -> 1760 | J14: =H14*I14 -> 0 | L14: =(J14+G14)-K14 -> 1760 | N14: =IF(M14>0,SUM(L14-M14)," ") | R14: =IF(O14>0,SUM(O14-(L14+P14))," ")
A15: 44963 | C15: CHICO PEREIRA | E15: 2 | F15: 880 | G15: =(F15*D15)+(E15*F15) -> 1760 | J15: =H15*I15 -> 0 | L15: =(J15+G15)-K15 -> 1760 | N15: =IF(M15>0,SUM(L15-M15)," ") | R15: =IF(O15>0,SUM(O15-(L15+P15))," ")
A16: 44964 | C16: AREMIX | E16: 10 | F16: 850 | G16: =(F16*D16)+(E16*F16) -> 8500 | J16: =H16*I16 -> 0 | L16: =(J16+G16)-K16 -> 8500 | N16: =IF(M16>0,SUM(L16-M16)," ") | R16: =IF(O16>0,SUM(O16-(L16+P16))," ")
A17: 44964 | C17: JOSIEL | E17: 1 | F17: 900 | G17: =(F17*D17)+(E17*F17) -> 900 | J17: =H17*I17 -> 0 | L17: =(J17+G17)-K17 -> 900 | N17: =IF(M17>0,SUM(L17-M17)," ") | R17: =IF(O17>0,SUM(O17-(L17+P17))," ")
A18: 44965 | C18: GETULIO | D18: 1 | F18: 880 | G18: =(F18*D18)+(E18*F18) -> 880 | J18: =H18*I18 -> 0 | L18: =(J18+G18)-K18 -> 880 | N18: =IF(M18>0,SUM(L18-M18)," ") | R18: =IF(O18>0,SUM(O18-(L18+P18))," ")
A19: 44965 | C19: CLAUDIO MOSSORO | D19: 8 | F19: 860 | G19: =(F19*D19)+(E19*F19) -> 6880 | J19: =H19*I19 -> 0 | L19: =(J19+G19)-K19 -> 6880 | N19: =IF(M19>0,SUM(L19-M19)," ") | R19: =IF(O19>0,SUM(O19-(L19+P19))," ")
A20: 44966 | C20: IRINEU | D20: 2 | F20: 880 | G20: =(F20*D20)+(E20*F20) -> 1760 | J20: =H20*I20 -> 0 | L20: =(J20+G20)-K20 -> 1760 | N20: =IF(M20>0,SUM(L20-M20)," ") | R20: =IF(O20>0,SUM(O20-(L20+P20))," ")
A21: 44966 | C21: DEMETRIU | E21: 6 | F21: 860 | G21: =(F21*D21)+(E21*F21) -> 5160 | J21: =H21*I21 -> 0 | L21: =(J21+G21)-K21 -> 5160 | N21: =IF(M21>0,SUM(L21-M21)," ") | R21: =IF(O21>0,SUM(O21-(L21+P21))," ")
A22: 44966 | C22: MULTCOLA | E22: 6 | F22: 860 | G22: =(F22*D22)+(E22*F22) -> 5160 | J22: =H22*I22 -> 0 | L22: =(J22+G22)-K22 -> 5160 | N22: =IF(M22>0,SUM(L22-M22)," ") | R22: =IF(O22>0,SUM(O22-(L22+P22))," ")
A23: 44966 | C23: TODA OBRA | E23: 3 | F23: 880 | G23: =(F23*D23)+(E23*F23) -> 2640 | J23: =H23*I23 -> 0 | L23: =(J23+G23)-K23 -> 2640 | N23: =IF(M23>0,SUM(L23-M23)," ") | R23: =IF(O23>0,SUM(O23-(L23+P23))," ")
A24: 44966 | C24: CEARAMIX | E24: 1 | F24: 900 | G24: =(F24*D24)+(E24*F24) -> 900 | J24: =H24*I24 -> 0 | L24: =(J24+G24)-K24 -> 900 | N24: =IF(M24>0,SUM(L24-M24)," ") | R24: =IF(O24>0,SUM(O24-(L24+P24))," ")
A25: 44967 | C25: ARG ROMA | D25: 4 | F25: 860 | G25: =(F25*D25)+(E25*F25) -> 3440 | J25: =H25*I25 -> 0 | L25: =(J25+G25)-K25 -> 3440 | N25: =IF(M25>0,SUM(L25-M25)," ") | R25: =IF(O25>0,SUM(O25-(L25+P25))," ")
A26: 44967 | C26: MOEBIO | D26: 1 | F26: 860 | G26: =(F26*D26)+(E26*F26) -> 860 | J26: =H26*I26 -> 0 | L26: =(J26+G26)-K26 -> 860 | N26: =IF(M26>0,SUM(L26-M26)," ") | R26: =IF(O26>0,SUM(O26-(L26+P26))," ")
A27: 44968 | C27: GETULIO | D27: 2 | F27: 880 | G27: =(F27*D27)+(E27*F27) -> 1760 | J27: =H27*I27 -> 0 | L27: =(J27+G27)-K27 -> 1760 | N27: =IF(M27>0,SUM(L27-M27)," ") | R27: =IF(O27>0,SUM(O27-(L27+P27))," ")
A28: 44968 | C28: FELIPE | D28: 1 | F28: 900 | G28: =(F28*D28)+(E28*F28) -> 900 | J28: =H28*I28 -> 0 | L28: =(J28+G28)-K28 -> 900 | N28: =IF(M28>0,SUM(L28-M28)," ") | R28: =IF(O28>0,SUM(O28-(L28+P28))," ")
A29: 44968 | C29: EVALDO SANTA INES | D29: 4 | F29: 860 | G29: =(F29*D29)+(E29*F29) -> 3440 | J29: =H29*I29 -> 0 | L29: =(J29+G29)-K29 -> 3440 | N29: =IF(M29>0,SUM(L29-M29)," ") | R29: =IF(O29>0,SUM(O29-(L29+P29))," ")
A30: 44970 | C30: LOURIMAR | E30: 4 | F30: 900 | G30: =(F30*D30)+(E30*F30) -> 3600 | J30: =H30*I30 -> 0 | L30: =(J30+G30)-K30 -> 3600 | N30: =IF(M30>0,SUM(L30-M30)," ") | R30: =IF(O30>0,SUM(O30-(L30+P30))," ")
A31: 44971 | C31: DEMETRIU | E31: 6 | F31: 860 | G31: =(F31*D31)+(E31*F31) -> 5160 | J31: =H31*I31 -> 0 | L31: =(J31+G31)-K31 -> 5160 | N31: =IF(M31>0,SUM(L31-M31)," ") | R31: =IF(O31>0,SUM(O31-(L31+P31))," ")
A32: 44971 | C32: ROBERTO LAGOA DO BANANA | E32: 2 | F32: 880 | G32: =(F32*D32)+(E32*F32) -> 1760 | J32: =H32*I32 -> 0 | L32: =(J32+G32)-K32 -> 1760 | N32: =IF(M32>0,SUM(L32-M32)," ") | R32: =IF(O32>0,SUM(O32-(L32+P32))," ")
A33: 44974 | C33: LOURIMAR | D33: 2 | F33: 900 | G33: =(F33*D33)+(E33*F33) -> 1800 | J33: =H33*I33 -> 0 | L33: =(J33+G33)-K33 -> 1800 | N33: =IF(M33>0,SUM(L33-M33)," ") | R33: =IF(O33>0,SUM(O33-(L33+P33))," ")
A34: 44975 | C34: IRINEU | D34: 1 | F34: 880 | G34: =(F34*D34)+(E34*F34) -> 880 | J34: =H34*I34 -> 0 | L34: =(J34+G34)-K34 -> 880 | N34: =IF(M34>0,SUM(L34-M34)," ") | R34: =IF(O34>0,SUM(O34-(L34+P34))," ")
A35: 44980 | C35: CHICO PEREIRA | D35: 2 | F35: 880 | G35: =(F35*D35)+(E35*F35) -> 1760 | J35: =H35*I35 -> 0 | L35: =(J35+G35)-K35 -> 1760 | N35: =IF(M35>0,SUM(L35-M35)," ") | R35: =IF(O35>0,SUM(O35-(L35+P35))," ")
A36: 44980 | C36: LOURIMAR | D36: 4 | F36: 900 | G36: =(F36*D36)+(E36*F36) -> 3600 | J36: =H36*I36 -> 0 | L36: =(J36+G36)-K36 -> 3600 | N36: =IF(M36>0,SUM(L36-M36)," ") | R36: =IF(O36>0,SUM(O36-(L36+P36))," ")
A37: 44981 | C37: GETULIO | D37: 3 | F37: 880 | G37: =(F37*D37)+(E37*F37) -> 2640 | J37: =H37*I37 -> 0 | L37: =(J37+G37)-K37 -> 2640 | N37: =IF(M37>0,SUM(L37-M37)," ") | R37: =IF(O37>0,SUM(O37-(L37+P37))," ")
A38: 44981 | C38: CLAUDIO MOSSORO | D38: 4 | F38: 860 | G38: =(F38*D38)+(E38*F38) -> 3440 | J38: =H38*I38 -> 0 | L38: =(J38+G38)-K38 -> 3440 | N38: =IF(M38>0,SUM(L38-M38)," ") | R38: =IF(O38>0,SUM(O38-(L38+P38))," ")
A39: 44981 | C39: EXPEDITO TIMON | D39: 2 | F39: 860 | G39: =(F39*D39)+(E39*F39) -> 1720 | J39: =H39*I39 -> 0 | L39: =(J39+G39)-K39 -> 1720 | N39: =IF(M39>0,SUM(L39-M39)," ") | R39: =IF(O39>0,SUM(O39-(L39+P39))," ")
A40: 44982 | C40: IRINEU | D40: 1 | F40: 880 | G40: =(F40*D40)+(E40*F40) -> 880 | J40: =H40*I40 -> 0 | L40: =(J40+G40)-K40 -> 880 | N40: =IF(M40>0,SUM(L40-M40)," ") | R40: =IF(O40>0,SUM(O40-(L40+P40))," ")
A41: 44982 | C41: EVALDO SANTA INES | D41: 3 | F41: 860 | G41: =(F41*D41)+(E41*F41) -> 2580 | J41: =H41*I41 -> 0 | L41: =(J41+G41)-K41 -> 2580 | N41: =IF(M41>0,SUM(L41-M41)," ") | R41: =IF(O41>0,SUM(O41-(L41+P41))," ")
A42: 44984 | C42: FELIPE | D42: 1 | F42: 900 | G42: =(F42*D42)+(E42*F42) -> 900 | J42: =H42*I42 -> 0 | L42: =(J42+G42)-K42 -> 900 | N42: =IF(M42>0,SUM(L42-M42)," ") | R42: =IF(O42>0,SUM(O42-(L42+P42))," ")
A43: 44984 | C43: FORTMASSA | D43: 1 | F43: 880 | G43: =(F43*D43)+(E43*F43) -> 880 | J43: =H43*I43 -> 0 | L43: =(J43+G43)-K43 -> 880 | N43: =IF(M43>0,SUM(L43-M43)," ") | R43: =IF(O43>0,SUM(O43-(L43+P43))," ")
A44: 44984 | C44: LUIZ PI | D44: 2 | F44: 880 | G44: =(F44*D44)+(E44*F44) -> 1760 | J44: =H44*I44 -> 0 | L44: =(J44+G44)-K44 -> 1760 | N44: =IF(M44>0,SUM(L44-M44)," ") | R44: =IF(O44>0,SUM(O44-(L44+P44))," ")
... A47: 44985 | C47: AREMIX | D47: 10 | F47: 850 | G47: =(F47*D47)+(E47*F47) -> 8500 | J47: =H47*I47 -> 0 | L47: =(J47+G47)-K47 -> 8500 | N47: =IF(M47>0,SUM(L47-M47)," ") | R47: =IF(O47>0,SUM(O47-(L47+P47))," ")
F48: 880 | G48: =(F48*D48)+(E48*F48) -> 0 | J48: =H48*I48 -> 0 | L48: =(J48+G48)-K48 -> 0 | N48: =IF(M48>0,SUM(L48-M48)," ") | R48: =IF(O48>0,SUM(O48-(L48+P48))," ")
F49: 880 | G49: =(F49*D49)+(E49*F49) -> 0 | J49: =H49*I49 -> 0 | L49: =(J49+G49)-K49 -> 0 | N49: =IF(M49>0,SUM(L49-M49)," ") | R49: =IF(O49>0,SUM(O49-(L49+P49))," ")
F50: 880 | G50: =(F50*D50)+(E50*F50) -> 0 | J50: =H50*I50 -> 0 | L50: =(J50+G50)-K50 -> 0 | N50: =IF(M50>0,SUM(L50-M50)," ") | R50: =IF(O50>0,SUM(O50-(L50+P50))," ")
F51: 870 | G51: =(F51*D51)+(E51*F51) -> 0 | J51: =H51*I51 -> 0 | L51: =(J51+G51)-K51 -> 0 | N51: =IF(M51>0,SUM(L51-M51)," ") | R51: =IF(O51>0,SUM(O51-(L51+P51))," ")
F52: 900 | G52: =(F52*D52)+(E52*F52) -> 0 | J52: =H52*I52 -> 0 | L52: =(J52+G52)-K52 -> 0 | N52: =IF(M52>0,SUM(L52-M52)," ") | R52: =IF(O52>0,SUM(O52-(L52+P52))," ")
F53: 880 | G53: =(F53*D53)+(E53*F53) -> 0 | J53: =H53*I53 -> 0 | L53: =(J53+G53)-K53 -> 0 | N53: =IF(M53>0,SUM(L53-M53)," ") | R53: =IF(O53>0,SUM(O53-(L53+P53))," ")
F54: 830 | G54: =(F54*D54)+(E54*F54) -> 0 | J54: =H54*I54 -> 0 | L54: =(J54+G54)-K54 -> 0 | N54: =IF(M54>0,SUM(L54-M54)," ") | R54: =IF(O54>0,SUM(O54-(L54+P54))," ")
F55: 800 | G55: =(F55*D55)+(E55*F55) -> 0 | J55: =H55*I55 -> 0 | L55: =(J55+G55)-K55 -> 0 | N55: =IF(M55>0,SUM(L55-M55)," ") | R55: =IF(O55>0,SUM(O55-(L55+P55))," ")
F56: 800 | G56: =(F56*D56)+(E56*F56) -> 0 | J56: =H56*I56 -> 0 | L56: =(J56+G56)-K56 -> 0 | N56: =IF(M56>0,SUM(L56-M56)," ") | R56: =IF(O56>0,SUM(O56-(L56+P56))," ")
F57: 800 | G57: =(F57*D57)+(E57*F57) -> 0 | J57: =H57*I57 -> 0 | L57: =(J57+G57)-K57 -> 0 | N57: =IF(M57>0,SUM(L57-M57)," ") | R57: =IF(O57>0,SUM(O57-(L57+P57))," ")
F58: 800 | G58: =(F58*D58)+(E58*F58) -> 0 | J58: =H58*I58 -> 0 | L58: =(J58+G58)-K58 -> 0 | N58: =IF(M58>0,SUM(L58-M58)," ") | R58: =IF(O58>0,SUM(O58-(L58+P58))," ")
F59: 800 | G59: =(F59*D59)+(E59*F59) -> 0 | J59: =H59*I59 -> 0 | L59: =(J59+G59)-K59 -> 0 | N59: =IF(M59>0,SUM(L59-M59)," ") | R59: =IF(O59>0,SUM(O59-(L59+P59))," ")
... F100: 800 | G100: =(F100*D100)+(E100*F100) -> 0 | J100: =H100*I100 -> 0 | L100: =(J100+G100)-K100 -> 0 | N100: =IF(M100>0,SUM(L100-M100)," ") | R100: =IF(O100>0,SUM(O100-(L100+P100))," ")
D101: =SUM(D4:D100) -> 77 | E101: =SUM(E4:E100) -> 43 | G101: =SUM(G4:G100) -> 104150 | H101: =SUM(H4:H100) -> 0 | J101: =SUM(J4:J100) -> 0 | L101: =SUM(L4:L100) -> 104150 | N101: =IF(M101>0,SUM(L101-M101)," ") | O101: =SUM(O4:O100) -> 1840 | P101: =SUM(P4:P100) -> 0 | Q101: =SUM(Q4:Q100) -> 0 | R101: =SUM(R4:R100) -> -1600 | S101: =SUM(S4:S100) -> 0
D102: =D101+E101 -> 120

Sheet Vendas - MAR
A1: VENDAS | B1: VENDAS | D1: =D102 -> 145
A2: DATA | B2: VENDEDOR | C2: Clientes | D2: CELULOSE | H2: POLÍMERO | K2: DESCONTO CHEQUE | L2: TOTAL | M2: PARCIAL | N2: DEVENDO | O2: CHEQUES / PAGAMENTOS A MAIS OU A MENOS | T2: Forma de Pagamento | U2: Prazo | V2: Frete CIF / FOB | W2: OBSERVAÇÃO | X2: OBSERVAÇÃO
D3: PALOMA | E3: UCHOA | F3: PREÇO | G3: TOTAL | H3: QTD | I3: PREÇO TAB | J3: TOTAL | O3: VALOR VENDA | P3: COBRAMOS % | Q3: PAGAMOS % | R3: SALDO/DEBITO CLIENTE | S3: LUCRO/PREJ JUROS
A4: 44987 | C4: VINICIUS PACAJUS | D4: 1 | F4: 870 | G4: =(F4*D4)+(E4*F4) -> 870 | J4: =H4*I4 -> 0 | L4: =(J4+G4)-K4 -> 870 | N4: =IF(M4>0,SUM(L4-M4)," ") | R4: =IF(O4>0,SUM(O4-(L4+P4))," ") | T4: A VISTA | U4: 0 | V4: FOB
A5: 44987 | C5: GETULIO | D5: 1 | F5: 880 | G5: =(F5*D5)+(E5*F5) -> 880 | J5: =H5*I5 -> 0 | L5: =(J5+G5)-K5 -> 880 | N5: =IF(M5>0,SUM(L5-M5)," ") | R5: =IF(O5>0,SUM(O5-(L5+P5))," ") | T5: A VISTA | U5: 0 | V5: FOB
A6: 44987 | C6: LOURIMAR | D6: 4 | F6: 900 | G6: =(F6*D6)+(E6*F6) -> 3600 | J6: =H6*I6 -> 0 | L6: =(J6+G6)-K6 -> 3600 | N6: =IF(M6>0,SUM(L6-M6)," ") | R6: =IF(O6>0,SUM(O6-(L6+P6))," ") | T6: A VISTA | U6: 0 | V6: FOB
A7: 44987 | C7: ARG ROMA | D7: 4 | F7: 860 | G7: =(F7*D7)+(E7*F7) -> 3440 | J7: =H7*I7 -> 0 | L7: =(J7+G7)-K7 -> 3440 | N7: =IF(M7>0,SUM(L7-M7)," ") | R7: =IF(O7>0,SUM(O7-(L7+P7))," ") | T7: A VISTA | U7: 0 | V7: FOB
A8: 44987 | C8: CLAUDIO MOSSORO | D8: 4 | F8: 860 | G8: =(F8*D8)+(E8*F8) -> 3440 | J8: =H8*I8 -> 0 | L8: =(J8+G8)-K8 -> 3440 | N8: =IF(M8>0,SUM(L8-M8)," ") | O8: 1400 | R8: =IF(O8>0,SUM(O8-(L8+P8))," ") -> -2040 | T8: CHEQUE/R$ | U8: 0 | V8: FOB | W8: 1100 + 300 | Y8: VALOR | Z8: QTD | AA8: =G101 -> 126290
A9: 44987 | C9: IRINEU | D9: 1 | F9: 880 | G9: =(F9*D9)+(E9*F9) -> 880 | J9: =H9*I9 -> 0 | L9: =(J9+G9)-K9 -> 880 | N9: =IF(M9>0,SUM(L9-M9)," ") | R9: =IF(O9>0,SUM(O9-(L9+P9))," ") | T9: A VISTA | U9: 0 | V9: FOB | Y9: 720 | AA9: =Y9*Z9 -> 0
A10: 44988 | C10: FORTMASSA | D10: 1 | F10: 880 | G10: =(F10*D10)+(E10*F10) -> 880 | J10: =H10*I10 -> 0 | L10: =(J10+G10)-K10 -> 880 | N10: =IF(M10>0,SUM(L10-M10)," ") | R10: =IF(O10>0,SUM(O10-(L10+P10))," ") | T10: A VISTA | U10: 0 | V10: FOB | Y10: 750 | AA10: =Y10*Z10 -> 0
A11: 44989 | C11: ACARI RN | D11: 1 | F11: 860 | G11: =(F11*D11)+(E11*F11) -> 860 | J11: =H11*I11 -> 0 | L11: =(J11+G11)-K11 -> 860 | N11: =IF(M11>0,SUM(L11-M11)," ") | R11: =IF(O11>0,SUM(O11-(L11+P11))," ") | T11: A VISTA | U11: 0 | V11: FOB | Y11: 780 | AA11: =Y11*Z11 -> 0
A12: 44989 | C12: EVALDO SANTA INES | D12: 3 | F12: 860 | G12: =(F12*D12)+(E12*F12) -> 2580 | J12: =H12*I12 -> 0 | L12: =(J12+G12)-K12 -> 2580 | N12: =IF(M12>0,SUM(L12-M12)," ") | R12: =IF(O12>0,SUM(O12-(L12+P12))," ") | T12: A VISTA | U12: 0 | V12: FOB | Y12: 800 | AA12: =Y12*Z12 -> 0
F13: 900 | G13: =(F13*D13)+(E13*F13) -> 0 | J13: =H13*I13 -> 0 | L13: =(J13+G13)-K13 -> 0 | N13: =IF(M13>0,SUM(L13-M13)," ") | O13: 440 | R13: =IF(O13>0,SUM(O13-(L13+P13))," ") -> 440 | S13: =P13-Q13 -> 0 | T13: A VISTA | U13: 30 | V13: FOB | W13: QUITACAO CREDITO | AA13: =AA8-(SUM(AA9:AA12)) -> 126290
A14: 44992 | C14: DEMETRIU | E14: 6 | F14: 860 | G14: =(F14*D14)+(E14*F14) -> 5160 | J14: =H14*I14 -> 0 | L14: =(J14+G14)-K14 -> 5160 | N14: =IF(M14>0,SUM(L14-M14)," ") | R14: =IF(O14>0,SUM(O14-(L14+P14))," ")
A15: 44992 | C15: ROBERTO LAGOA DO BANANA | E15: 1 | F15: 880 | G15: =(F15*D15)+(E15*F15) -> 880 | J15: =H15*I15 -> 0 | L15: =(J15+G15)-K15 -> 880 | N15: =IF(M15>0,SUM(L15-M15)," ") | R15: =IF(O15>0,SUM(O15-(L15+P15))," ")
A16: 44992 | C16: FELIPE | D16: 2 | F16: 900 | G16: =(F16*D16)+(E16*F16) -> 1800 | J16: =H16*I16 -> 0 | L16: =(J16+G16)-K16 -> 1800 | N16: =IF(M16>0,SUM(L16-M16)," ") | R16: =IF(O16>0,SUM(O16-(L16+P16))," ")
A17: 44993 | C17: EVALDO SANTA INES | E17: 4 | F17: 860 | G17: =(F17*D17)+(E17*F17) -> 3440 | J17: =H17*I17 -> 0 | L17: =(J17+G17)-K17 -> 3440 | N17: =IF(M17>0,SUM(L17-M17)," ") | R17: =IF(O17>0,SUM(O17-(L17+P17))," ")
A18: 44993 | C18: ARG ROMA | E18: 4 | F18: 860 | G18: =(F18*D18)+(E18*F18) -> 3440 | J18: =H18*I18 -> 0 | L18: =(J18+G18)-K18 -> 3440 | N18: =IF(M18>0,SUM(L18-M18)," ") | R18: =IF(O18>0,SUM(O18-(L18+P18))," ")
A19: 44994 | C19: MULTCOLA | E19: 4 | F19: 860 | G19: =(F19*D19)+(E19*F19) -> 3440 | J19: =H19*I19 -> 0 | L19: =(J19+G19)-K19 -> 3440 | N19: =IF(M19>0,SUM(L19-M19)," ") | R19: =IF(O19>0,SUM(O19-(L19+P19))," ")
A20: 44995 | C20: MOEBIO IGUATU | D20: 1 | F20: 860 | G20: =(F20*D20)+(E20*F20) -> 860 | J20: =H20*I20 -> 0 | L20: =(J20+G20)-K20 -> 860 | N20: =IF(M20>0,SUM(L20-M20)," ") | R20: =IF(O20>0,SUM(O20-(L20+P20))," ")
A21: 44995 | C21: LOURIMAR | D21: 4 | F21: 900 | G21: =(F21*D21)+(E21*F21) -> 3600 | J21: =H21*I21 -> 0 | L21: =(J21+G21)-K21 -> 3600 | N21: =IF(M21>0,SUM(L21-M21)," ") | R21: =IF(O21>0,SUM(O21-(L21+P21))," ")
A22: 44995 | C22: CLAUDIO MOSSORO | D22: 8 | F22: 860 | G22: =(F22*D22)+(E22*F22) -> 6880 | J22: =H22*I22 -> 0 | L22: =(J22+G22)-K22 -> 6880 | N22: =IF(M22>0,SUM(L22-M22)," ") | R22: =IF(O22>0,SUM(O22-(L22+P22))," ")
A23: 44996 | C23: GETULIO | D23: 2 | F23: 880 | G23: =(F23*D23)+(E23*F23) -> 1760 | J23: =H23*I23 -> 0 | L23: =(J23+G23)-K23 -> 1760 | N23: =IF(M23>0,SUM(L23-M23)," ") | R23: =IF(O23>0,SUM(O23-(L23+P23))," ")
A24: 44996 | C24: EVALDO SANTA INES | D24: 4 | F24: 860 | G24: =(F24*D24)+(E24*F24) -> 3440 | J24: =H24*I24 -> 0 | L24: =(J24+G24)-K24 -> 3440 | N24: =IF(M24>0,SUM(L24-M24)," ") | R24: =IF(O24>0,SUM(O24-(L24+P24))," ")
A25: 44998 | C25: DEMETRIU | E25: 6 | F25: 860 | G25: =(F25*D25)+(E25*F25) -> 5160 | J25: =H25*I25 -> 0 | L25: =(J25+G25)-K25 -> 5160 | N25: =IF(M25>0,SUM(L25-M25)," ") | R25: =IF(O25>0,SUM(O25-(L25+P25))," ")
A26: 44998 | C26: CHICO PEREIRA | E26: 2 | F26: 880 | G26: =(F26*D26)+(E26*F26) -> 1760 | J26: =H26*I26 -> 0 | L26: =(J26+G26)-K26 -> 1760 | N26: =IF(M26>0,SUM(L26-M26)," ") | R26: =IF(O26>0,SUM(O26-(L26+P26))," ")
A27: 44999 | C27: FELIPE | D27: 1 | F27: 900 | G27: =(F27*D27)+(E27*F27) -> 900 | J27: =H27*I27 -> 0 | L27: =(J27+G27)-K27 -> 900 | N27: =IF(M27>0,SUM(L27-M27)," ") | R27: =IF(O27>0,SUM(O27-(L27+P27))," ")
A28: 44999 | C28: JOSIEL | D28: 1 | F28: 900 | G28: =(F28*D28)+(E28*F28) -> 900 | J28: =H28*I28 -> 0 | L28: =(J28+G28)-K28 -> 900 | N28: =IF(M28>0,SUM(L28-M28)," ") | R28: =IF(O28>0,SUM(O28-(L28+P28))," ")
A29: 45000 | C29: EVALDO SANTA INES | D29: 4 | F29: 860 | G29: =(F29*D29)+(E29*F29) -> 3440 | J29: =H29*I29 -> 0 | L29: =(J29+G29)-K29 -> 3440 | N29: =IF(M29>0,SUM(L29-M29)," ") | R29: =IF(O29>0,SUM(O29-(L29+P29))," ")
A30: 45000 | C30: GETULIO | D30: 1 | F30: 880 | G30: =(F30*D30)+(E30*F30) -> 880 | J30: =H30*I30 -> 0 | L30: =(J30+G30)-K30 -> 880 | N30: =IF(M30>0,SUM(L30-M30)," ") | R30: =IF(O30>0,SUM(O30-(L30+P30))," ")
A31: 45001 | C31: IRINEU | D31: 1 | F31: 880 | G31: =(F31*D31)+(E31*F31) -> 880 | J31: =H31*I31 -> 0 | L31: =(J31+G31)-K31 -> 880 | N31: =IF(M31>0,SUM(L31-M31)," ") | R31: =IF(O31>0,SUM(O31-(L31+P31))," ")
A32: 45001 | C32: MASSA FIXA | D32: 2 | F32: 880 | G32: =(F32*D32)+(E32*F32) -> 1760 | J32: =H32*I32 -> 0 | L32: =(J32+G32)-K32 -> 1760 | N32: =IF(M32>0,SUM(L32-M32)," ") | R32: =IF(O32>0,SUM(O32-(L32+P32))," ")
A33: 45002 | C33: LOURIMAR | E33: 4 | F33: 900 | G33: =(F33*D33)+(E33*F33) -> 3600 | J33: =H33*I33 -> 0 | L33: =(J33+G33)-K33 -> 3600 | N33: =IF(M33>0,SUM(L33-M33)," ") | R33: =IF(O33>0,SUM(O33-(L33+P33))," ")
A34: 45003 | C34: EVALDO SANTA INES | D34: 4 | F34: 860 | G34: =(F34*D34)+(E34*F34) -> 3440 | J34: =H34*I34 -> 0 | L34: =(J34+G34)-K34 -> 3440 | N34: =IF(M34>0,SUM(L34-M34)," ") | R34: =IF(O34>0,SUM(O34-(L34+P34))," ")
A35: 45003 | C35: ARG ROMA | D35: 3 | F35: 860 | G35: =(F35*D35)+(E35*F35) -> 2580 | J35: =H35*I35 -> 0 | L35: =(J35+G35)-K35 -> 2580 | N35: =IF(M35>0,SUM(L35-M35)," ") | R35: =IF(O35>0,SUM(O35-(L35+P35))," ")
A36: 45006 | C36: DEMETRIU | E36: 6 | F36: 860 | G36: =(F36*D36)+(E36*F36) -> 5160 | J36: =H36*I36 -> 0 | L36: =(J36+G36)-K36 -> 5160 | N36: =IF(M36>0,SUM(L36-M36)," ") | R36: =IF(O36>0,SUM(O36-(L36+P36))," ")
A37: 45006 | C37: FELIPE | D37: 2 | F37: 900 | G37: =(F37*D37)+(E37*F37) -> 1800 | J37: =H37*I37 -> 0 | L37: =(J37+G37)-K37 -> 1800 | N37: =IF(M37>0,SUM(L37-M37)," ") | R37: =IF(O37>0,SUM(O37-(L37+P37))," ")
A38: 45006 | C38: MASSA FIXA | E38: 2 | F38: 880 | G38: =(F38*D38)+(E38*F38) -> 1760 | J38: =H38*I38 -> 0 | L38: =(J38+G38)-K38 -> 1760 | N38: =IF(M38>0,SUM(L38-M38)," ") | R38: =IF(O38>0,SUM(O38-(L38+P38))," ")
F39: 870 | G39: =(F39*D39)+(E39*F39) -> 0 | J39: =H39*I39 -> 0 | L39: =(J39+G39)-K39 -> 0 | N39: =IF(M39>0,SUM(L39-M39)," ") | R39: =IF(O39>0,SUM(O39-(L39+P39))," ")
A40: 45007 | C40: GETULIO | D40: 3 | F40: 880 | G40: =(F40*D40)+(E40*F40) -> 2640 | J40: =H40*I40 -> 0 | L40: =(J40+G40)-K40 -> 2640 | N40: =IF(M40>0,SUM(L40-M40)," ") | R40: =IF(O40>0,SUM(O40-(L40+P40))," ")
G41: =(F41*D41)+(E41*F41) -> 0 | J41: =H41*I41 -> 0 | L41: =(J41+G41)-K41 -> 0 | N41: =IF(M41>0,SUM(L41-M41)," ") | R41: =IF(O41>0,SUM(O41-(L41+P41))," ")
A42: 45007 | C42: EVALDO SANTA INES | D42: 4 | F42: 860 | G42: =(F42*D42)+(E42*F42) -> 3440 | J42: =H42*I42 -> 0 | L42: =(J42+G42)-K42 -> 3440 | N42: =IF(M42>0,SUM(L42-M42)," ") | R42: =IF(O42>0,SUM(O42-(L42+P42))," ")
A43: 45007 | C43: THIAGO TIANGUA | E43: 1 | F43: 900 | G43: =(F43*D43)+(E43*F43) -> 900 | J43: =H43*I43 -> 0 | L43: =(J43+G43)-K43 -> 900 | N43: =IF(M43>0,SUM(L43-M43)," ") | R43: =IF(O43>0,SUM(O43-(L43+P43))," ")
A44: 45007 | C44: LUIZ PI | E44: 2 | F44: 880 | G44: =(F44*D44)+(E44*F44) -> 1760 | J44: =H44*I44 -> 0 | L44: =(J44+G44)-K44 -> 1760 | N44: =IF(M44>0,SUM(L44-M44)," ") | R44: =IF(O44>0,SUM(O44-(L44+P44))," ")
A45: 45007 | C45: ROBERTO LAGOA DO BANANA | E45: 1 | F45: 880 | G45: =(F45*D45)+(E45*F45) -> 880 | J45: =H45*I45 -> 0 | L45: =(J45+G45)-K45 -> 880 | N45: =IF(M45>0,SUM(L45-M45)," ") | R45: =IF(O45>0,SUM(O45-(L45+P45))," ")
A46: 45007 | C46: TODA OBRA | E46: 4 | F46: 880 | G46: =(F46*D46)+(E46*F46) -> 3520 | J46: =H46*I46 -> 0 | L46: =(J46+G46)-K46 -> 3520 | N46: =IF(M46>0,SUM(L46-M46)," ") | R46: =IF(O46>0,SUM(O46-(L46+P46))," ")
A47: 45008 | C47: IRINEU | D47: 1 | F47: 880 | G47: =(F47*D47)+(E47*F47) -> 880 | J47: =H47*I47 -> 0 | L47: =(J47+G47)-K47 -> 880 | N47: =IF(M47>0,SUM(L47-M47)," ") | R47: =IF(O47>0,SUM(O47-(L47+P47))," ")
A48: 45010 | C48: EVALDO SANTA INES | D48: 3 | F48: 860 | G48: =(F48*D48)+(E48*F48) -> 2580 | J48: =H48*I48 -> 0 | L48: =(J48+G48)-K48 -> 2580 | N48: =IF(M48>0,SUM(L48-M48)," ") | R48: =IF(O48>0,SUM(O48-(L48+P48))," ")
A49: 45012 | C49: IRINEU | D49: 1 | F49: 880 | G49: =(F49*D49)+(E49*F49) -> 880 | J49: =H49*I49 -> 0 | L49: =(J49+G49)-K49 -> 880 | N49: =IF(M49>0,SUM(L49-M49)," ") | R49: =IF(O49>0,SUM(O49-(L49+P49))," ")
A50: 45013 | C50: CLAUDIO MOSSORO | D50: 8 | F50: 860 | G50: =(F50*D50)+(E50*F50) -> 6880 | J50: =H50*I50 -> 0 | L50: =(J50+G50)-K50 -> 6880 | N50: =IF(M50>0,SUM(L50-M50)," ") | R50: =IF(O50>0,SUM(O50-(L50+P50))," ")
A51: 45014 | C51: FELIPE | D51: 1 | F51: 900 | G51: =(F51*D51)+(E51*F51) -> 900 | J51: =H51*I51 -> 0 | L51: =(J51+G51)-K51 -> 900 | N51: =IF(M51>0,SUM(L51-M51)," ") | R51: =IF(O51>0,SUM(O51-(L51+P51))," ")
A52: 45014 | C52: LOURIMAR | E52: 4 | F52: 900 | G52: =(F52*D52)+(E52*F52) -> 3600 | J52: =H52*I52 -> 0 | L52: =(J52+G52)-K52 -> 3600 | N52: =IF(M52>0,SUM(L52-M52)," ") | R52: =IF(O52>0,SUM(O52-(L52+P52))," ")
A53: 45015 | C53: MOEBIO IGUATU | E53: 1 | F53: 860 | G53: =(F53*D53)+(E53*F53) -> 860 | J53: =H53*I53 -> 0 | L53: =(J53+G53)-K53 -> 860 | N53: =IF(M53>0,SUM(L53-M53)," ") | R53: =IF(O53>0,SUM(O53-(L53+P53))," ")
A54: 45016 | C54: THIAGO TIANGUA | E54: 1 | F54: 900 | G54: =(F54*D54)+(E54*F54) -> 900 | J54: =H54*I54 -> 0 | L54: =(J54+G54)-K54 -> 900 | N54: =IF(M54>0,SUM(L54-M54)," ") | R54: =IF(O54>0,SUM(O54-(L54+P54))," ")
A55: 45016 | C55: GETULIO | D55: 1 | F55: 880 | G55: =(F55*D55)+(E55*F55) -> 880 | J55: =H55*I55 -> 0 | L55: =(J55+G55)-K55 -> 880 | N55: =IF(M55>0,SUM(L55-M55)," ") | R55: =IF(O55>0,SUM(O55-(L55+P55))," ")
A56: 45016 | C56: MASSA FIXA | D56: 3 | F56: 880 | G56: =(F56*D56)+(E56*F56) -> 2640 | J56: =H56*I56 -> 0 | L56: =(J56+G56)-K56 -> 2640 | N56: =IF(M56>0,SUM(L56-M56)," ") | R56: =IF(O56>0,SUM(O56-(L56+P56))," ")
A57: 45017 | C57: GETULIO | D57: 1 | F57: 880 | G57: =(F57*D57)+(E57*F57) -> 880 | J57: =H57*I57 -> 0 | L57: =(J57+G57)-K57 -> 880 | N57: =IF(M57>0,SUM(L57-M57)," ") | R57: =IF(O57>0,SUM(O57-(L57+P57))," ")
A58: 45017 | C58: EVALDO SANTA INES | D58: 4 | F58: 860 | G58: =(F58*D58)+(E58*F58) -> 3440 | J58: =H58*I58 -> 0 | L58: =(J58+G58)-K58 -> 3440 | N58: =IF(M58>0,SUM(L58-M58)," ") | R58: =IF(O58>0,SUM(O58-(L58+P58))," ")
A59: 45019 | C59: DEMETRIU | D59: 2 | F59: 840 | G59: =(F59*D59)+(E59*F59) -> 1680 | J59: =H59*I59 -> 0 | L59: =(J59+G59)-K59 -> 1680 | N59: =IF(M59>0,SUM(L59-M59)," ") | R59: =IF(O59>0,SUM(O59-(L59+P59))," ")
F60: 860 | G60: =(F60*D60)+(E60*F60) -> 0 | J60: =H60*I60 -> 0 | L60: =(J60+G60)-K60 -> 0 | N60: =IF(M60>0,SUM(L60-M60)," ") | R60: =IF(O60>0,SUM(O60-(L60+P60))," ")
F61: 870 | G61: =(F61*D61)+(E61*F61) -> 0 | J61: =H61*I61 -> 0 | L61: =(J61+G61)-K61 -> 0 | N61: =IF(M61>0,SUM(L61-M61)," ") | R61: =IF(O61>0,SUM(O61-(L61+P61))," ")
F62: 880 | G62: =(F62*D62)+(E62*F62) -> 0 | J62: =H62*I62 -> 0 | L62: =(J62+G62)-K62 -> 0 | N62: =IF(M62>0,SUM(L62-M62)," ") | R62: =IF(O62>0,SUM(O62-(L62+P62))," ")
F63: 800 | G63: =(F63*D63)+(E63*F63) -> 0 | J63: =H63*I63 -> 0 | L63: =(J63+G63)-K63 -> 0 | N63: =IF(M63>0,SUM(L63-M63)," ") | R63: =IF(O63>0,SUM(O63-(L63+P63))," ")
F64: 800 | G64: =(F64*D64)+(E64*F64) -> 0 | J64: =H64*I64 -> 0 | L64: =(J64+G64)-K64 -> 0 | N64: =IF(M64>0,SUM(L64-M64)," ") | R64: =IF(O64>0,SUM(O64-(L64+P64))," ")
F65: 800 | G65: =(F65*D65)+(E65*F65) -> 0 | J65: =H65*I65 -> 0 | L65: =(J65+G65)-K65 -> 0 | N65: =IF(M65>0,SUM(L65-M65)," ") | R65: =IF(O65>0,SUM(O65-(L65+P65))," ")
F66: 800 | G66: =(F66*D66)+(E66*F66) -> 0 | J66: =H66*I66 -> 0 | L66: =(J66+G66)-K66 -> 0 | N66: =IF(M66>0,SUM(L66-M66)," ") | R66: =IF(O66>0,SUM(O66-(L66+P66))," ")
F67: 800 | G67: =(F67*D67)+(E67*F67) -> 0 | J67: =H67*I67 -> 0 | L67: =(J67+G67)-K67 -> 0 | N67: =IF(M67>0,SUM(L67-M67)," ") | R67: =IF(O67>0,SUM(O67-(L67+P67))," ")
F68: 800 | G68: =(F68*D68)+(E68*F68) -> 0 | J68: =H68*I68 -> 0 | L68: =(J68+G68)-K68 -> 0 | N68: =IF(M68>0,SUM(L68-M68)," ") | R68: =IF(O68>0,SUM(O68-(L68+P68))," ")
F69: 800 | G69: =(F69*D69)+(E69*F69) -> 0 | J69: =H69*I69 -> 0 | L69: =(J69+G69)-K69 -> 0 | N69: =IF(M69>0,SUM(L69-M69)," ") | R69: =IF(O69>0,SUM(O69-(L69+P69))," ")
F70: 800 | G70: =(F70*D70)+(E70*F70) -> 0 | J70: =H70*I70 -> 0 | L70: =(J70+G70)-K70 -> 0 | N70: =IF(M70>0,SUM(L70-M70)," ") | R70: =IF(O70>0,SUM(O70-(L70+P70))," ")
F71: 800 | G71: =(F71*D71)+(E71*F71) -> 0 | J71: =H71*I71 -> 0 | L71: =(J71+G71)-K71 -> 0 | N71: =IF(M71>0,SUM(L71-M71)," ") | R71: =IF(O71>0,SUM(O71-(L71+P71))," ")
... F100: 800 | G100: =(F100*D100)+(E100*F100) -> 0 | J100: =H100*I100 -> 0 | L100: =(J100+G100)-K100 -> 0 | N100: =IF(M100>0,SUM(L100-M100)," ") | R100: =IF(O100>0,SUM(O100-(L100+P100))," ")
D101: =SUM(D4:D100) -> 92 | E101: =SUM(E4:E100) -> 53 | G101: =SUM(G4:G100) -> 126290 | H101: =SUM(H4:H100) -> 0 | J101: =SUM(J4:J100) -> 0 | L101: =SUM(L4:L100) -> 126290 | N101: =IF(M101>0,SUM(L101-M101)," ") | O101: =SUM(O4:O100) -> 1840 | P101: =SUM(P4:P100) -> 0 | Q101: =SUM(Q4:Q100) -> 0 | R101: =SUM(R4:R100) -> -1600 | S101: =SUM(S4:S100) -> 0
D102: =D101+E101 -> 145
C108: CLEZIO - DURAPLIK
C109: DEMETRIUS - ULTRAMASSA
C110: CLEZIO - DURAPLIK
C111: RAPOSÃO - MASSA FORTE
C112: GETULIA - JOSE WALTER
C113: CLAUDIO - MOSSORO
C114: CLEZIO - DURAPLIK
C115: CLEZIO - DURAPLIK
C116: CLEZIO - DURAPLIK
C117: DEMETRIUS - ULTRAMASSA
C120: AREMIX
C121: THIAGO - TIANGUA
... C137: CLAUDIO - MOSSORO

Sheet Vendas - ABR
A1: VENDAS | B1: VENDAS | D1: =D102 -> 125
A2: DATA | B2: VENDEDOR | C2: Clientes - 35 | D2: CELULOSE | H2: POLÍMERO | K2: DESCONTO CHEQUE | L2: TOTAL | M2: PARCIAL | N2: DEVENDO | O2: CHEQUES / PAGAMENTOS A MAIS OU A MENOS | T2: Forma de Pagamento | U2: Prazo | V2: Frete CIF / FOB | W2: OBSERVAÇÃO | X2: OBSERVAÇÃO
D3: PALOMA | E3: UCHOA | F3: PREÇO | G3: TOTAL | H3: QTD | I3: PREÇO TAB | J3: TOTAL | O3: VALOR VENDA | P3: COBRAMOS % | Q3: PAGAMOS % | R3: SALDO/DEBITO CLIENTE | S3: LUCRO/PREJ JUROS
A4: 45019 | C4: DEMETRIU | D4: 4 | F4: 840 | G4: =(F4*D4)+(E4*F4) -> 3360 | J4: =H4*I4 -> 0 | L4: =(J4+G4)-K4 -> 3360 | N4: =IF(M4>0,SUM(L4-M4)," ") | R4: =IF(O4>0,SUM(O4-(L4+P4))," ") | T4: A VISTA | U4: 0 | V4: FOB
A5: 45020 | C5: GETULIO | D5: 1 | F5: 880 | G5: =(F5*D5)+(E5*F5) -> 880 | J5: =H5*I5 -> 0 | L5: =(J5+G5)-K5 -> 880 | N5: =IF(M5>0,SUM(L5-M5)," ") | R5: =IF(O5>0,SUM(O5-(L5+P5))," ") | T5: A VISTA | U5: 0 | V5: FOB
A6: 45021 | C6: IRINEU | D6: 1 | F6: 880 | G6: =(F6*D6)+(E6*F6) -> 880 | J6: =H6*I6 -> 0 | L6: =(J6+G6)-K6 -> 880 | N6: =IF(M6>0,SUM(L6-M6)," ") | R6: =IF(O6>0,SUM(O6-(L6+P6))," ") | T6: A VISTA | U6: 0 | V6: FOB
F7: 880 | G7: =(F7*D7)+(E7*F7) -> 0 | J7: =H7*I7 -> 0 | L7: =(J7+G7)-K7 -> 0 | N7: =IF(M7>0,SUM(L7-M7)," ") | R7: =IF(O7>0,SUM(O7-(L7+P7))," ") | T7: A VISTA | U7: 0 | V7: FOB
A8: 45021 | C8: EVALDO SANTA INES | D8: 6 | F8: 860 | G8: =(F8*D8)+(E8*F8) -> 5160 | J8: =H8*I8 -> 0 | L8: =(J8+G8)-K8 -> 5160 | N8: =IF(M8>0,SUM(L8-M8)," ") | O8: 1400 | R8: =IF(O8>0,SUM(O8-(L8+P8))," ") -> -3760 | T8: CHEQUE/R$ | U8: 0 | V8: FOB | W8: 1100 + 300 | Y8: VALOR | Z8: QTD | AA8: =G101 -> 107660
A9: 45022 | C9: CHICO PEREIRA | E9: 2 | F9: 880 | G9: =(F9*D9)+(E9*F9) -> 1760 | J9: =H9*I9 -> 0 | L9: =(J9+G9)-K9 -> 1760 | N9: =IF(M9>0,SUM(L9-M9)," ") | R9: =IF(O9>0,SUM(O9-(L9+P9))," ") | T9: A VISTA | U9: 0 | V9: FOB | Y9: 720 | AA9: =Y9*Z9 -> 0
A10: 45027 | C10: MOEBIO | D10: 1 | F10: 860 | G10: =(F10*D10)+(E10*F10) -> 860 | J10: =H10*I10 -> 0 | L10: =(J10+G10)-K10 -> 860 | N10: =IF(M10>0,SUM(L10-M10)," ") | R10: =IF(O10>0,SUM(O10-(L10+P10))," ") | T10: A VISTA | U10: 0 | V10: FOB | Y10: 750 | AA10: =Y10*Z10 -> 0
A11: 45027 | C11: FELIPE | D11: 1 | F11: 900 | G11: =(F11*D11)+(E11*F11) -> 900 | J11: =H11*I11 -> 0 | L11: =(J11+G11)-K11 -> 900 | N11: =IF(M11>0,SUM(L11-M11)," ") | R11: =IF(O11>0,SUM(O11-(L11+P11))," ") | T11: A VISTA | U11: 0 | V11: FOB | Y11: 780 | AA11: =Y11*Z11 -> 0
A12: 45027 | C12: JOSIEL | D12: 1 | F12: 900 | G12: =(F12*D12)+(E12*F12) -> 900 | J12: =H12*I12 -> 0 | L12: =(J12+G12)-K12 -> 900 | N12: =IF(M12>0,SUM(L12-M12)," ") | R12: =IF(O12>0,SUM(O12-(L12+P12))," ") | T12: A VISTA | U12: 0 | V12: FOB | Y12: 800 | AA12: =Y12*Z12 -> 0
A13: 45027 | C13: AREMIX | E13: 10 | F13: 850 | G13: =(F13*D13)+(E13*F13) -> 8500 | J13: =H13*I13 -> 0 | L13: =(J13+G13)-K13 -> 8500 | N13: =IF(M13>0,SUM(L13-M13)," ") | O13: 440 | R13: =IF(O13>0,SUM(O13-(L13+P13))," ") -> -8060 | S13: =P13-Q13 -> 0 | T13: A VISTA | U13: 30 | V13: FOB | W13: QUITACAO CREDITO | AA13: =AA8-(SUM(AA9:AA12)) -> 107660
A14: 45027 | C14: CEARAMIX | E14: 1 | F14: 900 | G14: =(F14*D14)+(E14*F14) -> 900 | J14: =H14*I14 -> 0 | L14: =(J14+G14)-K14 -> 900 | N14: =IF(M14>0,SUM(L14-M14)," ") | R14: =IF(O14>0,SUM(O14-(L14+P14))," ")
A15: 45027 | C15: LOURIMAR | E15: 2 | F15: 900 | G15: =(F15*D15)+(E15*F15) -> 1800 | J15: =H15*I15 -> 0 | L15: =(J15+G15)-K15 -> 1800 | N15: =IF(M15>0,SUM(L15-M15)," ") | R15: =IF(O15>0,SUM(O15-(L15+P15))," ")
A16: 45028 | C16: CONSTRUMIX | E16: 2 | F16: 860 | G16: =(F16*D16)+(E16*F16) -> 1720 | J16: =H16*I16 -> 0 | L16: =(J16+G16)-K16 -> 1720 | N16: =IF(M16>0,SUM(L16-M16)," ") | R16: =IF(O16>0,SUM(O16-(L16+P16))," ")
A17: 45028 | C17: IRINEU | D17: 1 | F17: 880 | G17: =(F17*D17)+(E17*F17) -> 880 | J17: =H17*I17 -> 0 | L17: =(J17+G17)-K17 -> 880 | N17: =IF(M17>0,SUM(L17-M17)," ") | R17: =IF(O17>0,SUM(O17-(L17+P17))," ")
A18: 45028 | C18: FORTMASSA | D18: 1 | F18: 880 | G18: =(F18*D18)+(E18*F18) -> 880 | J18: =H18*I18 -> 0 | L18: =(J18+G18)-K18 -> 880 | N18: =IF(M18>0,SUM(L18-M18)," ") | R18: =IF(O18>0,SUM(O18-(L18+P18))," ")
A19: 45029 | C19: DEMETRIU | E19: 7 | F19: 840 | G19: =(F19*D19)+(E19*F19) -> 5880 | J19: =H19*I19 -> 0 | L19: =(J19+G19)-K19 -> 5880 | N19: =IF(M19>0,SUM(L19-M19)," ") | R19: =IF(O19>0,SUM(O19-(L19+P19))," ")
A20: 45029 | C20: GETULIO | D20: 2 | F20: 880 | G20: =(F20*D20)+(E20*F20) -> 1760 | J20: =H20*I20 -> 0 | L20: =(J20+G20)-K20 -> 1760 | N20: =IF(M20>0,SUM(L20-M20)," ") | R20: =IF(O20>0,SUM(O20-(L20+P20))," ")
A21: 45032 | C21: REGINALDO LAGOA DO BANANA | E21: 1 | F21: 880 | G21: =(F21*D21)+(E21*F21) -> 880 | J21: =H21*I21 -> 0 | L21: =(J21+G21)-K21 -> 880 | N21: =IF(M21>0,SUM(L21-M21)," ") | R21: =IF(O21>0,SUM(O21-(L21+P21))," ")
A22: 45032 | C22: LOURIMAR | D22: 2 | F22: 880 | G22: =(F22*D22)+(E22*F22) -> 1760 | J22: =H22*I22 -> 0 | L22: =(J22+G22)-K22 -> 1760 | N22: =IF(M22>0,SUM(L22-M22)," ") | R22: =IF(O22>0,SUM(O22-(L22+P22))," ")
A23: 45032 | C23: EVALDO SANTA INES | D23: 4 | F23: 860 | G23: =(F23*D23)+(E23*F23) -> 3440 | J23: =H23*I23 -> 0 | L23: =(J23+G23)-K23 -> 3440 | N23: =IF(M23>0,SUM(L23-M23)," ") | R23: =IF(O23>0,SUM(O23-(L23+P23))," ")
A24: 45033 | C24: FORTMASSA | E24: 1 | F24: 880 | G24: =(F24*D24)+(E24*F24) -> 880 | J24: =H24*I24 -> 0 | L24: =(J24+G24)-K24 -> 880 | N24: =IF(M24>0,SUM(L24-M24)," ") | R24: =IF(O24>0,SUM(O24-(L24+P24))," ")
A25: 45034 | C25: GETULIO | D25: 1 | F25: 880 | G25: =(F25*D25)+(E25*F25) -> 880 | J25: =H25*I25 -> 0 | L25: =(J25+G25)-K25 -> 880 | N25: =IF(M25>0,SUM(L25-M25)," ") | R25: =IF(O25>0,SUM(O25-(L25+P25))," ")
A26: 45034 | C26: FELIPE | D26: 2 | F26: 900 | G26: =(F26*D26)+(E26*F26) -> 1800 | J26: =H26*I26 -> 0 | L26: =(J26+G26)-K26 -> 1800 | N26: =IF(M26>0,SUM(L26-M26)," ") | R26: =IF(O26>0,SUM(O26-(L26+P26))," ")
A27: 45034 | C27: ANDRE | E27: 1 | F27: 900 | G27: =(F27*D27)+(E27*F27) -> 900 | J27: =H27*I27 -> 0 | L27: =(J27+G27)-K27 -> 900 | N27: =IF(M27>0,SUM(L27-M27)," ") | R27: =IF(O27>0,SUM(O27-(L27+P27))," ")
A28: 45034 | C28: LOURIMAR | E28: 4 | F28: 880 | G28: =(F28*D28)+(E28*F28) -> 3520 | J28: =H28*I28 -> 0 | L28: =(J28+G28)-K28 -> 3520 | N28: =IF(M28>0,SUM(L28-M28)," ") | R28: =IF(O28>0,SUM(O28-(L28+P28))," ")
A29: 45035 | C29: DEMETRIU | E29: 6 | F29: 840 | G29: =(F29*D29)+(E29*F29) -> 5040 | J29: =H29*I29 -> 0 | L29: =(J29+G29)-K29 -> 5040 | N29: =IF(M29>0,SUM(L29-M29)," ") | R29: =IF(O29>0,SUM(O29-(L29+P29))," ")
A30: 45035 | C30: CLAUDIO MOSSORO | D30: 8 | F30: 860 | G30: =(F30*D30)+(E30*F30) -> 6880 | J30: =H30*I30 -> 0 | L30: =(J30+G30)-K30 -> 6880 | N30: =IF(M30>0,SUM(L30-M30)," ") | R30: =IF(O30>0,SUM(O30-(L30+P30))," ")
A31: 45035 | C31: GETULIO | D31: 1 | F31: 880 | G31: =(F31*D31)+(E31*F31) -> 880 | J31: =H31*I31 -> 0 | L31: =(J31+G31)-K31 -> 880 | N31: =IF(M31>0,SUM(L31-M31)," ") | R31: =IF(O31>0,SUM(O31-(L31+P31))," ")
A32: 45035 | C32: IRINEU | D32: 1 | F32: 880 | G32: =(F32*D32)+(E32*F32) -> 880 | J32: =H32*I32 -> 0 | L32: =(J32+G32)-K32 -> 880 | N32: =IF(M32>0,SUM(L32-M32)," ") | R32: =IF(O32>0,SUM(O32-(L32+P32))," ")
A33: 45035 | C33: FORTMASSA | D33: 1 | F33: 880 | G33: =(F33*D33)+(E33*F33) -> 880 | J33: =H33*I33 -> 0 | L33: =(J33+G33)-K33 -> 880 | N33: =IF(M33>0,SUM(L33-M33)," ") | R33: =IF(O33>0,SUM(O33-(L33+P33))," ")
A34: 45040 | C34: GETULIO | E34: 2 | F34: 880 | G34: =(F34*D34)+(E34*F34) -> 1760 | J34: =H34*I34 -> 0 | L34: =(J34+G34)-K34 -> 1760 | N34: =IF(M34>0,SUM(L34-M34)," ") | R34: =IF(O34>0,SUM(O34-(L34+P34))," ")
A35: 45042 | C35: TODA OBRA | E35: 2 | F35: 860 | G35: =(F35*D35)+(E35*F35) -> 1720 | J35: =H35*I35 -> 0 | L35: =(J35+G35)-K35 -> 1720 | N35: =IF(M35>0,SUM(L35-M35)," ") | R35: =IF(O35>0,SUM(O35-(L35+P35))," ")
A36: 45042 | C36: AREMIX | E36: 10 | F36: 850 | G36: =(F36*D36)+(E36*F36) -> 8500 | J36: =H36*I36 -> 0 | L36: =(J36+G36)-K36 -> 8500 | N36: =IF(M36>0,SUM(L36-M36)," ") | R36: =IF(O36>0,SUM(O36-(L36+P36))," ")
A37: 45042 | C37: GETULIO | D37: 2 | F37: 880 | G37: =(F37*D37)+(E37*F37) -> 1760 | J37: =H37*I37 -> 0 | L37: =(J37+G37)-K37 -> 1760 | N37: =IF(M37>0,SUM(L37-M37)," ") | R37: =IF(O37>0,SUM(O37-(L37+P37))," ")
F38: 900 | G38: =(F38*D38)+(E38*F38) -> 0 | J38: =H38*I38 -> 0 | L38: =(J38+G38)-K38 -> 0 | N38: =IF(M38>0,SUM(L38-M38)," ") | R38: =IF(O38>0,SUM(O38-(L38+P38))," ")
A39: 45042 | C39: FELIPE | D39: 2 | F39: 900 | G39: =(F39*D39)+(E39*F39) -> 1800 | J39: =H39*I39 -> 0 | L39: =(J39+G39)-K39 -> 1800 | N39: =IF(M39>0,SUM(L39-M39)," ") | R39: =IF(O39>0,SUM(O39-(L39+P39))," ")
A40: 45042 | C40: ARG MATHEUS | E40: 2 | F40: 860 | G40: =(F40*D40)+(E40*F40) -> 1720 | J40: =H40*I40 -> 0 | L40: =(J40+G40)-K40 -> 1720 | N40: =IF(M40>0,SUM(L40-M40)," ") | R40: =IF(O40>0,SUM(O40-(L40+P40))," ")
A41: 45043 | C41: ELIEL | D41: 10 | F41: 840 | G41: =(F41*D41)+(E41*F41) -> 8400 | J41: =H41*I41 -> 0 | L41: =(J41+G41)-K41 -> 8400 | N41: =IF(M41>0,SUM(L41-M41)," ") | R41: =IF(O41>0,SUM(O41-(L41+P41))," ")
A42: 45043 | C42: GETULIO | D42: 1 | F42: 880 | G42: =(F42*D42)+(E42*F42) -> 880 | J42: =H42*I42 -> 0 | L42: =(J42+G42)-K42 -> 880 | N42: =IF(M42>0,SUM(L42-M42)," ") | R42: =IF(O42>0,SUM(O42-(L42+P42))," ")
A43: 45042 | C43: IRINEU | D43: 1 | F43: 880 | G43: =(F43*D43)+(E43*F43) -> 880 | J43: =H43*I43 -> 0 | L43: =(J43+G43)-K43 -> 880 | N43: =IF(M43>0,SUM(L43-M43)," ") | R43: =IF(O43>0,SUM(O43-(L43+P43))," ")
A44: 45043 | C44: FORTMASSA | D44: 1 | F44: 880 | G44: =(F44*D44)+(E44*F44) -> 880 | J44: =H44*I44 -> 0 | L44: =(J44+G44)-K44 -> 880 | N44: =IF(M44>0,SUM(L44-M44)," ") | R44: =IF(O44>0,SUM(O44-(L44+P44))," ")
A45: 45043 | C45: LOURIMAR | E45: 4 | F45: 880 | G45: =(F45*D45)+(E45*F45) -> 3520 | J45: =H45*I45 -> 0 | L45: =(J45+G45)-K45 -> 3520 | N45: =IF(M45>0,SUM(L45-M45)," ") | R45: =IF(O45>0,SUM(O45-(L45+P45))," ")
A46: 45043 | C46: DEMETRIU | D46: 6 | F46: 840 | G46: =(F46*D46)+(E46*F46) -> 5040 | J46: =H46*I46 -> 0 | L46: =(J46+G46)-K46 -> 5040 | N46: =IF(M46>0,SUM(L46-M46)," ") | R46: =IF(O46>0,SUM(O46-(L46+P46))," ")
A47: 45043 | C47: EVALDO SANTA INES | D47: 6 | F47: 860 | G47: =(F47*D47)+(E47*F47) -> 5160 | J47: =H47*I47 -> 0 | L47: =(J47+G47)-K47 -> 5160 | N47: =IF(M47>0,SUM(L47-M47)," ") | R47: =IF(O47>0,SUM(O47-(L47+P47))," ")
F48: 860 | G48: =(F48*D48)+(E48*F48) -> 0 | J48: =H48*I48 -> 0 | L48: =(J48+G48)-K48 -> 0 | N48: =IF(M48>0,SUM(L48-M48)," ") | R48: =IF(O48>0,SUM(O48-(L48+P48))," ")
F49: 850 | G49: =(F49*D49)+(E49*F49) -> 0 | J49: =H49*I49 -> 0 | L49: =(J49+G49)-K49 -> 0 | N49: =IF(M49>0,SUM(L49-M49)," ") | R49: =IF(O49>0,SUM(O49-(L49+P49))," ")
F50: 880 | G50: =(F50*D50)+(E50*F50) -> 0 | J50: =H50*I50 -> 0 | L50: =(J50+G50)-K50 -> 0 | N50: =IF(M50>0,SUM(L50-M50)," ") | R50: =IF(O50>0,SUM(O50-(L50+P50))," ")
F51: 880 | G51: =(F51*D51)+(E51*F51) -> 0 | J51: =H51*I51 -> 0 | L51: =(J51+G51)-K51 -> 0 | N51: =IF(M51>0,SUM(L51-M51)," ") | R51: =IF(O51>0,SUM(O51-(L51+P51))," ")
F52: 850 | G52: =(F52*D52)+(E52*F52) -> 0 | J52: =H52*I52 -> 0 | L52: =(J52+G52)-K52 -> 0 | N52: =IF(M52>0,SUM(L52-M52)," ") | R52: =IF(O52>0,SUM(O52-(L52+P52))," ")
F53: 900 | G53: =(F53*D53)+(E53*F53) -> 0 | J53: =H53*I53 -> 0 | L53: =(J53+G53)-K53 -> 0 | N53: =IF(M53>0,SUM(L53-M53)," ") | R53: =IF(O53>0,SUM(O53-(L53+P53))," ")
F54: 880 | G54: =(F54*D54)+(E54*F54) -> 0 | J54: =H54*I54 -> 0 | L54: =(J54+G54)-K54 -> 0 | N54: =IF(M54>0,SUM(L54-M54)," ") | R54: =IF(O54>0,SUM(O54-(L54+P54))," ")
F55: 880 | G55: =(F55*D55)+(E55*F55) -> 0 | J55: =H55*I55 -> 0 | L55: =(J55+G55)-K55 -> 0 | N55: =IF(M55>0,SUM(L55-M55)," ") | R55: =IF(O55>0,SUM(O55-(L55+P55))," ")
F56: 880 | G56: =(F56*D56)+(E56*F56) -> 0 | J56: =H56*I56 -> 0 | L56: =(J56+G56)-K56 -> 0 | N56: =IF(M56>0,SUM(L56-M56)," ") | R56: =IF(O56>0,SUM(O56-(L56+P56))," ")
F57: 850 | G57: =(F57*D57)+(E57*F57) -> 0 | J57: =H57*I57 -> 0 | L57: =(J57+G57)-K57 -> 0 | N57: =IF(M57>0,SUM(L57-M57)," ") | R57: =IF(O57>0,SUM(O57-(L57+P57))," ")
F58: 880 | G58: =(F58*D58)+(E58*F58) -> 0 | J58: =H58*I58 -> 0 | L58: =(J58+G58)-K58 -> 0 | N58: =IF(M58>0,SUM(L58-M58)," ") | R58: =IF(O58>0,SUM(O58-(L58+P58))," ")
F59: 900 | G59: =(F59*D59)+(E59*F59) -> 0 | J59: =H59*I59 -> 0 | L59: =(J59+G59)-K59 -> 0 | N59: =IF(M59>0,SUM(L59-M59)," ") | R59: =IF(O59>0,SUM(O59-(L59+P59))," ")
... F100: 800 | G100: =(F100*D100)+(E100*F100) -> 0 | J100: =H100*I100 -> 0 | L100: =(J100+G100)-K100 -> 0 | N100: =IF(M100>0,SUM(L100-M100)," ") | R100: =IF(O100>0,SUM(O100-(L100+P100))," ")
D101: =SUM(D4:D100) -> 68 | E101: =SUM(E4:E100) -> 57 | G101: =SUM(G4:G100) -> 107660 | H101: =SUM(H4:H100) -> 0 | J101: =SUM(J4:J100) -> 0 | L101: =SUM(L4:L100) -> 107660 | N101: =IF(M101>0,SUM(L101-M101)," ") | O101: =SUM(O4:O100) -> 1840 | P101: =SUM(P4:P100) -> 0 | Q101: =SUM(Q4:Q100) -> 0 | R101: =SUM(R4:R100) -> -11820 | S101: =SUM(S4:S100) -> 0
D102: =D101+E101 -> 125
C108: CLEZIO - DURAPLIK
C109: DEMETRIUS - ULTRAMASSA
C110: CLEZIO - DURAPLIK
C111: RAPOSÃO - MASSA FORTE
C112: GETULIA - JOSE WALTER
C113: CLAUDIO - MOSSORO
C114: CLEZIO - DURAPLIK
C115: CLEZIO - DURAPLIK
C116: CLEZIO - DURAPLIK
C117: DEMETRIUS - ULTRAMASSA
C120: AREMIX
C121: THIAGO - TIANGUA
... C137: CLAUDIO - MOSSORO

Sheet Vendas - MAI
A1: VENDAS | B1: VENDAS | D1: =D102 -> 180
A2: DATA | B2: VENDEDOR | C2: Clientes | D2: CELULOSE | H2: POLÍMERO | K2: DESCONTO CHEQUE | L2: TOTAL | M2: PARCIAL | N2: DEVENDO | O2: CHEQUES / PAGAMENTOS A MAIS OU A MENOS | T2: Forma de Pagamento | U2: Prazo | V2: Frete CIF / FOB | W2: OBSERVAÇÃO | X2: OBSERVAÇÃO
D3: PALOMA | E3: UCHOA | F3: PREÇO | G3: TOTAL | H3: QTD | I3: PREÇO TAB | J3: TOTAL | O3: VALOR VENDA | P3: COBRAMOS % | Q3: PAGAMOS % | R3: SALDO/DEBITO CLIENTE | S3: LUCRO/PREJ JUROS
A4: 45048 | C4: IRINEU | D4: 1 | F4: 880 | G4: =(F4*D4)+(E4*F4) -> 880 | J4: =H4*I4 -> 0 | L4: =(J4+G4)-K4 -> 880 | N4: =IF(M4>0,SUM(L4-M4)," ") | R4: =IF(O4>0,SUM(O4-(L4+P4))," ") | T4: A VISTA | U4: 0 | V4: FOB
A5: 45048 | C5: FORTMASSA | D5: 1 | F5: 880 | G5: =(F5*D5)+(E5*F5) -> 880 | J5: =H5*I5 -> 0 | L5: =(J5+G5)-K5 -> 880 | N5: =IF(M5>0,SUM(L5-M5)," ") | R5: =IF(O5>0,SUM(O5-(L5+P5))," ") | T5: A VISTA | U5: 0 | V5: FOB
A6: 45049 | C6: GETULIO | D6: 2 | F6: 880 | G6: =(F6*D6)+(E6*F6) -> 1760 | J6: =H6*I6 -> 0 | L6: =(J6+G6)-K6 -> 1760 | N6: =IF(M6>0,SUM(L6-M6)," ") | R6: =IF(O6>0,SUM(O6-(L6+P6))," ") | T6: A VISTA | U6: 0 | V6: FOB
A7: 45049 | C7: CHICO PEREIRA | E7: 2 | F7: 880 | G7: =(F7*D7)+(E7*F7) -> 1760 | J7: =H7*I7 -> 0 | L7: =(J7+G7)-K7 -> 1760 | N7: =IF(M7>0,SUM(L7-M7)," ") | R7: =IF(O7>0,SUM(O7-(L7+P7))," ") | T7: A VISTA | U7: 0 | V7: FOB
A8: 45049 | C8: CEARAMIX | E8: 1 | F8: 880 | G8: =(F8*D8)+(E8*F8) -> 880 | J8: =H8*I8 -> 0 | L8: =(J8+G8)-K8 -> 880 | N8: =IF(M8>0,SUM(L8-M8)," ") | O8: 1400 | R8: =IF(O8>0,SUM(O8-(L8+P8))," ") -> 520 | T8: CHEQUE/R$ | U8: 0 | V8: FOB | W8: 1100 + 300 | Y8: VALOR | Z8: QTD | AA8: =G101 -> 154430
A9: 45050 | C9: DEMETRIU | E9: 6 | F9: 830 | G9: =(F9*D9)+(E9*F9) -> 4980 | J9: =H9*I9 -> 0 | L9: =(J9+G9)-K9 -> 4980 | N9: =IF(M9>0,SUM(L9-M9)," ") | R9: =IF(O9>0,SUM(O9-(L9+P9))," ") | T9: A VISTA | U9: 0 | V9: FOB | Y9: 800 | AA9: =Y9*Z9 -> 0
A10: 45050 | C10: TODA OBRA | E10: 2 | F10: 860 | G10: =(F10*D10)+(E10*F10) -> 1720 | J10: =H10*I10 -> 0 | L10: =(J10+G10)-K10 -> 1720 | N10: =IF(M10>0,SUM(L10-M10)," ") | R10: =IF(O10>0,SUM(O10-(L10+P10))," ") | T10: A VISTA | U10: 0 | V10: FOB | Y10: 850 | AA10: =Y10*Z10 -> 0
A11: 45050 | C11: PEDRO HENRIQUE | D11: 1 | F11: 880 | G11: =(F11*D11)+(E11*F11) -> 880 | J11: =H11*I11 -> 0 | L11: =(J11+G11)-K11 -> 880 | N11: =IF(M11>0,SUM(L11-M11)," ") | R11: =IF(O11>0,SUM(O11-(L11+P11))," ") | T11: A VISTA | U11: 0 | V11: FOB | Y11: 830 | AA11: =Y11*Z11 -> 0
A12: 45051 | C12: FORTMASSA | D12: 1 | F12: 880 | G12: =(F12*D12)+(E12*F12) -> 880 | J12: =H12*I12 -> 0 | L12: =(J12+G12)-K12 -> 880 | N12: =IF(M12>0,SUM(L12-M12)," ") | R12: =IF(O12>0,SUM(O12-(L12+P12))," ") | T12: A VISTA | U12: 0 | V12: FOB | AA12: =Y12*Z12 -> 0
A13: 45051 | C13: ARG MATHEUS | E13: 1 | F13: 860 | G13: =(F13*D13)+(E13*F13) -> 860 | J13: =H13*I13 -> 0 | L13: =(J13+G13)-K13 -> 860 | N13: =IF(M13>0,SUM(L13-M13)," ") | O13: 440 | R13: =IF(O13>0,SUM(O13-(L13+P13))," ") -> -420 | S13: =P13-Q13 -> 0 | T13: A VISTA | U13: 30 | V13: FOB | W13: QUITACAO CREDITO | AA13: =AA8-(SUM(AA9:AA12)) -> 154430
A14: 45051 | C14: CONSTRUMIX | E14: 1 | F14: 850 | G14: =(F14*D14)+(E14*F14) -> 850 | J14: =H14*I14 -> 0 | L14: =(J14+G14)-K14 -> 850 | N14: =IF(M14>0,SUM(L14-M14)," ") | R14: =IF(O14>0,SUM(O14-(L14+P14))," ")
A15: 45052 | C15: GETULIO | D15: 2 | F15: 880 | G15: =(F15*D15)+(E15*F15) -> 1760 | J15: =H15*I15 -> 0 | L15: =(J15+G15)-K15 -> 1760 | N15: =IF(M15>0,SUM(L15-M15)," ") | R15: =IF(O15>0,SUM(O15-(L15+P15))," ")
A16: 45052 | C16: EVALDO SANTA INES | E16: 3 | F16: 860 | G16: =(F16*D16)+(E16*F16) -> 2580 | J16: =H16*I16 -> 0 | L16: =(J16+G16)-K16 -> 2580 | N16: =IF(M16>0,SUM(L16-M16)," ") | R16: =IF(O16>0,SUM(O16-(L16+P16))," ")
A17: 45054 | C17: GETULIO | D17: 1 | F17: 880 | G17: =(F17*D17)+(E17*F17) -> 880 | J17: =H17*I17 -> 0 | L17: =(J17+G17)-K17 -> 880 | N17: =IF(M17>0,SUM(L17-M17)," ") | R17: =IF(O17>0,SUM(O17-(L17+P17))," ")
A18: 45054 | C18: IRINEU | D18: 2 | F18: 880 | G18: =(F18*D18)+(E18*F18) -> 1760 | J18: =H18*I18 -> 0 | L18: =(J18+G18)-K18 -> 1760 | N18: =IF(M18>0,SUM(L18-M18)," ") | R18: =IF(O18>0,SUM(O18-(L18+P18))," ")
A19: 45054 | C19: ROBERTO LAGOA DO BANANA | D19: 1 | F19: 860 | G19: =(F19*D19)+(E19*F19) -> 860 | J19: =H19*I19 -> 0 | L19: =(J19+G19)-K19 -> 860 | N19: =IF(M19>0,SUM(L19-M19)," ") | R19: =IF(O19>0,SUM(O19-(L19+P19))," ")
A20: 45054 | C20: CONSTRUMIX | D20: 1 | F20: 850 | G20: =(F20*D20)+(E20*F20) -> 850 | J20: =H20*I20 -> 0 | L20: =(J20+G20)-K20 -> 850 | N20: =IF(M20>0,SUM(L20-M20)," ") | R20: =IF(O20>0,SUM(O20-(L20+P20))," ")
A21: 45054 | C21: THIAGO TIANGUA | D21: 1 | F21: 850 | G21: =(F21*D21)+(E21*F21) -> 850 | J21: =H21*I21 -> 0 | L21: =(J21+G21)-K21 -> 850 | N21: =IF(M21>0,SUM(L21-M21)," ") | R21: =IF(O21>0,SUM(O21-(L21+P21))," ")
A22: 45055 | C22: DEMETRIU | E22: 8 | F22: 830 | G22: =(F22*D22)+(E22*F22) -> 6640 | J22: =H22*I22 -> 0 | L22: =(J22+G22)-K22 -> 6640 | N22: =IF(M22>0,SUM(L22-M22)," ") | R22: =IF(O22>0,SUM(O22-(L22+P22))," ")
A23: 45055 | C23: CONSTRUMIX | E23: 2 | F23: 850 | G23: =(F23*D23)+(E23*F23) -> 1700 | J23: =H23*I23 -> 0 | L23: =(J23+G23)-K23 -> 1700 | N23: =IF(M23>0,SUM(L23-M23)," ") | R23: =IF(O23>0,SUM(O23-(L23+P23))," ")
A24: 45055 | C24: LOURIMAR | E24: 3 | F24: 880 | G24: =(F24*D24)+(E24*F24) -> 2640 | J24: =H24*I24 -> 0 | L24: =(J24+G24)-K24 -> 2640 | N24: =IF(M24>0,SUM(L24-M24)," ") | R24: =IF(O24>0,SUM(O24-(L24+P24))," ")
A25: 45055 | C25: LUIZ PI | E25: 2 | F25: 880 | G25: =(F25*D25)+(E25*F25) -> 1760 | J25: =H25*I25 -> 0 | L25: =(J25+G25)-K25 -> 1760 | N25: =IF(M25>0,SUM(L25-M25)," ") | R25: =IF(O25>0,SUM(O25-(L25+P25))," ")
A26: 45055 | C26: FELIPE | D26: 2 | F26: 900 | G26: =(F26*D26)+(E26*F26) -> 1800 | J26: =H26*I26 -> 0 | L26: =(J26+G26)-K26 -> 1800 | N26: =IF(M26>0,SUM(L26-M26)," ") | R26: =IF(O26>0,SUM(O26-(L26+P26))," ")
A27: 45055 | C27: FORTMASSA | D27: 1 | F27: 880 | G27: =(F27*D27)+(E27*F27) -> 880 | J27: =H27*I27 -> 0 | L27: =(J27+G27)-K27 -> 880 | N27: =IF(M27>0,SUM(L27-M27)," ") | R27: =IF(O27>0,SUM(O27-(L27+P27))," ")
A28: 45056 | C28: GETULIO | D28: 2 | F28: 880 | G28: =(F28*D28)+(E28*F28) -> 1760 | J28: =H28*I28 -> 0 | L28: =(J28+G28)-K28 -> 1760 | N28: =IF(M28>0,SUM(L28-M28)," ") | R28: =IF(O28>0,SUM(O28-(L28+P28))," ")
A29: 45056 | C29: MOEBIO IGUATU | D29: 2 | F29: 850 | G29: =(F29*D29)+(E29*F29) -> 1700 | J29: =H29*I29 -> 0 | L29: =(J29+G29)-K29 -> 1700 | N29: =IF(M29>0,SUM(L29-M29)," ") | R29: =IF(O29>0,SUM(O29-(L29+P29))," ")
A30: 45056 | C30: ARG MATHEUS | D30: 3 | F30: 850 | G30: =(F30*D30)+(E30*F30) -> 2550 | J30: =H30*I30 -> 0 | L30: =(J30+G30)-K30 -> 2550 | N30: =IF(M30>0,SUM(L30-M30)," ") | R30: =IF(O30>0,SUM(O30-(L30+P30))," ")
A31: 45056 | C31: EVALDO SANTA INES | D31: 5 | F31: 860 | G31: =(F31*D31)+(E31*F31) -> 4300 | J31: =H31*I31 -> 0 | L31: =(J31+G31)-K31 -> 4300 | N31: =IF(M31>0,SUM(L31-M31)," ") | R31: =IF(O31>0,SUM(O31-(L31+P31))," ")
A32: 45057 | C32: TODA OBRA | E32: 6 | F32: 860 | G32: =(F32*D32)+(E32*F32) -> 5160 | J32: =H32*I32 -> 0 | L32: =(J32+G32)-K32 -> 5160 | N32: =IF(M32>0,SUM(L32-M32)," ") | R32: =IF(O32>0,SUM(O32-(L32+P32))," ")
A33: 45057 | C33: CLAUDIO MOSSORO | D33: 8 | F33: 860 | G33: =(F33*D33)+(E33*F33) -> 6880 | J33: =H33*I33 -> 0 | L33: =(J33+G33)-K33 -> 6880 | N33: =IF(M33>0,SUM(L33-M33)," ") | R33: =IF(O33>0,SUM(O33-(L33+P33))," ")
A34: 45061 | C34: FORTMASSA | E34: 1 | F34: 880 | G34: =(F34*D34)+(E34*F34) -> 880 | J34: =H34*I34 -> 0 | L34: =(J34+G34)-K34 -> 880 | N34: =IF(M34>0,SUM(L34-M34)," ") | R34: =IF(O34>0,SUM(O34-(L34+P34))," ")
A35: 45062 | C35: FORTMASSA | D35: 1 | F35: 880 | G35: =(F35*D35)+(E35*F35) -> 880 | J35: =H35*I35 -> 0 | L35: =(J35+G35)-K35 -> 880 | N35: =IF(M35>0,SUM(L35-M35)," ") | R35: =IF(O35>0,SUM(O35-(L35+P35))," ")
A36: 45062 | C36: TAVARES | D36: 2 | F36: 850 | G36: =(F36*D36)+(E36*F36) -> 1700 | J36: =H36*I36 -> 0 | L36: =(J36+G36)-K36 -> 1700 | N36: =IF(M36>0,SUM(L36-M36)," ") | R36: =IF(O36>0,SUM(O36-(L36+P36))," ")
A37: 45062 | C37: GETULIO | D37: 1 | F37: 880 | G37: =(F37*D37)+(E37*F37) -> 880 | J37: =H37*I37 -> 0 | L37: =(J37+G37)-K37 -> 880 | N37: =IF(M37>0,SUM(L37-M37)," ") | R37: =IF(O37>0,SUM(O37-(L37+P37))," ")
A38: 45062 | C38: GETULIO | D38: 1 | F38: 880 | G38: =(F38*D38)+(E38*F38) -> 880 | J38: =H38*I38 -> 0 | L38: =(J38+G38)-K38 -> 880 | N38: =IF(M38>0,SUM(L38-M38)," ") | R38: =IF(O38>0,SUM(O38-(L38+P38))," ")
A39: 45062 | C39: LUIZ PI | E39: 2 | F39: 880 | G39: =(F39*D39)+(E39*F39) -> 1760 | J39: =H39*I39 -> 0 | L39: =(J39+G39)-K39 -> 1760 | N39: =IF(M39>0,SUM(L39-M39)," ") | R39: =IF(O39>0,SUM(O39-(L39+P39))," ")
A40: 45063 | C40: ARG MATHEUS | D40: 4 | F40: 850 | G40: =(F40*D40)+(E40*F40) -> 3400 | J40: =H40*I40 -> 0 | L40: =(J40+G40)-K40 -> 3400 | N40: =IF(M40>0,SUM(L40-M40)," ") | R40: =IF(O40>0,SUM(O40-(L40+P40))," ")
A41: 45063 | C41: GETULIO | D41: 1 | F41: 880 | G41: =(F41*D41)+(E41*F41) -> 880 | J41: =H41*I41 -> 0 | L41: =(J41+G41)-K41 -> 880 | N41: =IF(M41>0,SUM(L41-M41)," ") | R41: =IF(O41>0,SUM(O41-(L41+P41))," ")
A42: 45063 | C42: IRINEU | D42: 1 | F42: 880 | G42: =(F42*D42)+(E42*F42) -> 880 | J42: =H42*I42 -> 0 | L42: =(J42+G42)-K42 -> 880 | N42: =IF(M42>0,SUM(L42-M42)," ") | R42: =IF(O42>0,SUM(O42-(L42+P42))," ")
A43: 45063 | C43: TODA OBRA | E43: 4 | F43: 860 | G43: =(F43*D43)+(E43*F43) -> 3440 | J43: =H43*I43 -> 0 | L43: =(J43+G43)-K43 -> 3440 | N43: =IF(M43>0,SUM(L43-M43)," ") | R43: =IF(O43>0,SUM(O43-(L43+P43))," ")
A44: 45063 | C44: LOURIMAR | E44: 4 | F44: 880 | G44: =(F44*D44)+(E44*F44) -> 3520 | J44: =H44*I44 -> 0 | L44: =(J44+G44)-K44 -> 3520 | N44: =IF(M44>0,SUM(L44-M44)," ") | R44: =IF(O44>0,SUM(O44-(L44+P44))," ")
A45: 45064 | C45: CHICO PEREIRA | E45: 2 | F45: 880 | G45: =(F45*D45)+(E45*F45) -> 1760 | J45: =H45*I45 -> 0 | L45: =(J45+G45)-K45 -> 1760 | N45: =IF(M45>0,SUM(L45-M45)," ") | R45: =IF(O45>0,SUM(O45-(L45+P45))," ")
A46: 45064 | C46: AREMIX | D46: 10 | F46: 850 | G46: =(F46*D46)+(E46*F46) -> 8500 | J46: =H46*I46 -> 0 | L46: =(J46+G46)-K46 -> 8500 | N46: =IF(M46>0,SUM(L46-M46)," ") | R46: =IF(O46>0,SUM(O46-(L46+P46))," ")
A47: 45064 | C47: FELIPE | D47: 2 | F47: 900 | G47: =(F47*D47)+(E47*F47) -> 1800 | J47: =H47*I47 -> 0 | L47: =(J47+G47)-K47 -> 1800 | N47: =IF(M47>0,SUM(L47-M47)," ") | R47: =IF(O47>0,SUM(O47-(L47+P47))," ")
A48: 45066 | C48: GETULIO | E48: 2 | F48: 880 | G48: =(F48*D48)+(E48*F48) -> 1760 | J48: =H48*I48 -> 0 | L48: =(J48+G48)-K48 -> 1760 | N48: =IF(M48>0,SUM(L48-M48)," ") | R48: =IF(O48>0,SUM(O48-(L48+P48))," ")
A49: 45066 | C49: DEMETRIU | E49: 8 | F49: 830 | G49: =(F49*D49)+(E49*F49) -> 6640 | J49: =H49*I49 -> 0 | L49: =(J49+G49)-K49 -> 6640 | N49: =IF(M49>0,SUM(L49-M49)," ") | R49: =IF(O49>0,SUM(O49-(L49+P49))," ")
F50: 880 | G50: =(F50*D50)+(E50*F50) -> 0 | J50: =H50*I50 -> 0 | L50: =(J50+G50)-K50 -> 0 | N50: =IF(M50>0,SUM(L50-M50)," ") | R50: =IF(O50>0,SUM(O50-(L50+P50))," ")
A51: 45066 | C51: FORTMASSA | E51: 1 | F51: 880 | G51: =(F51*D51)+(E51*F51) -> 880 | J51: =H51*I51 -> 0 | L51: =(J51+G51)-K51 -> 880 | N51: =IF(M51>0,SUM(L51-M51)," ") | R51: =IF(O51>0,SUM(O51-(L51+P51))," ")
A52: 45068 | C52: IRINEU | E52: 1 | F52: 880 | G52: =(F52*D52)+(E52*F52) -> 880 | J52: =H52*I52 -> 0 | L52: =(J52+G52)-K52 -> 880 | N52: =IF(M52>0,SUM(L52-M52)," ") | R52: =IF(O52>0,SUM(O52-(L52+P52))," ")
A53: 45069 | C53: FORTMASSA | D53: 1 | F53: 880 | G53: =(F53*D53)+(E53*F53) -> 880 | J53: =H53*I53 -> 0 | L53: =(J53+G53)-K53 -> 880 | N53: =IF(M53>0,SUM(L53-M53)," ") | R53: =IF(O53>0,SUM(O53-(L53+P53))," ")
A54: 45070 | C54: PAVIMARI | D54: 1 | F54: 840 | G54: =(F54*D54)+(E54*F54) -> 840 | J54: =H54*I54 -> 0 | L54: =(J54+G54)-K54 -> 840 | N54: =IF(M54>0,SUM(L54-M54)," ") | R54: =IF(O54>0,SUM(O54-(L54+P54))," ")
A55: 45070 | C55: LOURIMAR | D55: 4 | F55: 880 | G55: =(F55*D55)+(E55*F55) -> 3520 | J55: =H55*I55 -> 0 | L55: =(J55+G55)-K55 -> 3520 | N55: =IF(M55>0,SUM(L55-M55)," ") | R55: =IF(O55>0,SUM(O55-(L55+P55))," ")
A56: 45070 | C56: ARG MATHEUS | D56: 2 | F56: 850 | G56: =(F56*D56)+(E56*F56) -> 1700 | J56: =H56*I56 -> 0 | L56: =(J56+G56)-K56 -> 1700 | N56: =IF(M56>0,SUM(L56-M56)," ") | R56: =IF(O56>0,SUM(O56-(L56+P56))," ")
A57: 45070 | C57: CLAUDIO MOSSORO | D57: 8 | F57: 860 | G57: =(F57*D57)+(E57*F57) -> 6880 | J57: =H57*I57 -> 0 | L57: =(J57+G57)-K57 -> 6880 | N57: =IF(M57>0,SUM(L57-M57)," ") | R57: =IF(O57>0,SUM(O57-(L57+P57))," ")
A58: 45071 | C58: FELIPE | D58: 1 | F58: 900 | G58: =(F58*D58)+(E58*F58) -> 900 | J58: =H58*I58 -> 0 | L58: =(J58+G58)-K58 -> 900 | N58: =IF(M58>0,SUM(L58-M58)," ") | R58: =IF(O58>0,SUM(O58-(L58+P58))," ")
A59: 45072 | C59: FORTMASSA | E59: 1 | F59: 880 | G59: =(F59*D59)+(E59*F59) -> 880 | J59: =H59*I59 -> 0 | L59: =(J59+G59)-K59 -> 880 | N59: =IF(M59>0,SUM(L59-M59)," ") | R59: =IF(O59>0,SUM(O59-(L59+P59))," ")
A60: 45072 | C60: MULTCOLA | E60: 2 | F60: 840 | G60: =(F60*D60)+(E60*F60) -> 1680 | J60: =H60*I60 -> 0 | L60: =(J60+G60)-K60 -> 1680 | N60: =IF(M60>0,SUM(L60-M60)," ") | R60: =IF(O60>0,SUM(O60-(L60+P60))," ")
A61: 45072 | C61: CONSTRUMIX | E61: 3 | F61: 850 | G61: =(F61*D61)+(E61*F61) -> 2550 | J61: =H61*I61 -> 0 | L61: =(J61+G61)-K61 -> 2550 | N61: =IF(M61>0,SUM(L61-M61)," ") | R61: =IF(O61>0,SUM(O61-(L61+P61))," ")
A62: 45073 | C62: GETULIO | D62: 2 | F62: 880 | G62: =(F62*D62)+(E62*F62) -> 1760 | J62: =H62*I62 -> 0 | L62: =(J62+G62)-K62 -> 1760 | N62: =IF(M62>0,SUM(L62-M62)," ") | R62: =IF(O62>0,SUM(O62-(L62+P62))," ")
A63: 45073 | C63: ARG MATHEUS | D63: 4 | F63: 850 | G63: =(F63*D63)+(E63*F63) -> 3400 | J63: =H63*I63 -> 0 | L63: =(J63+G63)-K63 -> 3400 | N63: =IF(M63>0,SUM(L63-M63)," ") | R63: =IF(O63>0,SUM(O63-(L63+P63))," ")
A64: 45073 | C64: ARG ROMA | D64: 4 | F64: 850 | G64: =(F64*D64)+(E64*F64) -> 3400 | J64: =H64*I64 -> 0 | L64: =(J64+G64)-K64 -> 3400 | N64: =IF(M64>0,SUM(L64-M64)," ") | R64: =IF(O64>0,SUM(O64-(L64+P64))," ")
A65: 45075 | C65: CONTRUMIX | E65: 2 | F65: 850 | G65: =(F65*D65)+(E65*F65) -> 1700 | J65: =H65*I65 -> 0 | L65: =(J65+G65)-K65 -> 1700 | N65: =IF(M65>0,SUM(L65-M65)," ") | R65: =IF(O65>0,SUM(O65-(L65+P65))," ")
A66: 45075 | C66: FORTMASSA | D66: 1 | F66: 880 | G66: =(F66*D66)+(E66*F66) -> 880 | J66: =H66*I66 -> 0 | L66: =(J66+G66)-K66 -> 880 | N66: =IF(M66>0,SUM(L66-M66)," ") | R66: =IF(O66>0,SUM(O66-(L66+P66))," ")
A67: 45075 | C67: IRINEU | D67: 1 | F67: 880 | G67: =(F67*D67)+(E67*F67) -> 880 | J67: =H67*I67 -> 0 | L67: =(J67+G67)-K67 -> 880 | N67: =IF(M67>0,SUM(L67-M67)," ") | R67: =IF(O67>0,SUM(O67-(L67+P67))," ")
A68: 45076 | C68: DEMETRIU | E68: 6 | F68: 800 | G68: =(F68*D68)+(E68*F68) -> 4800 | J68: =H68*I68 -> 0 | L68: =(J68+G68)-K68 -> 4800 | N68: =IF(M68>0,SUM(L68-M68)," ") | R68: =IF(O68>0,SUM(O68-(L68+P68))," ")
A69: 45076 | C69: ROBERTO LAGOA DO BANANA | E69: 1 | F69: 860 | G69: =(F69*D69)+(E69*F69) -> 860 | J69: =H69*I69 -> 0 | L69: =(J69+G69)-K69 -> 860 | N69: =IF(M69>0,SUM(L69-M69)," ") | R69: =IF(O69>0,SUM(O69-(L69+P69))," ")
A70: 45077 | C70: FORTMASSA | E70: 1 | F70: 880 | G70: =(F70*D70)+(E70*F70) -> 880 | J70: =H70*I70 -> 0 | L70: =(J70+G70)-K70 -> 880 | N70: =IF(M70>0,SUM(L70-M70)," ") | R70: =IF(O70>0,SUM(O70-(L70+P70))," ")
A71: 45077 | C71: AREMIX | E71: 10 | F71: 850 | G71: =(F71*D71)+(E71*F71) -> 8500 | J71: =H71*I71 -> 0 | L71: =(J71+G71)-K71 -> 8500 | N71: =IF(M71>0,SUM(L71-M71)," ") | R71: =IF(O71>0,SUM(O71-(L71+P71))," ")
A72: 45077 | C72: TAVARES | D72: 2 | F72: 850 | G72: =(F72*D72)+(E72*F72) -> 1700 | J72: =H72*I72 -> 0 | L72: =(J72+G72)-K72 -> 1700 | N72: =IF(M72>0,SUM(L72-M72)," ") | R72: =IF(O72>0,SUM(O72-(L72+P72))," ")
A73: 45078 | C73: CEARAMIX | E73: 1 | F73: 880 | G73: =(F73*D73)+(E73*F73) -> 880 | J73: =H73*I73 -> 0 | L73: =(J73+G73)-K73 -> 880 | N73: =IF(M73>0,SUM(L73-M73)," ") | R73: =IF(O73>0,SUM(O73-(L73+P73))," ")
F74: 800 | G74: =(F74*D74)+(E74*F74) -> 0 | J74: =H74*I74 -> 0 | L74: =(J74+G74)-K74 -> 0 | N74: =IF(M74>0,SUM(L74-M74)," ") | R74: =IF(O74>0,SUM(O74-(L74+P74))," ")
F75: 800 | G75: =(F75*D75)+(E75*F75) -> 0 | J75: =H75*I75 -> 0 | L75: =(J75+G75)-K75 -> 0 | N75: =IF(M75>0,SUM(L75-M75)," ") | R75: =IF(O75>0,SUM(O75-(L75+P75))," ")
F76: 800 | G76: =(F76*D76)+(E76*F76) -> 0 | J76: =H76*I76 -> 0 | L76: =(J76+G76)-K76 -> 0 | N76: =IF(M76>0,SUM(L76-M76)," ") | R76: =IF(O76>0,SUM(O76-(L76+P76))," ")
F77: 800 | G77: =(F77*D77)+(E77*F77) -> 0 | J77: =H77*I77 -> 0 | L77: =(J77+G77)-K77 -> 0 | N77: =IF(M77>0,SUM(L77-M77)," ") | R77: =IF(O77>0,SUM(O77-(L77+P77))," ")
F78: 800 | G78: =(F78*D78)+(E78*F78) -> 0 | J78: =H78*I78 -> 0 | L78: =(J78+G78)-K78 -> 0 | N78: =IF(M78>0,SUM(L78-M78)," ") | R78: =IF(O78>0,SUM(O78-(L78+P78))," ")
F79: 800 | G79: =(F79*D79)+(E79*F79) -> 0 | J79: =H79*I79 -> 0 | L79: =(J79+G79)-K79 -> 0 | N79: =IF(M79>0,SUM(L79-M79)," ") | R79: =IF(O79>0,SUM(O79-(L79+P79))," ")
F80: 800 | G80: =(F80*D80)+(E80*F80) -> 0 | J80: =H80*I80 -> 0 | L80: =(J80+G80)-K80 -> 0 | N80: =IF(M80>0,SUM(L80-M80)," ") | R80: =IF(O80>0,SUM(O80-(L80+P80))," ")
F81: 800 | G81: =(F81*D81)+(E81*F81) -> 0 | J81: =H81*I81 -> 0 | L81: =(J81+G81)-K81 -> 0 | N81: =IF(M81>0,SUM(L81-M81)," ") | R81: =IF(O81>0,SUM(O81-(L81+P81))," ")
F82: 800 | G82: =(F82*D82)+(E82*F82) -> 0 | J82: =H82*I82 -> 0 | L82: =(J82+G82)-K82 -> 0 | N82: =IF(M82>0,SUM(L82-M82)," ") | R82: =IF(O82>0,SUM(O82-(L82+P82))," ")
F83: 800 | G83: =(F83*D83)+(E83*F83) -> 0 | J83: =H83*I83 -> 0 | L83: =(J83+G83)-K83 -> 0 | N83: =IF(M83>0,SUM(L83-M83)," ") | R83: =IF(O83>0,SUM(O83-(L83+P83))," ")
F84: 800 | G84: =(F84*D84)+(E84*F84) -> 0 | J84: =H84*I84 -> 0 | L84: =(J84+G84)-K84 -> 0 | N84: =IF(M84>0,SUM(L84-M84)," ") | R84: =IF(O84>0,SUM(O84-(L84+P84))," ")
F85: 800 | G85: =(F85*D85)+(E85*F85) -> 0 | J85: =H85*I85 -> 0 | L85: =(J85+G85)-K85 -> 0 | N85: =IF(M85>0,SUM(L85-M85)," ") | R85: =IF(O85>0,SUM(O85-(L85+P85))," ")
... F100: 800 | G100: =(F100*D100)+(E100*F100) -> 0 | J100: =H100*I100 -> 0 | L100: =(J100+G100)-K100 -> 0 | N100: =IF(M100>0,SUM(L100-M100)," ") | R100: =IF(O100>0,SUM(O100-(L100+P100))," ")
D101: =SUM(D4:D100) -> 91 | E101: =SUM(E4:E100) -> 89 | G101: =SUM(G4:G100) -> 154430 | H101: =SUM(H4:H100) -> 0 | J101: =SUM(J4:J100) -> 0 | L101: =SUM(L4:L100) -> 154430 | N101: =IF(M101>0,SUM(L101-M101)," ") | O101: =SUM(O4:O100) -> 1840 | P101: =SUM(P4:P100) -> 0 | Q101: =SUM(Q4:Q100) -> 0 | R101: =SUM(R4:R100) -> 100 | S101: =SUM(S4:S100) -> 0
D102: =D101+E101 -> 180

Sheet Vendas - JUN
A1: VENDAS | B1: VENDAS | D1: =D102 -> 185
A2: DATA | B2: VENDEDOR | C2: Clientes | D2: CELULOSE | H2: POLÍMERO | K2: DESCONTO CHEQUE | L2: TOTAL | M2: PARCIAL | N2: DEVENDO | O2: CHEQUES / PAGAMENTOS A MAIS OU A MENOS | T2: Forma de Pagamento | U2: Prazo | V2: Frete CIF / FOB | W2: OBSERVAÇÃO | X2: OBSERVAÇÃO
D3: PALOMA | E3: UCHOA | F3: PREÇO | G3: TOTAL | H3: QTD | I3: PREÇO TAB | J3: TOTAL | O3: VALOR VENDA | P3: COBRAMOS % | Q3: PAGAMOS % | R3: SALDO/DEBITO CLIENTE | S3: LUCRO/PREJ JUROS
F4: 850 | G4: =(F4*D4)+(E4*F4) -> 0 | J4: =H4*I4 -> 0 | L4: =(J4+G4)-K4 -> 0 | N4: =IF(M4>0,SUM(L4-M4)," ") | R4: =IF(O4>0,SUM(O4-(L4+P4))," ") | T4: A VISTA | U4: 0 | V4: FOB
F5: 850 | G5: =(F5*D5)+(E5*F5) -> 0 | J5: =H5*I5 -> 0 | L5: =(J5+G5)-K5 -> 0 | N5: =IF(M5>0,SUM(L5-M5)," ") | R5: =IF(O5>0,SUM(O5-(L5+P5))," ") | T5: A VISTA | U5: 0 | V5: FOB
F6: 880 | G6: =(F6*D6)+(E6*F6) -> 0 | J6: =H6*I6 -> 0 | L6: =(J6+G6)-K6 -> 0 | N6: =IF(M6>0,SUM(L6-M6)," ") | R6: =IF(O6>0,SUM(O6-(L6+P6))," ") | T6: A VISTA | U6: 0 | V6: FOB
F7: 880 | G7: =(F7*D7)+(E7*F7) -> 0 | J7: =H7*I7 -> 0 | L7: =(J7+G7)-K7 -> 0 | N7: =IF(M7>0,SUM(L7-M7)," ") | R7: =IF(O7>0,SUM(O7-(L7+P7))," ") | T7: A VISTA | U7: 0 | V7: FOB
F8: 850 | G8: =(F8*D8)+(E8*F8) -> 0 | J8: =H8*I8 -> 0 | L8: =(J8+G8)-K8 -> 0 | N8: =IF(M8>0,SUM(L8-M8)," ") | O8: 1400 | R8: =IF(O8>0,SUM(O8-(L8+P8))," ") -> 1400 | T8: CHEQUE/R$ | U8: 0 | V8: FOB | W8: 1100 + 300 | Y8: VALOR | Z8: QTD | AA8: =G101 -> 154510
F9: 860 | G9: =(F9*D9)+(E9*F9) -> 0 | J9: =H9*I9 -> 0 | L9: =(J9+G9)-K9 -> 0 | N9: =IF(M9>0,SUM(L9-M9)," ") | R9: =IF(O9>0,SUM(O9-(L9+P9))," ") | T9: A VISTA | U9: 0 | V9: FOB | Y9: 720 | AA9: =Y9*Z9 -> 0
F10: 880 | G10: =(F10*D10)+(E10*F10) -> 0 | J10: =H10*I10 -> 0 | L10: =(J10+G10)-K10 -> 0 | N10: =IF(M10>0,SUM(L10-M10)," ") | R10: =IF(O10>0,SUM(O10-(L10+P10))," ") | T10: A VISTA | U10: 0 | V10: FOB | Y10: 750 | AA10: =Y10*Z10 -> 0
A11: 45078 | C11: CONTRUMIX | E11: 1 | F11: 850 | G11: =(F11*D11)+(E11*F11) -> 850 | J11: =H11*I11 -> 0 | L11: =(J11+G11)-K11 -> 850 | N11: =IF(M11>0,SUM(L11-M11)," ") | R11: =IF(O11>0,SUM(O11-(L11+P11))," ") | T11: A VISTA | U11: 0 | V11: FOB | Y11: 780 | AA11: =Y11*Z11 -> 0
A12: 45078 | C12: TODA OBRA | E12: 2 | F12: 860 | G12: =(F12*D12)+(E12*F12) -> 1720 | J12: =H12*I12 -> 0 | L12: =(J12+G12)-K12 -> 1720 | N12: =IF(M12>0,SUM(L12-M12)," ") | R12: =IF(O12>0,SUM(O12-(L12+P12))," ") | T12: A VISTA | U12: 0 | V12: FOB | Y12: 800 | AA12: =Y12*Z12 -> 0
A13: 45078 | C13: LOURIMAR | D13: 4 | F13: 880 | G13: =(F13*D13)+(E13*F13) -> 3520 | J13: =H13*I13 -> 0 | L13: =(J13+G13)-K13 -> 3520 | N13: =IF(M13>0,SUM(L13-M13)," ") | O13: 440 | R13: =IF(O13>0,SUM(O13-(L13+P13))," ") -> -3080 | S13: =P13-Q13 -> 0 | T13: A VISTA | U13: 30 | V13: FOB | W13: QUITACAO CREDITO | AA13: =AA8-(SUM(AA9:AA12)) -> 154510
A14: 45078 | C14: ELIEL | D14: 10 | F14: 830 | G14: =(F14*D14)+(E14*F14) -> 8300 | J14: =H14*I14 -> 0 | L14: =(J14+G14)-K14 -> 8300 | N14: =IF(M14>0,SUM(L14-M14)," ") | R14: =IF(O14>0,SUM(O14-(L14+P14))," ")
A15: 45079 | C15: ARG MATEUS | D15: 3 | F15: 850 | G15: =(F15*D15)+(E15*F15) -> 2550 | J15: =H15*I15 -> 0 | L15: =(J15+G15)-K15 -> 2550 | N15: =IF(M15>0,SUM(L15-M15)," ") | R15: =IF(O15>0,SUM(O15-(L15+P15))," ")
A16: 45079 | C16: FORTMASSA | D16: 1 | F16: 880 | G16: =(F16*D16)+(E16*F16) -> 880 | J16: =H16*I16 -> 0 | L16: =(J16+G16)-K16 -> 880 | N16: =IF(M16>0,SUM(L16-M16)," ") | R16: =IF(O16>0,SUM(O16-(L16+P16))," ")
A17: 45079 | C17: IRINEU | D17: 1 | F17: 880 | G17: =(F17*D17)+(E17*F17) -> 880 | J17: =H17*I17 -> 0 | L17: =(J17+G17)-K17 -> 880
A18: 45079 | C18: FELIPE | D18: 2 | F18: 900 | G18: =(F18*D18)+(E18*F18) -> 1800 | J18: =H18*I18 -> 0 | L18: =(J18+G18)-K18 -> 1800 | N18: =IF(M18>0,SUM(L18-M18)," ") | R18: =IF(O18>0,SUM(O18-(L18+P18))," ")
A19: 45080 | C19: GETULIO | D19: 2 | F19: 880 | G19: =(F19*D19)+(E19*F19) -> 1760 | J19: =H19*I19 -> 0 | L19: =(J19+G19)-K19 -> 1760 | N19: =IF(M19>0,SUM(L19-M19)," ") | R19: =IF(O19>0,SUM(O19-(L19+P19))," ")
A20: 45082 | C20: DEMETRIU | D20: 2 | F20: 800 | G20: =(F20*D20)+(E20*F20) -> 1600 | J20: =H20*I20 -> 0 | L20: =(J20+G20)-K20 -> 1600 | N20: =IF(M20>0,SUM(L20-M20)," ") | R20: =IF(O20>0,SUM(O20-(L20+P20))," ")
A21: 45082 | C21: FORTMASSA | D21: 1 | F21: 880 | G21: =(F21*D21)+(E21*F21) -> 880 | J21: =H21*I21 -> 0 | L21: =(J21+G21)-K21 -> 880 | N21: =IF(M21>0,SUM(L21-M21)," ") | R21: =IF(O21>0,SUM(O21-(L21+P21))," ")
A22: 45083 | C22: GETULIO | D22: 1 | F22: 880 | G22: =(F22*D22)+(E22*F22) -> 880 | J22: =H22*I22 -> 0 | L22: =(J22+G22)-K22 -> 880 | N22: =IF(M22>0,SUM(L22-M22)," ") | R22: =IF(O22>0,SUM(O22-(L22+P22))," ")
A23: 45084 | C23: IRINEU | D23: 1 | F23: 880 | G23: =(F23*D23)+(E23*F23) -> 880 | J23: =H23*I23 -> 0 | L23: =(J23+G23)-K23 -> 880 | N23: =IF(M23>0,SUM(L23-M23)," ") | R23: =IF(O23>0,SUM(O23-(L23+P23))," ")
A24: 45084 | C24: CLAUDIO MOSSORO | D24: 8 | F24: 830 | G24: =(F24*D24)+(E24*F24) -> 6640 | J24: =H24*I24 -> 0 | L24: =(J24+G24)-K24 -> 6640 | N24: =IF(M24>0,SUM(L24-M24)," ") | R24: =IF(O24>0,SUM(O24-(L24+P24))," ")
A25: 45084 | C25: LOURIMAR | E25: 4 | F25: 880 | G25: =(F25*D25)+(E25*F25) -> 3520 | J25: =H25*I25 -> 0 | L25: =(J25+G25)-K25 -> 3520 | N25: =IF(M25>0,SUM(L25-M25)," ") | R25: =IF(O25>0,SUM(O25-(L25+P25))," ")
A26: 45084 | C26: ANDRE | E26: 1 | F26: 900 | G26: =(F26*D26)+(E26*F26) -> 900 | J26: =H26*I26 -> 0 | L26: =(J26+G26)-K26 -> 900 | N26: =IF(M26>0,SUM(L26-M26)," ") | R26: =IF(O26>0,SUM(O26-(L26+P26))," ")
A27: 45084 | C27: DEMETRIU | E27: 5 | F27: 800 | G27: =(F27*D27)+(E27*F27) -> 4000 | J27: =H27*I27 -> 0 | L27: =(J27+G27)-K27 -> 4000 | N27: =IF(M27>0,SUM(L27-M27)," ") | R27: =IF(O27>0,SUM(O27-(L27+P27))," ")
A28: 45084 | C28: TODA OBRA | E28: 6 | F28: 860 | G28: =(F28*D28)+(E28*F28) -> 5160 | J28: =H28*I28 -> 0 | L28: =(J28+G28)-K28 -> 5160 | N28: =IF(M28>0,SUM(L28-M28)," ") | R28: =IF(O28>0,SUM(O28-(L28+P28))," ")
A29: 45086 | C29: MOEBIO | D29: 1 | F29: 850 | G29: =(F29*D29)+(E29*F29) -> 850 | J29: =H29*I29 -> 0 | L29: =(J29+G29)-K29 -> 850 | N29: =IF(M29>0,SUM(L29-M29)," ") | R29: =IF(O29>0,SUM(O29-(L29+P29))," ")
G30: =(F30*D30)+(E30*F30) -> 0 | J30: =H30*I30 -> 0 | L30: =(J30+G30)-K30 -> 0 | N30: =IF(M30>0,SUM(L30-M30)," ") | R30: =IF(O30>0,SUM(O30-(L30+P30))," ")
A31: 45087 | C31: GETULIO | D31: 2 | F31: 880 | G31: =(F31*D31)+(E31*F31) -> 1760 | J31: =H31*I31 -> 0 | L31: =(J31+G31)-K31 -> 1760 | N31: =IF(M31>0,SUM(L31-M31)," ") | R31: =IF(O31>0,SUM(O31-(L31+P31))," ")
A32: 45090 | C32: IRINEU | D32: 1 | F32: 880 | G32: =(F32*D32)+(E32*F32) -> 880 | J32: =H32*I32 -> 0 | L32: =(J32+G32)-K32 -> 880 | N32: =IF(M32>0,SUM(L32-M32)," ") | R32: =IF(O32>0,SUM(O32-(L32+P32))," ")
A33: 45090 | C33: FORTMASSA | D33: 1 | F33: 880 | G33: =(F33*D33)+(E33*F33) -> 880 | J33: =H33*I33 -> 0 | L33: =(J33+G33)-K33 -> 880 | N33: =IF(M33>0,SUM(L33-M33)," ") | R33: =IF(O33>0,SUM(O33-(L33+P33))," ")
A34: 45090 | C34: FELIPE | D34: 1 | F34: 900 | G34: =(F34*D34)+(E34*F34) -> 900 | J34: =H34*I34 -> 0 | L34: =(J34+G34)-K34 -> 900 | N34: =IF(M34>0,SUM(L34-M34)," ") | R34: =IF(O34>0,SUM(O34-(L34+P34))," ")
A35: 45090 | C35: DEMETRIU | E35: 5 | F35: 800 | G35: =(F35*D35)+(E35*F35) -> 4000 | J35: =H35*I35 -> 0 | L35: =(J35+G35)-K35 -> 4000 | N35: =IF(M35>0,SUM(L35-M35)," ") | R35: =IF(O35>0,SUM(O35-(L35+P35))," ")
A36: 45090 | C36: CHICO PEREIRA | E36: 2 | F36: 840 | G36: =(F36*D36)+(E36*F36) -> 1680 | J36: =H36*I36 -> 0 | L36: =(J36+G36)-K36 -> 1680 | N36: =IF(M36>0,SUM(L36-M36)," ") | R36: =IF(O36>0,SUM(O36-(L36+P36))," ")
A37: 45090 | C37: ARG MATEUS | E37: 3 | F37: 830 | G37: =(F37*D37)+(E37*F37) -> 2490 | J37: =H37*I37 -> 0 | L37: =(J37+G37)-K37 -> 2490 | N37: =IF(M37>0,SUM(L37-M37)," ") | R37: =IF(O37>0,SUM(O37-(L37+P37))," ")
A38: 45091 | C38: LOURIMAR | E38: 4 | F38: 850 | G38: =(F38*D38)+(E38*F38) -> 3400 | J38: =H38*I38 -> 0 | L38: =(J38+G38)-K38 -> 3400 | N38: =IF(M38>0,SUM(L38-M38)," ") | R38: =IF(O38>0,SUM(O38-(L38+P38))," ")
A39: 45091 | C39: FORTMASSA | D39: 1 | F39: 850 | G39: =(F39*D39)+(E39*F39) -> 850 | J39: =H39*I39 -> 0 | L39: =(J39+G39)-K39 -> 850 | N39: =IF(M39>0,SUM(L39-M39)," ") | R39: =IF(O39>0,SUM(O39-(L39+P39))," ")
A40: 45091 | C40: TODA OBRA | E40: 2 | F40: 840 | G40: =(F40*D40)+(E40*F40) -> 1680 | J40: =H40*I40 -> 0 | L40: =(J40+G40)-K40 -> 1680 | N40: =IF(M40>0,SUM(L40-M40)," ") | R40: =IF(O40>0,SUM(O40-(L40+P40))," ")
A41: 45091 | C41: GETULIO | D41: 2 | F41: 880 | G41: =(F41*D41)+(E41*F41) -> 1760 | J41: =H41*I41 -> 0 | L41: =(J41+G41)-K41 -> 1760 | N41: =IF(M41>0,SUM(L41-M41)," ") | R41: =IF(O41>0,SUM(O41-(L41+P41))," ")
A42: 45092 | C42: FORTMASSA | D42: 1 | F42: 850 | G42: =(F42*D42)+(E42*F42) -> 850 | J42: =H42*I42 -> 0 | L42: =(J42+G42)-K42 -> 850 | N42: =IF(M42>0,SUM(L42-M42)," ") | R42: =IF(O42>0,SUM(O42-(L42+P42))," ")
A43: 45093 | C43: DEDE DO ARROZ | D43: 1 | F43: 900 | G43: =(F43*D43)+(E43*F43) -> 900 | J43: =H43*I43 -> 0 | L43: =(J43+G43)-K43 -> 900 | N43: =IF(M43>0,SUM(L43-M43)," ") | R43: =IF(O43>0,SUM(O43-(L43+P43))," ")
A44: 45093 | C44: ROBERTO LAGOA DO BANANA | E44: 1 | F44: 860 | G44: =(F44*D44)+(E44*F44) -> 860 | J44: =H44*I44 -> 0 | L44: =(J44+G44)-K44 -> 860 | N44: =IF(M44>0,SUM(L44-M44)," ") | R44: =IF(O44>0,SUM(O44-(L44+P44))," ")
A45: 45093 | C45: CEARAMIX | E45: 1 | F45: 850 | G45: =(F45*D45)+(E45*F45) -> 850 | J45: =H45*I45 -> 0 | L45: =(J45+G45)-K45 -> 850 | N45: =IF(M45>0,SUM(L45-M45)," ") | R45: =IF(O45>0,SUM(O45-(L45+P45))," ")
A46: 45094 | C46: FORTMASSA | D46: 1 | F46: 850 | G46: =(F46*D46)+(E46*F46) -> 850 | J46: =H46*I46 -> 0 | L46: =(J46+G46)-K46 -> 850 | N46: =IF(M46>0,SUM(L46-M46)," ") | R46: =IF(O46>0,SUM(O46-(L46+P46))," ")
A47: 45096 | C47: AREMIX | D47: 10 | F47: 820 | G47: =(F47*D47)+(E47*F47) -> 8200 | J47: =H47*I47 -> 0 | L47: =(J47+G47)-K47 -> 8200 | N47: =IF(M47>0,SUM(L47-M47)," ") | R47: =IF(O47>0,SUM(O47-(L47+P47))," ")
A48: 45096 | C48: DEMETRIU | E48: 6 | F48: 800 | G48: =(F48*D48)+(E48*F48) -> 4800 | J48: =H48*I48 -> 0 | L48: =(J48+G48)-K48 -> 4800 | N48: =IF(M48>0,SUM(L48-M48)," ") | R48: =IF(O48>0,SUM(O48-(L48+P48))," ")
A49: 45096 | C49: ARG TAVARES | D49: 1 | F49: 850 | G49: =(F49*D49)+(E49*F49) -> 850 | J49: =H49*I49 -> 0 | L49: =(J49+G49)-K49 -> 850 | N49: =IF(M49>0,SUM(L49-M49)," ") | R49: =IF(O49>0,SUM(O49-(L49+P49))," ")
A50: 45097 | C50: FORTMASSA | E50: 1 | F50: 850 | G50: =(F50*D50)+(E50*F50) -> 850 | J50: =H50*I50 -> 0 | L50: =(J50+G50)-K50 -> 850 | N50: =IF(M50>0,SUM(L50-M50)," ") | R50: =IF(O50>0,SUM(O50-(L50+P50))," ")
A51: 45097 | C51: ARG MATEUS | E51: 3 | F51: 830 | G51: =(F51*D51)+(E51*F51) -> 2490 | J51: =H51*I51 -> 0 | L51: =(J51+G51)-K51 -> 2490 | N51: =IF(M51>0,SUM(L51-M51)," ") | R51: =IF(O51>0,SUM(O51-(L51+P51))," ")
A52: 45097 | C52: LUIZ PI | E52: 2 | F52: 840 | G52: =(F52*D52)+(E52*F52) -> 1680 | J52: =H52*I52 -> 0 | L52: =(J52+G52)-K52 -> 1680 | N52: =IF(M52>0,SUM(L52-M52)," ") | R52: =IF(O52>0,SUM(O52-(L52+P52))," ")
A53: 45098 | C53: GETULIO | D53: 2 | F53: 880 | G53: =(F53*D53)+(E53*F53) -> 1760 | J53: =H53*I53 -> 0 | L53: =(J53+G53)-K53 -> 1760 | N53: =IF(M53>0,SUM(L53-M53)," ") | R53: =IF(O53>0,SUM(O53-(L53+P53))," ")
A54: 45098 | C54: GETULIO | D54: 1 | F54: 880 | G54: =(F54*D54)+(E54*F54) -> 880 | J54: =H54*I54 -> 0 | L54: =(J54+G54)-K54 -> 880 | N54: =IF(M54>0,SUM(L54-M54)," ") | R54: =IF(O54>0,SUM(O54-(L54+P54))," ")
A55: 45098 | C55: IRINEU | D55: 1 | F55: 880 | G55: =(F55*D55)+(E55*F55) -> 880 | J55: =H55*I55 -> 0 | L55: =(J55+G55)-K55 -> 880 | N55: =IF(M55>0,SUM(L55-M55)," ") | R55: =IF(O55>0,SUM(O55-(L55+P55))," ")
A56: 45098 | C56: ELIEL | D56: 10 | F56: 800 | G56: =(F56*D56)+(E56*F56) -> 8000 | J56: =H56*I56 -> 0 | L56: =(J56+G56)-K56 -> 8000 | N56: =IF(M56>0,SUM(L56-M56)," ") | R56: =IF(O56>0,SUM(O56-(L56+P56))," ")
A57: 45098 | C57: LOURIMAR | E57: 4 | F57: 850 | G57: =(F57*D57)+(E57*F57) -> 3400 | J57: =H57*I57 -> 0 | L57: =(J57+G57)-K57 -> 3400 | N57: =IF(M57>0,SUM(L57-M57)," ") | R57: =IF(O57>0,SUM(O57-(L57+P57))," ")
A58: 45099 | C58: TODA OBRA | E58: 2 | F58: 840 | G58: =(F58*D58)+(E58*F58) -> 1680 | J58: =H58*I58 -> 0 | L58: =(J58+G58)-K58 -> 1680 | N58: =IF(M58>0,SUM(L58-M58)," ") | R58: =IF(O58>0,SUM(O58-(L58+P58))," ")
A59: 45099 | C59: CHICO PEREIRA | E59: 2 | F59: 840 | G59: =(F59*D59)+(E59*F59) -> 1680 | J59: =H59*I59 -> 0 | L59: =(J59+G59)-K59 -> 1680 | N59: =IF(M59>0,SUM(L59-M59)," ") | R59: =IF(O59>0,SUM(O59-(L59+P59))," ")
A60: 45099 | C60: JULIO | D60: 2 | F60: 800 | G60: =(F60*D60)+(E60*F60) -> 1600 | J60: =H60*I60 -> 0 | L60: =(J60+G60)-K60 -> 1600 | N60: =IF(M60>0,SUM(L60-M60)," ") | R60: =IF(O60>0,SUM(O60-(L60+P60))," ")
A61: 45099 | C61: NEWMASSA | D61: 2 | F61: 800 | G61: =(F61*D61)+(E61*F61) -> 1600 | J61: =H61*I61 -> 0 | L61: =(J61+G61)-K61 -> 1600 | N61: =IF(M61>0,SUM(L61-M61)," ") | R61: =IF(O61>0,SUM(O61-(L61+P61))," ")
A62: 45099 | C62: FELIPE | D62: 1 | F62: 900 | G62: =(F62*D62)+(E62*F62) -> 900 | J62: =H62*I62 -> 0 | L62: =(J62+G62)-K62 -> 900 | N62: =IF(M62>0,SUM(L62-M62)," ") | R62: =IF(O62>0,SUM(O62-(L62+P62))," ")
A63: 45100 | C63: DEMETRIU | D63: 6 | F63: 800 | G63: =(F63*D63)+(E63*F63) -> 4800 | J63: =H63*I63 -> 0 | L63: =(J63+G63)-K63 -> 4800 | N63: =IF(M63>0,SUM(L63-M63)," ") | R63: =IF(O63>0,SUM(O63-(L63+P63))," ")
A64: 45100 | C64: ARG MATEUS | D64: 2 | F64: 840 | G64: =(F64*D64)+(E64*F64) -> 1680 | J64: =H64*I64 -> 0 | L64: =(J64+G64)-K64 -> 1680 | N64: =IF(M64>0,SUM(L64-M64)," ") | R64: =IF(O64>0,SUM(O64-(L64+P64))," ")
A65: 45103 | C65: IRINEU | D65: 1 | F65: 880 | G65: =(F65*D65)+(E65*F65) -> 880 | J65: =H65*I65 -> 0 | L65: =(J65+G65)-K65 -> 880 | N65: =IF(M65>0,SUM(L65-M65)," ") | R65: =IF(O65>0,SUM(O65-(L65+P65))," ")
A66: 45103 | C66: FORTMASSA | D66: 1 | F66: 850 | G66: =(F66*D66)+(E66*F66) -> 850 | J66: =H66*I66 -> 0 | L66: =(J66+G66)-K66 -> 850 | N66: =IF(M66>0,SUM(L66-M66)," ") | R66: =IF(O66>0,SUM(O66-(L66+P66))," ")
A67: 45103 | C67: JULIO | D67: 2 | F67: 800 | G67: =(F67*D67)+(E67*F67) -> 1600 | J67: =H67*I67 -> 0 | L67: =(J67+G67)-K67 -> 1600 | N67: =IF(M67>0,SUM(L67-M67)," ") | R67: =IF(O67>0,SUM(O67-(L67+P67))," ")
A68: 45103 | C68: ARG TAVARES | D68: 1 | F68: 850 | G68: =(F68*D68)+(E68*F68) -> 850 | J68: =H68*I68 -> 0 | L68: =(J68+G68)-K68 -> 850 | N68: =IF(M68>0,SUM(L68-M68)," ") | R68: =IF(O68>0,SUM(O68-(L68+P68))," ")
A69: 45103 | C69: MULTCOLA | E69: 5 | F69: 800 | G69: =(F69*D69)+(E69*F69) -> 4000 | J69: =H69*I69 -> 0 | L69: =(J69+G69)-K69 -> 4000 | N69: =IF(M69>0,SUM(L69-M69)," ") | R69: =IF(O69>0,SUM(O69-(L69+P69))," ")
A70: 45104 | C70: GETULIO | D70: 2 | F70: 850 | G70: =(F70*D70)+(E70*F70) -> 1700 | J70: =H70*I70 -> 0 | L70: =(J70+G70)-K70 -> 1700 | N70: =IF(M70>0,SUM(L70-M70)," ") | R70: =IF(O70>0,SUM(O70-(L70+P70))," ")
A71: 45104 | C71: ARG MATEUS | E71: 3 | F71: 830 | G71: =(F71*D71)+(E71*F71) -> 2490 | J71: =H71*I71 -> 0 | L71: =(J71+G71)-K71 -> 2490 | N71: =IF(M71>0,SUM(L71-M71)," ") | R71: =IF(O71>0,SUM(O71-(L71+P71))," ")
A72: 45105 | C72: MOEBIO IGUATU | E72: 1 | F72: 800 | G72: =(F72*D72)+(E72*F72) -> 800 | J72: =H72*I72 -> 0 | L72: =(J72+G72)-K72 -> 800 | N72: =IF(M72>0,SUM(L72-M72)," ") | R72: =IF(O72>0,SUM(O72-(L72+P72))," ")
A73: 45105 | C73: LUIZ PI | E73: 2 | F73: 810 | G73: =(F73*D73)+(E73*F73) -> 1620 | J73: =H73*I73 -> 0 | L73: =(J73+G73)-K73 -> 1620 | N73: =IF(M73>0,SUM(L73-M73)," ") | R73: =IF(O73>0,SUM(O73-(L73+P73))," ")
A74: 45105 | C74: TODA OBRA | E74: 5 | F74: 820 | G74: =(F74*D74)+(E74*F74) -> 4100 | J74: =H74*I74 -> 0 | L74: =(J74+G74)-K74 -> 4100 | N74: =IF(M74>0,SUM(L74-M74)," ") | R74: =IF(O74>0,SUM(O74-(L74+P74))," ")
F75: 800 | G75: =(F75*D75)+(E75*F75) -> 0 | J75: =H75*I75 -> 0 | L75: =(J75+G75)-K75 -> 0 | N75: =IF(M75>0,SUM(L75-M75)," ") | R75: =IF(O75>0,SUM(O75-(L75+P75))," ")
A76: 45105 | C76: LOURIMAR | D76: 4 | F76: 840 | G76: =(F76*D76)+(E76*F76) -> 3360 | J76: =H76*I76 -> 0 | L76: =(J76+G76)-K76 -> 3360 | N76: =IF(M76>0,SUM(L76-M76)," ") | R76: =IF(O76>0,SUM(O76-(L76+P76))," ")
A77: 45105 | C77: DEMETRIU | D77: 6 | F77: 800 | G77: =(F77*D77)+(E77*F77) -> 4800 | J77: =H77*I77 -> 0 | L77: =(J77+G77)-K77 -> 4800 | N77: =IF(M77>0,SUM(L77-M77)," ") | R77: =IF(O77>0,SUM(O77-(L77+P77))," ")
A78: 45105 | C78: CLAUDIO MOSSORO | D78: 4 | F78: 830 | G78: =(F78*D78)+(E78*F78) -> 3320 | J78: =H78*I78 -> 0 | L78: =(J78+G78)-K78 -> 3320 | N78: =IF(M78>0,SUM(L78-M78)," ") | R78: =IF(O78>0,SUM(O78-(L78+P78))," ")
A79: 45107 | C79: CERAMIX | D79: 1 | F79: 850 | G79: =(F79*D79)+(E79*F79) -> 850 | J79: =H79*I79 -> 0 | L79: =(J79+G79)-K79 -> 850 | N79: =IF(M79>0,SUM(L79-M79)," ") | R79: =IF(O79>0,SUM(O79-(L79+P79))," ")
A80: 45107 | C80: FELIPE | D80: 2 | F80: 850 | G80: =(F80*D80)+(E80*F80) -> 1700 | J80: =H80*I80 -> 0 | L80: =(J80+G80)-K80 -> 1700 | N80: =IF(M80>0,SUM(L80-M80)," ") | R80: =IF(O80>0,SUM(O80-(L80+P80))," ")
A81: 45107 | C81: ANDRE | D81: 1 | F81: 850 | G81: =(F81*D81)+(E81*F81) -> 850 | J81: =H81*I81 -> 0 | L81: =(J81+G81)-K81 -> 850 | N81: =IF(M81>0,SUM(L81-M81)," ") | R81: =IF(O81>0,SUM(O81-(L81+P81))," ")
A82: 45107 | C82: IRINEU | D82: 1 | F82: 850 | G82: =(F82*D82)+(E82*F82) -> 850 | J82: =H82*I82 -> 0 | L82: =(J82+G82)-K82 -> 850 | N82: =IF(M82>0,SUM(L82-M82)," ") | R82: =IF(O82>0,SUM(O82-(L82+P82))," ")
F83: 850 | G83: =(F83*D83)+(E83*F83) -> 0 | J83: =H83*I83 -> 0 | L83: =(J83+G83)-K83 -> 0 | N83: =IF(M83>0,SUM(L83-M83)," ") | R83: =IF(O83>0,SUM(O83-(L83+P83))," ")
F84: 850 | G84: =(F84*D84)+(E84*F84) -> 0 | J84: =H84*I84 -> 0 | L84: =(J84+G84)-K84 -> 0 | N84: =IF(M84>0,SUM(L84-M84)," ") | R84: =IF(O84>0,SUM(O84-(L84+P84))," ")
F85: 800 | G85: =(F85*D85)+(E85*F85) -> 0 | J85: =H85*I85 -> 0 | L85: =(J85+G85)-K85 -> 0 | N85: =IF(M85>0,SUM(L85-M85)," ") | R85: =IF(O85>0,SUM(O85-(L85+P85))," ")
F86: 800 | G86: =(F86*D86)+(E86*F86) -> 0 | J86: =H86*I86 -> 0 | L86: =(J86+G86)-K86 -> 0 | N86: =IF(M86>0,SUM(L86-M86)," ") | R86: =IF(O86>0,SUM(O86-(L86+P86))," ")
F87: 800 | G87: =(F87*D87)+(E87*F87) -> 0 | J87: =H87*I87 -> 0 | L87: =(J87+G87)-K87 -> 0 | N87: =IF(M87>0,SUM(L87-M87)," ") | R87: =IF(O87>0,SUM(O87-(L87+P87))," ")
F88: 800 | G88: =(F88*D88)+(E88*F88) -> 0 | J88: =H88*I88 -> 0 | L88: =(J88+G88)-K88 -> 0 | N88: =IF(M88>0,SUM(L88-M88)," ") | R88: =IF(O88>0,SUM(O88-(L88+P88))," ")
F89: 800 | G89: =(F89*D89)+(E89*F89) -> 0 | J89: =H89*I89 -> 0 | L89: =(J89+G89)-K89 -> 0 | N89: =IF(M89>0,SUM(L89-M89)," ") | R89: =IF(O89>0,SUM(O89-(L89+P89))," ")
F90: 800 | G90: =(F90*D90)+(E90*F90) -> 0 | J90: =H90*I90 -> 0 | L90: =(J90+G90)-K90 -> 0 | N90: =IF(M90>0,SUM(L90-M90)," ") | R90: =IF(O90>0,SUM(O90-(L90+P90))," ")
F91: 800 | G91: =(F91*D91)+(E91*F91) -> 0 | J91: =H91*I91 -> 0 | L91: =(J91+G91)-K91 -> 0 | N91: =IF(M91>0,SUM(L91-M91)," ") | R91: =IF(O91>0,SUM(O91-(L91+P91))," ")
F92: 800 | G92: =(F92*D92)+(E92*F92) -> 0 | J92: =H92*I92 -> 0 | L92: =(J92+G92)-K92 -> 0 | N92: =IF(M92>0,SUM(L92-M92)," ") | R92: =IF(O92>0,SUM(O92-(L92+P92))," ")
F93: 800 | G93: =(F93*D93)+(E93*F93) -> 0 | J93: =H93*I93 -> 0 | L93: =(J93+G93)-K93 -> 0 | N93: =IF(M93>0,SUM(L93-M93)," ") | R93: =IF(O93>0,SUM(O93-(L93+P93))," ")
F94: 800 | G94: =(F94*D94)+(E94*F94) -> 0 | J94: =H94*I94 -> 0 | L94: =(J94+G94)-K94 -> 0 | N94: =IF(M94>0,SUM(L94-M94)," ") | R94: =IF(O94>0,SUM(O94-(L94+P94))," ")
... F100: 800 | G100: =(F100*D100)+(E100*F100) -> 0 | J100: =H100*I100 -> 0 | L100: =(J100+G100)-K100 -> 0 | N100: =IF(M100>0,SUM(L100-M100)," ") | R100: =IF(O100>0,SUM(O100-(L100+P100))," ")
D101: =SUM(D4:D100) -> 112 | E101: =SUM(E4:E100) -> 73 | G101: =SUM(G4:G100) -> 154510 | H101: =SUM(H4:H100) -> 0 | J101: =SUM(J4:J100) -> 0 | L101: =SUM(L4:L100) -> 154510 | N101: =IF(M101>0,SUM(L101-M101)," ") | O101: =SUM(O4:O100) -> 1840 | P101: =SUM(P4:P100) -> 0 | Q101: =SUM(Q4:Q100) -> 0 | R101: =SUM(R4:R100) -> -1680 | S101: =SUM(S4:S100) -> 0
D102: =D101+E101 -> 185
C108: CLEZIO - DURAPLIK
C109: DEMETRIUS - ULTRAMASSA
C110: CLEZIO - DURAPLIK
...

Sheet Vendas - JUL
A1: VENDAS | B1: VENDAS | D1: =D102 -> 220
A2: DATA | B2: VENDEDOR | C2: Clientes | D2: CELULOSE | H2: POLÍMERO | K2: DESCONTO CHEQUE | L2: TOTAL | M2: PARCIAL | N2: DEVENDO | O2: CHEQUES / PAGAMENTOS A MAIS OU A MENOS | T2: Forma de Pagamento | U2: Prazo | V2: Frete CIF / FOB | W2: OBSERVAÇÃO | X2: OBSERVAÇÃO
D3: PALOMA | E3: UCHOA | F3: PREÇO | G3: TOTAL | H3: QTD | I3: PREÇO TAB | J3: TOTAL | O3: VALOR VENDA | P3: COBRAMOS % | Q3: PAGAMOS % | R3: SALDO/DEBITO CLIENTE | S3: LUCRO/PREJ JUROS
A4: 45107 | C4: PAULO HENRIQUE | D4: 1 | F4: 850 | G4: =(F4*D4)+(E4*F4) -> 850 | J4: =H4*I4 -> 0 | L4: =(J4+G4)-K4 -> 850 | N4: =IF(M4>0,SUM(L4-M4)," ") | R4: =IF(O4>0,SUM(O4-(L4+P4))," ") | T4: A VISTA | U4: 0 | V4: FOB
A5: 45107 | C5: FORTMASSA | D5: 1 | F5: 850 | G5: =(F5*D5)+(E5*F5) -> 850 | J5: =H5*I5 -> 0 | L5: =(J5+G5)-K5 -> 850 | N5: =IF(M5>0,SUM(L5-M5)," ") | R5: =IF(O5>0,SUM(O5-(L5+P5))," ") | T5: A VISTA | U5: 0 | V5: FOB
A6: 45110 | C6: CHICO PEREIRA | D6: 2 | F6: 840 | G6: =(F6*D6)+(E6*F6) -> 1680 | J6: =H6*I6 -> 0 | L6: =(J6+G6)-K6 -> 1680 | N6: =IF(M6>0,SUM(L6-M6)," ") | R6: =IF(O6>0,SUM(O6-(L6+P6))," ") | T6: A VISTA | U6: 0 | V6: FOB
A7: 45110 | C7: FELIPE | D7: 1 | F7: 850 | G7: =(F7*D7)+(E7*F7) -> 850 | J7: =H7*I7 -> 0 | L7: =(J7+G7)-K7 -> 850 | N7: =IF(M7>0,SUM(L7-M7)," ") | R7: =IF(O7>0,SUM(O7-(L7+P7))," ") | T7: A VISTA | U7: 0 | V7: FOB
A8: 45110 | C8: ROBERTO LAGOA DO BANANA | E8: 1 | F8: 850 | G8: =(F8*D8)+(E8*F8) -> 850 | J8: =H8*I8 -> 0 | L8: =(J8+G8)-K8 -> 850 | N8: =IF(M8>0,SUM(L8-M8)," ") | O8: 1400 | R8: =IF(O8>0,SUM(O8-(L8+P8))," ") -> 550 | T8: CHEQUE/R$ | U8: 0 | V8: FOB | W8: 1100 + 300 | Y8: VALOR | Z8: QTD | AA8: =G101 -> 181620
A9: 45110 | C9: CONSTRUMIX | E9: 3 | F9: 820 | G9: =(F9*D9)+(E9*F9) -> 2460 | J9: =H9*I9 -> 0 | L9: =(J9+G9)-K9 -> 2460 | N9: =IF(M9>0,SUM(L9-M9)," ") | R9: =IF(O9>0,SUM(O9-(L9+P9))," ") | T9: A VISTA | U9: 0 | V9: FOB | Y9: 720 | AA9: =Y9*Z9 -> 0
A10: 45110 | C10: ARG MATHEUS | E10: 3 | F10: 830 | G10: =(F10*D10)+(E10*F10) -> 2490 | J10: =H10*I10 -> 0 | L10: =(J10+G10)-K10 -> 2490 | N10: =IF(M10>0,SUM(L10-M10)," ") | R10: =IF(O10>0,SUM(O10-(L10+P10))," ") | T10: A VISTA | U10: 0 | V10: FOB | Y10: 750 | AA10: =Y10*Z10 -> 0
A11: 45110 | C11: FORTMASSA | E11: 1 | F11: 850 | G11: =(F11*D11)+(E11*F11) -> 850 | J11: =H11*I11 -> 0 | L11: =(J11+G11)-K11 -> 850 | N11: =IF(M11>0,SUM(L11-M11)," ") | R11: =IF(O11>0,SUM(O11-(L11+P11))," ") | T11: A VISTA | U11: 0 | V11: FOB | Y11: 780 | AA11: =Y11*Z11 -> 0
A12: 45112 | C12: AREMIX | D12: 10 | F12: 820 | G12: =(F12*D12)+(E12*F12) -> 8200 | J12: =H12*I12 -> 0 | L12: =(J12+G12)-K12 -> 8200 | N12: =IF(M12>0,SUM(L12-M12)," ") | R12: =IF(O12>0,SUM(O12-(L12+P12))," ") | T12: A VISTA | U12: 0 | V12: FOB | Y12: 800 | AA12: =Y12*Z12 -> 0
A13: 45112 | C13: DEMETRIU | E13: 6 | F13: 800 | G13: =(F13*D13)+(E13*F13) -> 4800 | J13: =H13*I13 -> 0 | L13: =(J13+G13)-K13 -> 4800 | N13: =IF(M13>0,SUM(L13-M13)," ") | O13: 440 | R13: =IF(O13>0,SUM(O13-(L13+P13))," ") -> -4360 | S13: =P13-Q13 -> 0 | T13: A VISTA | U13: 30 | V13: FOB | W13: QUITACAO CREDITO | AA13: =AA8-(SUM(AA9:AA12)) -> 181620
A14: 45112 | C14: TODA OBRA | E14: 6 | F14: 820 | G14: =(F14*D14)+(E14*F14) -> 4920 | J14: =H14*I14 -> 0 | L14: =(J14+G14)-K14 -> 4920 | N14: =IF(M14>0,SUM(L14-M14)," ") | R14: =IF(O14>0,SUM(O14-(L14+P14))," ")
A15: 45112 | C15: LOURIMAR | E15: 4 | F15: 840 | G15: =(F15*D15)+(E15*F15) -> 3360 | J15: =H15*I15 -> 0 | L15: =(J15+G15)-K15 -> 3360 | N15: =IF(M15>0,SUM(L15-M15)," ") | R15: =IF(O15>0,SUM(O15-(L15+P15))," ")
A16: 45112 | C16: CLAUDIO MOSSORO | D16: 8 | F16: 830 | G16: =(F16*D16)+(E16*F16) -> 6640 | J16: =H16*I16 -> 0 | L16: =(J16+G16)-K16 -> 6640 | N16: =IF(M16>0,SUM(L16-M16)," ") | R16: =IF(O16>0,SUM(O16-(L16+P16))," ")
A17: 45112 | C17: IRINEU | D17: 1 | F17: 850 | G17: =(F17*D17)+(E17*F17) -> 850 | J17: =H17*I17 -> 0 | L17: =(J17+G17)-K17 -> 850 | N17: =IF(M17>0,SUM(L17-M17)," ") | R17: =IF(O17>0,SUM(O17-(L17+P17))," ")
A18: 45112 | C18: MASSA FIXA | D18: 1 | F18: 850 | G18: =(F18*D18)+(E18*F18) -> 850 | J18: =H18*I18 -> 0 | L18: =(J18+G18)-K18 -> 850 | N18: =IF(M18>0,SUM(L18-M18)," ") | R18: =IF(O18>0,SUM(O18-(L18+P18))," ")
A19: 45113 | C19: FORTMASSA | E19: 1 | F19: 850 | G19: =(F19*D19)+(E19*F19) -> 850 | J19: =H19*I19 -> 0 | L19: =(J19+G19)-K19 -> 850 | N19: =IF(M19>0,SUM(L19-M19)," ") | R19: =IF(O19>0,SUM(O19-(L19+P19))," ")
A20: 45113 | C20: ARG ROMA | D20: 4 | F20: 800 | G20: =(F20*D20)+(E20*F20) -> 3200 | J20: =H20*I20 -> 0 | L20: =(J20+G20)-K20 -> 3200 | N20: =IF(M20>0,SUM(L20-M20)," ") | R20: =IF(O20>0,SUM(O20-(L20+P20))," ")
A21: 45113 | C21: GETULIO | D21: 2 | F21: 850 | G21: =(F21*D21)+(E21*F21) -> 1700 | J21: =H21*I21 -> 0 | L21: =(J21+G21)-K21 -> 1700 | N21: =IF(M21>0,SUM(L21-M21)," ") | R21: =IF(O21>0,SUM(O21-(L21+P21))," ")
A22: 45113 | C22: GETULIO | D22: 1 | F22: 850 | G22: =(F22*D22)+(E22*F22) -> 850 | J22: =H22*I22 -> 0 | L22: =(J22+G22)-K22 -> 850 | N22: =IF(M22>0,SUM(L22-M22)," ") | R22: =IF(O22>0,SUM(O22-(L22+P22))," ")
A23: 45114 | C23: TIAGO TIANGUA | E23: 1 | F23: 850 | G23: =(F23*D23)+(E23*F23) -> 850 | J23: =H23*I23 -> 0 | L23: =(J23+G23)-K23 -> 850 | N23: =IF(M23>0,SUM(L23-M23)," ") | R23: =IF(O23>0,SUM(O23-(L23+P23))," ")
A24: 45117 | C24: FELIPE | D24: 2 | F24: 850 | G24: =(F24*D24)+(E24*F24) -> 1700 | J24: =H24*I24 -> 0 | L24: =(J24+G24)-K24 -> 1700 | N24: =IF(M24>0,SUM(L24-M24)," ") | R24: =IF(O24>0,SUM(O24-(L24+P24))," ")
A25: 45117 | C25: FORTMASSA | D25: 1 | F25: 850 | G25: =(F25*D25)+(E25*F25) -> 850 | J25: =H25*I25 -> 0 | L25: =(J25+G25)-K25 -> 850 | N25: =IF(M25>0,SUM(L25-M25)," ") | R25: =IF(O25>0,SUM(O25-(L25+P25))," ")
A26: 45117 | C26: DEMETRIU | E26: 6 | F26: 800 | G26: =(F26*D26)+(E26*F26) -> 4800 | J26: =H26*I26 -> 0 | L26: =(J26+G26)-K26 -> 4800 | N26: =IF(M26>0,SUM(L26-M26)," ") | R26: =IF(O26>0,SUM(O26-(L26+P26))," ")
A27: 45117 | C27: LOURIMAR | E27: 4 | F27: 840 | G27: =(F27*D27)+(E27*F27) -> 3360 | J27: =H27*I27 -> 0 | L27: =(J27+G27)-K27 -> 3360 | N27: =IF(M27>0,SUM(L27-M27)," ") | R27: =IF(O27>0,SUM(O27-(L27+P27))," ")
A28: 45117 | C28: REGINALDO | E28: 1 | F28: 840 | G28: =(F28*D28)+(E28*F28) -> 840 | J28: =H28*I28 -> 0 | L28: =(J28+G28)-K28 -> 840 | N28: =IF(M28>0,SUM(L28-M28)," ") | R28: =IF(O28>0,SUM(O28-(L28+P28))," ")
A29: 45117 | C29: CEARAMIX | E29: 1 | F29: 830 | G29: =(F29*D29)+(E29*F29) -> 830 | J29: =H29*I29 -> 0 | L29: =(J29+G29)-K29 -> 830 | N29: =IF(M29>0,SUM(L29-M29)," ") | R29: =IF(O29>0,SUM(O29-(L29+P29))," ")
A30: 45117 | C30: JULIO | D30: 2 | F30: 800 | G30: =(F30*D30)+(E30*F30) -> 1600 | J30: =H30*I30 -> 0 | L30: =(J30+G30)-K30 -> 1600 | N30: =IF(M30>0,SUM(L30-M30)," ") | R30: =IF(O30>0,SUM(O30-(L30+P30))," ")
A31: 45118 | C31: JOSIEL | D31: 1 | F31: 850 | G31: =(F31*D31)+(E31*F31) -> 850 | J31: =H31*I31 -> 0 | L31: =(J31+G31)-K31 -> 850 | N31: =IF(M31>0,SUM(L31-M31)," ") | R31: =IF(O31>0,SUM(O31-(L31+P31))," ")
A32: 45118 | C32: MASSA FIXA | D32: 1 | F32: 850 | G32: =(F32*D32)+(E32*F32) -> 850 | J32: =H32*I32 -> 0 | L32: =(J32+G32)-K32 -> 850 | N32: =IF(M32>0,SUM(L32-M32)," ") | R32: =IF(O32>0,SUM(O32-(L32+P32))," ")
A33: 45118 | C33: ARG MATEUS | D33: 3 | F33: 830 | G33: =(F33*D33)+(E33*F33) -> 2490 | J33: =H33*I33 -> 0 | L33: =(J33+G33)-K33 -> 2490 | N33: =IF(M33>0,SUM(L33-M33)," ") | R33: =IF(O33>0,SUM(O33-(L33+P33))," ")
A34: 45119 | C34: EVALDO SANTA INES | D34: 4 | F34: 820 | G34: =(F34*D34)+(E34*F34) -> 3280 | J34: =H34*I34 -> 0 | L34: =(J34+G34)-K34 -> 3280 | N34: =IF(M34>0,SUM(L34-M34)," ") | R34: =IF(O34>0,SUM(O34-(L34+P34))," ")
A35: 45119 | C35: GETULIO | D35: 2 | F35: 850 | G35: =(F35*D35)+(E35*F35) -> 1700 | J35: =H35*I35 -> 0 | L35: =(J35+G35)-K35 -> 1700 | N35: =IF(M35>0,SUM(L35-M35)," ") | R35: =IF(O35>0,SUM(O35-(L35+P35))," ")
A36: 45119 | C36: IRINEU | D36: 1 | F36: 850 | G36: =(F36*D36)+(E36*F36) -> 850 | J36: =H36*I36 -> 0 | L36: =(J36+G36)-K36 -> 850 | N36: =IF(M36>0,SUM(L36-M36)," ") | R36: =IF(O36>0,SUM(O36-(L36+P36))," ")
A37: 45120 | C37: JULIO | E37: 2 | F37: 800 | G37: =(F37*D37)+(E37*F37) -> 1600 | J37: =H37*I37 -> 0 | L37: =(J37+G37)-K37 -> 1600 | N37: =IF(M37>0,SUM(L37-M37)," ") | R37: =IF(O37>0,SUM(O37-(L37+P37))," ")
A38: 45120 | C38: FORTMASSA | D38: 1 | F38: 850 | G38: =(F38*D38)+(E38*F38) -> 850 | J38: =H38*I38 -> 0 | L38: =(J38+G38)-K38 -> 850 | N38: =IF(M38>0,SUM(L38-M38)," ") | R38: =IF(O38>0,SUM(O38-(L38+P38))," ")
A39: 45121 | C39: DEMETRIU | D39: 6 | F39: 800 | G39: =(F39*D39)+(E39*F39) -> 4800 | J39: =H39*I39 -> 0 | L39: =(J39+G39)-K39 -> 4800 | N39: =IF(M39>0,SUM(L39-M39)," ") | R39: =IF(O39>0,SUM(O39-(L39+P39))," ")
A40: 45122 | C40: JULIO | D40: 2 | F40: 800 | G40: =(F40*D40)+(E40*F40) -> 1600 | J40: =H40*I40 -> 0 | L40: =(J40+G40)-K40 -> 1600 | N40: =IF(M40>0,SUM(L40-M40)," ") | R40: =IF(O40>0,SUM(O40-(L40+P40))," ")
A41: 45122 | C41: MULTCOLA | E41: 2 | F41: 800 | G41: =(F41*D41)+(E41*F41) -> 1600 | J41: =H41*I41 -> 0 | L41: =(J41+G41)-K41 -> 1600 | N41: =IF(M41>0,SUM(L41-M41)," ") | R41: =IF(O41>0,SUM(O41-(L41+P41))," ")
A42: 45122 | C42: TODA OBRA | E42: 3 | F42: 820 | G42: =(F42*D42)+(E42*F42) -> 2460 | J42: =H42*I42 -> 0 | L42: =(J42+G42)-K42 -> 2460 | N42: =IF(M42>0,SUM(L42-M42)," ") | R42: =IF(O42>0,SUM(O42-(L42+P42))," ")
A43: 45122 | C43: THIAGO TIANGUA | E43: 1 | F43: 850 | G43: =(F43*D43)+(E43*F43) -> 850 | J43: =H43*I43 -> 0 | L43: =(J43+G43)-K43 -> 850 | N43: =IF(M43>0,SUM(L43-M43)," ") | R43: =IF(O43>0,SUM(O43-(L43+P43))," ")
A44: 45124 | C44: FELIPE | D44: 2 | F44: 850 | G44: =(F44*D44)+(E44*F44) -> 1700 | J44: =H44*I44 -> 0 | L44: =(J44+G44)-K44 -> 1700 | N44: =IF(M44>0,SUM(L44-M44)," ") | R44: =IF(O44>0,SUM(O44-(L44+P44))," ")
A45: 45125 | C45: MASSA FIXA | D45: 1 | F45: 850 | G45: =(F45*D45)+(E45*F45) -> 850 | J45: =H45*I45 -> 0 | L45: =(J45+G45)-K45 -> 850 | N45: =IF(M45>0,SUM(L45-M45)," ") | R45: =IF(O45>0,SUM(O45-(L45+P45))," ")
A46: 45125 | C46: IRINEU | D46: 1 | F46: 850 | G46: =(F46*D46)+(E46*F46) -> 850 | J46: =H46*I46 -> 0 | L46: =(J46+G46)-K46 -> 850 | N46: =IF(M46>0,SUM(L46-M46)," ") | R46: =IF(O46>0,SUM(O46-(L46+P46))," ")
A47: 45125 | C47: FORTMASSA | D47: 1 | F47: 850 | G47: =(F47*D47)+(E47*F47) -> 850 | J47: =H47*I47 -> 0 | L47: =(J47+G47)-K47 -> 850 | N47: =IF(M47>0,SUM(L47-M47)," ") | R47: =IF(O47>0,SUM(O47-(L47+P47))," ")
A48: 45125 | C48: CLAUDIO MOSSORO | D48: 8 | F48: 830 | G48: =(F48*D48)+(E48*F48) -> 6640 | J48: =H48*I48 -> 0 | L48: =(J48+G48)-K48 -> 6640 | N48: =IF(M48>0,SUM(L48-M48)," ") | R48: =IF(O48>0,SUM(O48-(L48+P48))," ")
A49: 45124 | C49: CHICO PEREIRA | E49: 2 | F49: 840 | G49: =(F49*D49)+(E49*F49) -> 1680 | J49: =H49*I49 -> 0 | L49: =(J49+G49)-K49 -> 1680 | N49: =IF(M49>0,SUM(L49-M49)," ") | R49: =IF(O49>0,SUM(O49-(L49+P49))," ")
A50: 45124 | C50: MOEBIO | E50: 1 | F50: 800 | G50: =(F50*D50)+(E50*F50) -> 800 | J50: =H50*I50 -> 0 | L50: =(J50+G50)-K50 -> 800 | N50: =IF(M50>0,SUM(L50-M50)," ") | R50: =IF(O50>0,SUM(O50-(L50+P50))," ")
A51: 45124 | C51: IONALDO | E51: 1 | F51: 830 | G51: =(F51*D51)+(E51*F51) -> 830 | J51: =H51*I51 -> 0 | L51: =(J51+G51)-K51 -> 830 | N51: =IF(M51>0,SUM(L51-M51)," ") | R51: =IF(O51>0,SUM(O51-(L51+P51))," ")
A52: 45124 | C52: GETULIO | E52: 2 | F52: 850 | G52: =(F52*D52)+(E52*F52) -> 1700 | J52: =H52*I52 -> 0 | L52: =(J52+G52)-K52 -> 1700 | N52: =IF(M52>0,SUM(L52-M52)," ") | R52: =IF(O52>0,SUM(O52-(L52+P52))," ")
A53: 45124 | C53: CONSTRUMIX | E53: 2 | F53: 830 | G53: =(F53*D53)+(E53*F53) -> 1660 | J53: =H53*I53 -> 0 | L53: =(J53+G53)-K53 -> 1660 | N53: =IF(M53>0,SUM(L53-M53)," ") | R53: =IF(O53>0,SUM(O53-(L53+P53))," ")
A54: 45125 | C54: ROBERTO LAGOA DO BANANA | E54: 1 | F54: 850 | G54: =(F54*D54)+(E54*F54) -> 850 | J54: =H54*I54 -> 0 | L54: =(J54+G54)-K54 -> 850 | N54: =IF(M54>0,SUM(L54-M54)," ") | R54: =IF(O54>0,SUM(O54-(L54+P54))," ")
A55: 45125 | C55: LOURIMAR | E55: 4 | F55: 840 | G55: =(F55*D55)+(E55*F55) -> 3360 | J55: =H55*I55 -> 0 | L55: =(J55+G55)-K55 -> 3360 | N55: =IF(M55>0,SUM(L55-M55)," ") | R55: =IF(O55>0,SUM(O55-(L55+P55))," ")
A56: 45126 | C56: AREMIX | D56: 10 | F56: 820 | G56: =(F56*D56)+(E56*F56) -> 8200 | J56: =H56*I56 -> 0 | L56: =(J56+G56)-K56 -> 8200 | N56: =IF(M56>0,SUM(L56-M56)," ") | R56: =IF(O56>0,SUM(O56-(L56+P56))," ")
A57: 45126 | C57: EVALDO SANTA INES | E57: 5 | F57: 830 | G57: =(F57*D57)+(E57*F57) -> 4150 | J57: =H57*I57 -> 0 | L57: =(J57+G57)-K57 -> 4150 | N57: =IF(M57>0,SUM(L57-M57)," ") | R57: =IF(O57>0,SUM(O57-(L57+P57))," ")
A58: 45126 | C58: ARG MATEUS | E58: 5 | F58: 820 | G58: =(F58*D58)+(E58*F58) -> 4100 | J58: =H58*I58 -> 0 | L58: =(J58+G58)-K58 -> 4100 | N58: =IF(M58>0,SUM(L58-M58)," ") | R58: =IF(O58>0,SUM(O58-(L58+P58))," ")
A59: 45126 | C59: DEMETRIU | E59: 6 | F59: 800 | G59: =(F59*D59)+(E59*F59) -> 4800 | J59: =H59*I59 -> 0 | L59: =(J59+G59)-K59 -> 4800 | N59: =IF(M59>0,SUM(L59-M59)," ") | R59: =IF(O59>0,SUM(O59-(L59+P59))," ")
A60: 45126 | C60: CARLOS | E60: 1 | F60: 850 | G60: =(F60*D60)+(E60*F60) -> 850 | J60: =H60*I60 -> 0 | L60: =(J60+G60)-K60 -> 850 | N60: =IF(M60>0,SUM(L60-M60)," ") | R60: =IF(O60>0,SUM(O60-(L60+P60))," ")
A61: 45127 | C61: MULTCOLA | E61: 2 | F61: 800 | G61: =(F61*D61)+(E61*F61) -> 1600 | J61: =H61*I61 -> 0 | L61: =(J61+G61)-K61 -> 1600 | N61: =IF(M61>0,SUM(L61-M61)," ") | R61: =IF(O61>0,SUM(O61-(L61+P61))," ")
A62: 45127 | C62: CONSTRUMIX | E62: 1 | F62: 830 | G62: =(F62*D62)+(E62*F62) -> 830 | J62: =H62*I62 -> 0 | L62: =(J62+G62)-K62 -> 830 | N62: =IF(M62>0,SUM(L62-M62)," ") | R62: =IF(O62>0,SUM(O62-(L62+P62))," ")
A63: 45127 | C63: TODA OBRA | E63: 4 | F63: 820 | G63: =(F63*D63)+(E63*F63) -> 3280 | J63: =H63*I63 -> 0 | L63: =(J63+G63)-K63 -> 3280 | N63: =IF(M63>0,SUM(L63-M63)," ") | R63: =IF(O63>0,SUM(O63-(L63+P63))," ")
A64: 45127 | C64: GETULIO | D64: 1 | F64: 850 | G64: =(F64*D64)+(E64*F64) -> 850 | J64: =H64*I64 -> 0 | L64: =(J64+G64)-K64 -> 850 | N64: =IF(M64>0,SUM(L64-M64)," ") | R64: =IF(O64>0,SUM(O64-(L64+P64))," ")
A65: 45127 | C65: FORTMASSA | D65: 1 | F65: 850 | G65: =(F65*D65)+(E65*F65) -> 850 | J65: =H65*I65 -> 0 | L65: =(J65+G65)-K65 -> 850 | N65: =IF(M65>0,SUM(L65-M65)," ") | R65: =IF(O65>0,SUM(O65-(L65+P65))," ")
A66: 45128 | C66: JULIO | D66: 2 | F66: 800 | G66: =(F66*D66)+(E66*F66) -> 1600 | J66: =H66*I66 -> 0 | L66: =(J66+G66)-K66 -> 1600 | N66: =IF(M66>0,SUM(L66-M66)," ") | R66: =IF(O66>0,SUM(O66-(L66+P66))," ")
A67: 45128 | C67: FELIPE | D67: 1 | F67: 850 | G67: =(F67*D67)+(E67*F67) -> 850 | J67: =H67*I67 -> 0 | L67: =(J67+G67)-K67 -> 850 | N67: =IF(M67>0,SUM(L67-M67)," ") | R67: =IF(O67>0,SUM(O67-(L67+P67))," ")
A68: 45129 | C68: GETULIO | D68: 2 | F68: 850 | G68: =(F68*D68)+(E68*F68) -> 1700 | J68: =H68*I68 -> 0 | L68: =(J68+G68)-K68 -> 1700 | N68: =IF(M68>0,SUM(L68-M68)," ") | R68: =IF(O68>0,SUM(O68-(L68+P68))," ")
A69: 45130 | C69: IRINEU | D69: 1 | F69: 850 | G69: =(F69*D69)+(E69*F69) -> 850 | J69: =H69*I69 -> 0 | L69: =(J69+G69)-K69 -> 850 | N69: =IF(M69>0,SUM(L69-M69)," ") | R69: =IF(O69>0,SUM(O69-(L69+P69))," ")
A70: 45131 | C70: ANDRE | D70: 1 | F70: 850 | G70: =(F70*D70)+(E70*F70) -> 850 | J70: =H70*I70 -> 0 | L70: =(J70+G70)-K70 -> 850 | N70: =IF(M70>0,SUM(L70-M70)," ") | R70: =IF(O70>0,SUM(O70-(L70+P70))," ")
A71: 45131 | C71: LOURIMAR | D71: 4 | F71: 840 | G71: =(F71*D71)+(E71*F71) -> 3360 | J71: =H71*I71 -> 0 | L71: =(J71+G71)-K71 -> 3360 | N71: =IF(M71>0,SUM(L71-M71)," ") | R71: =IF(O71>0,SUM(O71-(L71+P71))," ")
A72: 45132 | C72: FORTMASSA | E72: 1 | F72: 850 | G72: =(F72*D72)+(E72*F72) -> 850 | J72: =H72*I72 -> 0 | L72: =(J72+G72)-K72 -> 850 | N72: =IF(M72>0,SUM(L72-M72)," ") | R72: =IF(O72>0,SUM(O72-(L72+P72))," ")
A73: 45132 | C73: ARG LUZ E COLA | E73: 1 | F73: 820 | G73: =(F73*D73)+(E73*F73) -> 820 | J73: =H73*I73 -> 0 | L73: =(J73+G73)-K73 -> 820 | N73: =IF(M73>0,SUM(L73-M73)," ") | R73: =IF(O73>0,SUM(O73-(L73+P73))," ")
A74: 45132 | C74: ARG MATEUS | E74: 2 | F74: 830 | G74: =(F74*D74)+(E74*F74) -> 1660 | J74: =H74*I74 -> 0 | L74: =(J74+G74)-K74 -> 1660 | N74: =IF(M74>0,SUM(L74-M74)," ") | R74: =IF(O74>0,SUM(O74-(L74+P74))," ")
A75: 45133 | C75: EVALDO SANTA INES | D75: 5 | F75: 830 | G75: =(F75*D75)+(E75*F75) -> 4150 | J75: =H75*I75 -> 0 | L75: =(J75+G75)-K75 -> 4150 | N75: =IF(M75>0,SUM(L75-M75)," ") | R75: =IF(O75>0,SUM(O75-(L75+P75))," ")
A76: 45133 | C76: CHICO PEREIRA | E76: 2 | F76: 830 | G76: =(F76*D76)+(E76*F76) -> 1660 | J76: =H76*I76 -> 0 | L76: =(J76+G76)-K76 -> 1660 | N76: =IF(M76>0,SUM(L76-M76)," ") | R76: =IF(O76>0,SUM(O76-(L76+P76))," ")
A77: 45133 | C77: IRINEU | D77: 1 | F77: 850 | G77: =(F77*D77)+(E77*F77) -> 850 | J77: =H77*I77 -> 0 | L77: =(J77+G77)-K77 -> 850 | N77: =IF(M77>0,SUM(L77-M77)," ") | R77: =IF(O77>0,SUM(O77-(L77+P77))," ")
A78: 45133 | C78: DEMETRIU | E78: 6 | F78: 800 | G78: =(F78*D78)+(E78*F78) -> 4800 | J78: =H78*I78 -> 0 | L78: =(J78+G78)-K78 -> 4800 | N78: =IF(M78>0,SUM(L78-M78)," ") | R78: =IF(O78>0,SUM(O78-(L78+P78))," ")
A79: 45134 | C79: MULTCOLA | E79: 2 | F79: 800 | G79: =(F79*D79)+(E79*F79) -> 1600 | J79: =H79*I79 -> 0 | L79: =(J79+G79)-K79 -> 1600 | N79: =IF(M79>0,SUM(L79-M79)," ") | R79: =IF(O79>0,SUM(O79-(L79+P79))," ")
A80: 45134 | C80: FORTMASSA | D80: 1 | F80: 850 | G80: =(F80*D80)+(E80*F80) -> 850 | J80: =H80*I80 -> 0 | L80: =(J80+G80)-K80 -> 850 | N80: =IF(M80>0,SUM(L80-M80)," ") | R80: =IF(O80>0,SUM(O80-(L80+P80))," ")
A81: 45134 | C81: MOEBIO | D81: 1 | F81: 800 | G81: =(F81*D81)+(E81*F81) -> 800 | J81: =H81*I81 -> 0 | L81: =(J81+G81)-K81 -> 800 | N81: =IF(M81>0,SUM(L81-M81)," ") | R81: =IF(O81>0,SUM(O81-(L81+P81))," ")
A82: 45134 | C82: CLAUDIO MOSSORO | D82: 4 | F82: 830 | G82: =(F82*D82)+(E82*F82) -> 3320 | J82: =H82*I82 -> 0 | L82: =(J82+G82)-K82 -> 3320 | N82: =IF(M82>0,SUM(L82-M82)," ") | R82: =IF(O82>0,SUM(O82-(L82+P82))," ")
A83: 45135 | C83: LOURIMAR | D83: 4 | F83: 840 | G83: =(F83*D83)+(E83*F83) -> 3360 | J83: =H83*I83 -> 0 | L83: =(J83+G83)-K83 -> 3360 | N83: =IF(M83>0,SUM(L83-M83)," ") | R83: =IF(O83>0,SUM(O83-(L83+P83))," ")
A84: 45136 | C84: FELIPE | D84: 2 | F84: 850 | G84: =(F84*D84)+(E84*F84) -> 1700 | J84: =H84*I84 -> 0 | L84: =(J84+G84)-K84 -> 1700 | N84: =IF(M84>0,SUM(L84-M84)," ") | R84: =IF(O84>0,SUM(O84-(L84+P84))," ")
A85: 45136 | C85: GETULIO | D85: 2 | F85: 850 | G85: =(F85*D85)+(E85*F85) -> 1700 | J85: =H85*I85 -> 0 | L85: =(J85+G85)-K85 -> 1700 | N85: =IF(M85>0,SUM(L85-M85)," ") | R85: =IF(O85>0,SUM(O85-(L85+P85))," ")
A86: 45138 | C86: IRINEU | D86: 1 | F86: 850 | G86: =(F86*D86)+(E86*F86) -> 850 | J86: =H86*I86 -> 0 | L86: =(J86+G86)-K86 -> 850 | N86: =IF(M86>0,SUM(L86-M86)," ") | R86: =IF(O86>0,SUM(O86-(L86+P86))," ")
A87: 45138 | C87: FORTMASSA | D87: 1 | F87: 850 | G87: =(F87*D87)+(E87*F87) -> 850 | J87: =H87*I87 -> 0 | L87: =(J87+G87)-K87 -> 850 | N87: =IF(M87>0,SUM(L87-M87)," ") | R87: =IF(O87>0,SUM(O87-(L87+P87))," ")
A88: 45138 | C88: DEMETRIU | D88: 3 | F88: 800 | G88: =(F88*D88)+(E88*F88) -> 2400 | J88: =H88*I88 -> 0 | L88: =(J88+G88)-K88 -> 2400 | N88: =IF(M88>0,SUM(L88-M88)," ") | R88: =IF(O88>0,SUM(O88-(L88+P88))," ")
A89: 45138 | C89: ARG ROMA | E89: 4 | F89: 800 | G89: =(F89*D89)+(E89*F89) -> 3200 | J89: =H89*I89 -> 0 | L89: =(J89+G89)-K89 -> 3200 | N89: =IF(M89>0,SUM(L89-M89)," ") | R89: =IF(O89>0,SUM(O89-(L89+P89))," ")
F90: 800 | G90: =(F90*D90)+(E90*F90) -> 0 | J90: =H90*I90 -> 0 | L90: =(J90+G90)-K90 -> 0 | N90: =IF(M90>0,SUM(L90-M90)," ") | R90: =IF(O90>0,SUM(O90-(L90+P90))," ")
F91: 800 | G91: =(F91*D91)+(E91*F91) -> 0 | J91: =H91*I91 -> 0 | L91: =(J91+G91)-K91 -> 0 | N91: =IF(M91>0,SUM(L91-M91)," ") | R91: =IF(O91>0,SUM(O91-(L91+P91))," ")
F92: 800 | G92: =(F92*D92)+(E92*F92) -> 0 | J92: =H92*I92 -> 0 | L92: =(J92+G92)-K92 -> 0 | N92: =IF(M92>0,SUM(L92-M92)," ") | R92: =IF(O92>0,SUM(O92-(L92+P92))," ")
F93: 800 | G93: =(F93*D93)+(E93*F93) -> 0 | J93: =H93*I93 -> 0 | L93: =(J93+G93)-K93 -> 0 | N93: =IF(M93>0,SUM(L93-M93)," ") | R93: =IF(O93>0,SUM(O93-(L93+P93))," ")
F94: 800 | G94: =(F94*D94)+(E94*F94) -> 0 | J94: =H94*I94 -> 0 | L94: =(J94+G94)-K94 -> 0 | N94: =IF(M94>0,SUM(L94-M94)," ") | R94: =IF(O94>0,SUM(O94-(L94+P94))," ")
F95: 800 | G95: =(F95*D95)+(E95*F95) -> 0 | J95: =H95*I95 -> 0 | L95: =(J95+G95)-K95 -> 0 | N95: =IF(M95>0,SUM(L95-M95)," ") | R95: =IF(O95>0,SUM(O95-(L95+P95))," ")
F96: 800 | G96: =(F96*D96)+(E96*F96) -> 0 | J96: =H96*I96 -> 0 | L96: =(J96+G96)-K96 -> 0 | N96: =IF(M96>0,SUM(L96-M96)," ") | R96: =IF(O96>0,SUM(O96-(L96+P96))," ")
F97: 800 | G97: =(F97*D97)+(E97*F97) -> 0 | J97: =H97*I97 -> 0 | L97: =(J97+G97)-K97 -> 0 | N97: =IF(M97>0,SUM(L97-M97)," ") | R97: =IF(O97>0,SUM(O97-(L97+P97))," ")
F98: 800 | G98: =(F98*D98)+(E98*F98) -> 0 | J98: =H98*I98 -> 0 | L98: =(J98+G98)-K98 -> 0 | N98: =IF(M98>0,SUM(L98-M98)," ") | R98: =IF(O98>0,SUM(O98-(L98+P98))," ")
F99: 800 | G99: =(F99*D99)+(E99*F99) -> 0 | J99: =H99*I99 -> 0 | L99: =(J99+G99)-K99 -> 0 | N99: =IF(M99>0,SUM(L99-M99)," ") | R99: =IF(O99>0,SUM(O99-(L99+P99))," ")
F100: 800 | G100: =(F100*D100)+(E100*F100) -> 0 | J100: =H100*I100 -> 0 | L100: =(J100+G100)-K100 -> 0 | N100: =IF(M100>0,SUM(L100-M100)," ") | R100: =IF(O100>0,SUM(O100-(L100+P100))," ")
...

Sheet Vendas - AGO
A1: VENDAS | B1: VENDAS | D1: =D102 -> 245
A2: DATA | B2: VENDEDOR | C2: Clientes | D2: CELULOSE | H2: POLÍMERO | K2: DESCONTO CHEQUE | L2: TOTAL | M2: PARCIAL | N2: DEVENDO | O2: CHEQUES / PAGAMENTOS A MAIS OU A MENOS | T2: Forma de Pagamento | U2: Prazo | V2: Frete CIF / FOB | W2: OBSERVAÇÃO | X2: OBSERVAÇÃO
D3: PALOMA | E3: UCHOA | F3: PREÇO | G3: TOTAL | H3: QTD | I3: PREÇO TAB | J3: TOTAL | O3: VALOR VENDA | P3: COBRAMOS % | Q3: PAGAMOS % | R3: SALDO/DEBITO CLIENTE | S3: LUCRO/PREJ JUROS
A4: 45138 | C4: ROBERTO LAGOA DO BANANA | E4: 1 | F4: 850 | G4: =(F4*D4)+(E4*F4) -> 850 | J4: =H4*I4 -> 0 | L4: =(J4+G4)-K4 -> 850 | N4: =IF(M4>0,SUM(L4-M4)," ") | R4: =IF(O4>0,SUM(O4-(L4+P4))," ") | T4: A VISTA | U4: 0 | V4: FOB
A5: 45140 | C5: JOSIEL | D5: 1 | F5: 850 | G5: =(F5*D5)+(E5*F5) -> 850 | J5: =H5*I5 -> 0 | L5: =(J5+G5)-K5 -> 850 | N5: =IF(M5>0,SUM(L5-M5)," ") | R5: =IF(O5>0,SUM(O5-(L5+P5))," ") | T5: A VISTA | U5: 0 | V5: FOB
A6: 45140 | C6: TODA OBRA | E6: 1 | F6: 820 | G6: =(F6*D6)+(E6*F6) -> 820 | J6: =H6*I6 -> 0 | L6: =(J6+G6)-K6 -> 820 | N6: =IF(M6>0,SUM(L6-M6)," ") | R6: =IF(O6>0,SUM(O6-(L6+P6))," ") | T6: A VISTA | U6: 0 | V6: FOB
A7: 45140 | C7: DEMETRIU | D7: 3 | F7: 800 | G7: =(F7*D7)+(E7*F7) -> 2400 | J7: =H7*I7 -> 0 | L7: =(J7+G7)-K7 -> 2400 | N7: =IF(M7>0,SUM(L7-M7)," ") | R7: =IF(O7>0,SUM(O7-(L7+P7))," ") | T7: A VISTA | U7: 0 | V7: FOB
A8: 45140 | C8: ARG MATEUS | D8: 4 | F8: 830 | G8: =(F8*D8)+(E8*F8) -> 3320 | J8: =H8*I8 -> 0 | L8: =(J8+G8)-K8 -> 3320 | N8: =IF(M8>0,SUM(L8-M8)," ") | O8: 1400 | R8: =IF(O8>0,SUM(O8-(L8+P8))," ") -> -1920 | T8: CHEQUE/R$ | U8: 0 | V8: FOB | W8: 1100 + 300 | Y8: VALOR | Z8: QTD | AA8: =G101 -> 202040
A9: 45140 | C9: FORTMASSA | D9: 1 | F9: 850 | G9: =(F9*D9)+(E9*F9) -> 850 | J9: =H9*I9 -> 0 | L9: =(J9+G9)-K9 -> 850 | N9: =IF(M9>0,SUM(L9-M9)," ") | R9: =IF(O9>0,SUM(O9-(L9+P9))," ") | T9: A VISTA | U9: 0 | V9: FOB | Y9: 720 | AA9: =Y9*Z9 -> 0
A10: 45141 | C10: GETULIO | D10: 1 | F10: 850 | G10: =(F10*D10)+(E10*F10) -> 850 | J10: =H10*I10 -> 0 | L10: =(J10+G10)-K10 -> 850 | N10: =IF(M10>0,SUM(L10-M10)," ") | R10: =IF(O10>0,SUM(O10-(L10+P10))," ") | T10: A VISTA | U10: 0 | V10: FOB | Y10: 750 | AA10: =Y10*Z10 -> 0
A11: 45141 | C11: IRINEU | D11: 1 | F11: 850 | G11: =(F11*D11)+(E11*F11) -> 850 | J11: =H11*I11 -> 0 | L11: =(J11+G11)-K11 -> 850 | N11: =IF(M11>0,SUM(L11-M11)," ") | R11: =IF(O11>0,SUM(O11-(L11+P11))," ") | T11: A VISTA | U11: 0 | V11: FOB | Y11: 780 | AA11: =Y11*Z11 -> 0
A12: 45141 | C12: MASSA FIXA | D12: 1 | F12: 820 | G12: =(F12*D12)+(E12*F12) -> 820 | J12: =H12*I12 -> 0 | L12: =(J12+G12)-K12 -> 820 | N12: =IF(M12>0,SUM(L12-M12)," ") | R12: =IF(O12>0,SUM(O12-(L12+P12))," ") | T12: A VISTA | U12: 0 | V12: FOB | Y12: 800 | AA12: =Y12*Z12 -> 0
A13: 45141 | C13: CLAUDIO MOSSORO | D13: 8 | F13: 830 | G13: =(F13*D13)+(E13*F13) -> 6640 | J13: =H13*I13 -> 0 | L13: =(J13+G13)-K13 -> 6640 | N13: =IF(M13>0,SUM(L13-M13)," ") | O13: 440 | R13: =IF(O13>0,SUM(O13-(L13+P13))," ") -> -6200 | S13: =P13-Q13 -> 0 | T13: A VISTA | U13: 30 | V13: FOB | W13: QUITACAO CREDITO | AA13: =AA8-(SUM(AA9:AA12)) -> 202040
A14: 45141 | C14: AREMIX | D14: 10 | F14: 820 | G14: =(F14*D14)+(E14*F14) -> 8200 | J14: =H14*I14 -> 0 | L14: =(J14+G14)-K14 -> 8200 | N14: =IF(M14>0,SUM(L14-M14)," ") | R14: =IF(O14>0,SUM(O14-(L14+P14))," ")
A15: 45141 | C15: DEMETRIU | E15: 6 | F15: 800 | G15: =(F15*D15)+(E15*F15) -> 4800 | J15: =H15*I15 -> 0 | L15: =(J15+G15)-K15 -> 4800 | N15: =IF(M15>0,SUM(L15-M15)," ") | R15: =IF(O15>0,SUM(O15-(L15+P15))," ")
A16: 45141 | C16: TODA OBRA | E16: 6 | F16: 820 | G16: =(F16*D16)+(E16*F16) -> 4920 | J16: =H16*I16 -> 0 | L16: =(J16+G16)-K16 -> 4920 | N16: =IF(M16>0,SUM(L16-M16)," ") | R16: =IF(O16>0,SUM(O16-(L16+P16))," ")
A17: 45142 | C17: FORTMASSA | D17: 1 | F17: 850 | G17: =(F17*D17)+(E17*F17) -> 850 | J17: =H17*I17 -> 0 | L17: =(J17+G17)-K17 -> 850 | N17: =IF(M17>0,SUM(L17-M17)," ") | R17: =IF(O17>0,SUM(O17-(L17+P17))," ")
A18: 45142 | C18: LOURIMAR | E18: 4 | F18: 840 | G18: =(F18*D18)+(E18*F18) -> 3360 | J18: =H18*I18 -> 0 | L18: =(J18+G18)-K18 -> 3360 | N18: =IF(M18>0,SUM(L18-M18)," ") | R18: =IF(O18>0,SUM(O18-(L18+P18))," ")
A19: 45143 | C19: EVALDO SANTA INES | D19: 5 | F19: 830 | G19: =(F19*D19)+(E19*F19) -> 4150 | J19: =H19*I19 -> 0 | L19: =(J19+G19)-K19 -> 4150 | N19: =IF(M19>0,SUM(L19-M19)," ") | R19: =IF(O19>0,SUM(O19-(L19+P19))," ")
A20: 45143 | C20: GETULIO | D20: 2 | F20: 850 | G20: =(F20*D20)+(E20*F20) -> 1700 | J20: =H20*I20 -> 0 | L20: =(J20+G20)-K20 -> 1700 | N20: =IF(M20>0,SUM(L20-M20)," ") | R20: =IF(O20>0,SUM(O20-(L20+P20))," ")
A21: 45145 | C21: IRINEU | D21: 1 | F21: 850 | G21: =(F21*D21)+(E21*F21) -> 850 | J21: =H21*I21 -> 0 | L21: =(J21+G21)-K21 -> 850 | N21: =IF(M21>0,SUM(L21-M21)," ") | R21: =IF(O21>0,SUM(O21-(L21+P21))," ")
A22: 45145 | C22: FORTMASSA | D22: 1 | F22: 850 | G22: =(F22*D22)+(E22*F22) -> 850 | J22: =H22*I22 -> 0 | L22: =(J22+G22)-K22 -> 850 | N22: =IF(M22>0,SUM(L22-M22)," ") | R22: =IF(O22>0,SUM(O22-(L22+P22))," ")
A23: 45146 | C23: REGINALDO | E23: 1 | F23: 840 | G23: =(F23*D23)+(E23*F23) -> 840 | J23: =H23*I23 -> 0 | L23: =(J23+G23)-K23 -> 840 | N23: =IF(M23>0,SUM(L23-M23)," ") | R23: =IF(O23>0,SUM(O23-(L23+P23))," ")
A24: 45146 | C24: GETULIO | D24: 1 | F24: 850 | G24: =(F24*D24)+(E24*F24) -> 850 | J24: =H24*I24 -> 0 | L24: =(J24+G24)-K24 -> 850 | N24: =IF(M24>0,SUM(L24-M24)," ") | R24: =IF(O24>0,SUM(O24-(L24+P24))," ")
A25: 45147 | C25: GETULIO | D25: 3 | F25: 850 | G25: =(F25*D25)+(E25*F25) -> 2550 | J25: =H25*I25 -> 0 | L25: =(J25+G25)-K25 -> 2550 | N25: =IF(M25>0,SUM(L25-M25)," ") | R25: =IF(O25>0,SUM(O25-(L25+P25))," ")
A26: 45147 | C26: ARG MATEUS | D26: 4 | F26: 830 | G26: =(F26*D26)+(E26*F26) -> 3320 | J26: =H26*I26 -> 0 | L26: =(J26+G26)-K26 -> 3320 | N26: =IF(M26>0,SUM(L26-M26)," ") | R26: =IF(O26>0,SUM(O26-(L26+P26))," ")
A27: 45147 | C27: CHICO PEREIRA | E27: 2 | F27: 830 | G27: =(F27*D27)+(E27*F27) -> 1660 | J27: =H27*I27 -> 0 | L27: =(J27+G27)-K27 -> 1660 | N27: =IF(M27>0,SUM(L27-M27)," ") | R27: =IF(O27>0,SUM(O27-(L27+P27))," ")
A28: 45148 | C28: FELIPE | D28: 2 | F28: 850 | G28: =(F28*D28)+(E28*F28) -> 1700 | J28: =H28*I28 -> 0 | L28: =(J28+G28)-K28 -> 1700 | N28: =IF(M28>0,SUM(L28-M28)," ") | R28: =IF(O28>0,SUM(O28-(L28+P28))," ")
A29: 45148 | C29: NEWMASSA | D29: 2 | F29: 800 | G29: =(F29*D29)+(E29*F29) -> 1600 | J29: =H29*I29 -> 0 | L29: =(J29+G29)-K29 -> 1600 | N29: =IF(M29>0,SUM(L29-M29)," ") | R29: =IF(O29>0,SUM(O29-(L29+P29))," ")
A30: 45148 | C30: FORTMASSA | D30: 1 | F30: 850 | G30: =(F30*D30)+(E30*F30) -> 850 | J30: =H30*I30 -> 0 | L30: =(J30+G30)-K30 -> 850 | N30: =IF(M30>0,SUM(L30-M30)," ") | R30: =IF(O30>0,SUM(O30-(L30+P30))," ")
A31: 45148 | C31: CLAUDIO MOSSORO | D31: 8 | F31: 830 | G31: =(F31*D31)+(E31*F31) -> 6640 | J31: =H31*I31 -> 0 | L31: =(J31+G31)-K31 -> 6640 | N31: =IF(M31>0,SUM(L31-M31)," ") | R31: =IF(O31>0,SUM(O31-(L31+P31))," ")
A32: 45148 | C32: TODA OBRA | E32: 6 | F32: 820 | G32: =(F32*D32)+(E32*F32) -> 4920 | J32: =H32*I32 -> 0 | L32: =(J32+G32)-K32 -> 4920 | N32: =IF(M32>0,SUM(L32-M32)," ") | R32: =IF(O32>0,SUM(O32-(L32+P32))," ")
A33: 45148 | C33: DEMETRIU | E33: 6 | F33: 800 | G33: =(F33*D33)+(E33*F33) -> 4800 | J33: =H33*I33 -> 0 | L33: =(J33+G33)-K33 -> 4800 | N33: =IF(M33>0,SUM(L33-M33)," ") | R33: =IF(O33>0,SUM(O33-(L33+P33))," ")
A34: 45148 | C34: LOURIMAR | E34: 4 | F34: 840 | G34: =(F34*D34)+(E34*F34) -> 3360 | J34: =H34*I34 -> 0 | L34: =(J34+G34)-K34 -> 3360 | N34: =IF(M34>0,SUM(L34-M34)," ") | R34: =IF(O34>0,SUM(O34-(L34+P34))," ")
A35: 45149 | C35: NEWMASSA | E35: 2 | F35: 800 | G35: =(F35*D35)+(E35*F35) -> 1600 | J35: =H35*I35 -> 0 | L35: =(J35+G35)-K35 -> 1600 | N35: =IF(M35>0,SUM(L35-M35)," ") | R35: =IF(O35>0,SUM(O35-(L35+P35))," ")
A36: 45152 | C36: IRINEU | D36: 1 | F36: 850 | G36: =(F36*D36)+(E36*F36) -> 850 | J36: =H36*I36 -> 0 | L36: =(J36+G36)-K36 -> 850 | N36: =IF(M36>0,SUM(L36-M36)," ") | R36: =IF(O36>0,SUM(O36-(L36+P36))," ")
A37: 45152 | C37: MOEBIO IGUATU | E37: 1 | F37: 800 | G37: =(F37*D37)+(E37*F37) -> 800 | J37: =H37*I37 -> 0 | L37: =(J37+G37)-K37 -> 800 | N37: =IF(M37>0,SUM(L37-M37)," ") | R37: =IF(O37>0,SUM(O37-(L37+P37))," ")
A38: 45152 | C38: ANDRE | E38: 1 | F38: 850 | G38: =(F38*D38)+(E38*F38) -> 850 | J38: =H38*I38 -> 0 | L38: =(J38+G38)-K38 -> 850 | N38: =IF(M38>0,SUM(L38-M38)," ") | R38: =IF(O38>0,SUM(O38-(L38+P38))," ")
A39: 45152 | C39: MASSA FIXA | E39: 1 | F39: 800 | G39: =(F39*D39)+(E39*F39) -> 800 | J39: =H39*I39 -> 0 | L39: =(J39+G39)-K39 -> 800 | N39: =IF(M39>0,SUM(L39-M39)," ") | R39: =IF(O39>0,SUM(O39-(L39+P39))," ")
A40: 45152 | C40: LUIZ PI | E40: 2 | F40: 820 | G40: =(F40*D40)+(E40*F40) -> 1640 | J40: =H40*I40 -> 0 | L40: =(J40+G40)-K40 -> 1640 | N40: =IF(M40>0,SUM(L40-M40)," ") | R40: =IF(O40>0,SUM(O40-(L40+P40))," ")
A41: 45153 | C41: CONSTRUMIX | E41: 2 | F41: 820 | G41: =(F41*D41)+(E41*F41) -> 1640 | J41: =H41*I41 -> 0 | L41: =(J41+G41)-K41 -> 1640 | N41: =IF(M41>0,SUM(L41-M41)," ") | R41: =IF(O41>0,SUM(O41-(L41+P41))," ")
A42: 45154 | C42: TODA OBRA | E42: 6 | F42: 820 | G42: =(F42*D42)+(E42*F42) -> 4920 | J42: =H42*I42 -> 0 | L42: =(J42+G42)-K42 -> 4920 | N42: =IF(M42>0,SUM(L42-M42)," ") | R42: =IF(O42>0,SUM(O42-(L42+P42))," ")
A43: 45154 | C43: GETULIO | E43: 3 | F43: 850 | G43: =(F43*D43)+(E43*F43) -> 2550 | J43: =H43*I43 -> 0 | L43: =(J43+G43)-K43 -> 2550 | N43: =IF(M43>0,SUM(L43-M43)," ") | R43: =IF(O43>0,SUM(O43-(L43+P43))," ")
A44: 45154 | C44: FORTMASSA | E44: 1 | F44: 850 | G44: =(F44*D44)+(E44*F44) -> 850 | J44: =H44*I44 -> 0 | L44: =(J44+G44)-K44 -> 850 | N44: =IF(M44>0,SUM(L44-M44)," ") | R44: =IF(O44>0,SUM(O44-(L44+P44))," ")
A45: 45154 | C45: ARG MATEUS | E45: 2 | F45: 830 | G45: =(F45*D45)+(E45*F45) -> 1660 | J45: =H45*I45 -> 0 | L45: =(J45+G45)-K45 -> 1660 | N45: =IF(M45>0,SUM(L45-M45)," ") | R45: =IF(O45>0,SUM(O45-(L45+P45))," ")
F46: 900 | G46: =(F46*D46)+(E46*F46) -> 0 | J46: =H46*I46 -> 0 | L46: =(J46+G46)-K46 -> 0 | N46: =IF(M46>0,SUM(L46-M46)," ") | R46: =IF(O46>0,SUM(O46-(L46+P46))," ")
C47: LOURIMAR | E47: 4 | F47: 840 | G47: =(F47*D47)+(E47*F47) -> 3360 | J47: =H47*I47 -> 0 | L47: =(J47+G47)-K47 -> 3360 | N47: =IF(M47>0,SUM(L47-M47)," ") | R47: =IF(O47>0,SUM(O47-(L47+P47))," ")
C48: DEMETRIU | E48: 6 | F48: 800 | G48: =(F48*D48)+(E48*F48) -> 4800 | J48: =H48*I48 -> 0 | L48: =(J48+G48)-K48 -> 4800 | N48: =IF(M48>0,SUM(L48-M48)," ") | R48: =IF(O48>0,SUM(O48-(L48+P48))," ")
C49: LUIZ PI | E49: 3 | F49: 820 | G49: =(F49*D49)+(E49*F49) -> 2460 | J49: =H49*I49 -> 0 | L49: =(J49+G49)-K49 -> 2460 | N49: =IF(M49>0,SUM(L49-M49)," ") | R49: =IF(O49>0,SUM(O49-(L49+P49))," ")
C50: CONSTRUMIX | E50: 2 | F50: 820 | G50: =(F50*D50)+(E50*F50) -> 1640 | J50: =H50*I50 -> 0 | L50: =(J50+G50)-K50 -> 1640 | N50: =IF(M50>0,SUM(L50-M50)," ") | R50: =IF(O50>0,SUM(O50-(L50+P50))," ")
C51: CONSTRUMIX | E51: 2 | F51: 820 | G51: =(F51*D51)+(E51*F51) -> 1640 | J51: =H51*I51 -> 0 | L51: =(J51+G51)-K51 -> 1640 | N51: =IF(M51>0,SUM(L51-M51)," ") | R51: =IF(O51>0,SUM(O51-(L51+P51))," ")
C52: IRINEU | D52: 1 | F52: 850 | G52: =(F52*D52)+(E52*F52) -> 850 | J52: =H52*I52 -> 0 | L52: =(J52+G52)-K52 -> 850 | N52: =IF(M52>0,SUM(L52-M52)," ") | R52: =IF(O52>0,SUM(O52-(L52+P52))," ")
C53: FELIPE | D53: 2 | F53: 850 | G53: =(F53*D53)+(E53*F53) -> 1700 | J53: =H53*I53 -> 0 | L53: =(J53+G53)-K53 -> 1700 | N53: =IF(M53>0,SUM(L53-M53)," ") | R53: =IF(O53>0,SUM(O53-(L53+P53))," ")
A54: 45159 | C54: CHICO PEREIRA | E54: 2 | F54: 830 | G54: =(F54*D54)+(E54*F54) -> 1660 | J54: =H54*I54 -> 0 | L54: =(J54+G54)-K54 -> 1660 | N54: =IF(M54>0,SUM(L54-M54)," ") | R54: =IF(O54>0,SUM(O54-(L54+P54))," ")
A55: 45159 | C55: FORTMASSA | D55: 1 | F55: 850 | G55: =(F55*D55)+(E55*F55) -> 850 | J55: =H55*I55 -> 0 | L55: =(J55+G55)-K55 -> 850 | N55: =IF(M55>0,SUM(L55-M55)," ") | R55: =IF(O55>0,SUM(O55-(L55+P55))," ")
A56: 45159 | C56: JULIO | D56: 3 | F56: 800 | G56: =(F56*D56)+(E56*F56) -> 2400 | J56: =H56*I56 -> 0 | L56: =(J56+G56)-K56 -> 2400 | N56: =IF(M56>0,SUM(L56-M56)," ") | R56: =IF(O56>0,SUM(O56-(L56+P56))," ")
A57: 45159 | C57: AREMIX | D57: 10 | F57: 820 | G57: =(F57*D57)+(E57*F57) -> 8200 | J57: =H57*I57 -> 0 | L57: =(J57+G57)-K57 -> 8200 | N57: =IF(M57>0,SUM(L57-M57)," ") | R57: =IF(O57>0,SUM(O57-(L57+P57))," ")
A58: 45160 | C58: DEMETRIU | E58: 7 | F58: 800 | G58: =(F58*D58)+(E58*F58) -> 5600 | J58: =H58*I58 -> 0 | L58: =(J58+G58)-K58 -> 5600 | N58: =IF(M58>0,SUM(L58-M58)," ") | R58: =IF(O58>0,SUM(O58-(L58+P58))," ")
A59: 45160 | C59: CEARAMIX | E59: 1 | F59: 840 | G59: =(F59*D59)+(E59*F59) -> 840 | J59: =H59*I59 -> 0 | L59: =(J59+G59)-K59 -> 840 | N59: =IF(M59>0,SUM(L59-M59)," ") | R59: =IF(O59>0,SUM(O59-(L59+P59))," ")
A60: 45161 | C60: ARG MATEUS | E60: 2 | F60: 830 | G60: =(F60*D60)+(E60*F60) -> 1660 | J60: =H60*I60 -> 0 | L60: =(J60+G60)-K60 -> 1660 | N60: =IF(M60>0,SUM(L60-M60)," ") | R60: =IF(O60>0,SUM(O60-(L60+P60))," ")
A61: 45161 | C61: ELIEL | D61: 10 | F61: 800 | G61: =(F61*D61)+(E61*F61) -> 8000 | J61: =H61*I61 -> 0 | L61: =(J61+G61)-K61 -> 8000 | N61: =IF(M61>0,SUM(L61-M61)," ") | R61: =IF(O61>0,SUM(O61-(L61+P61))," ")
A62: 45161 | C62: IRINEU | D62: 1 | F62: 850 | G62: =(F62*D62)+(E62*F62) -> 850 | J62: =H62*I62 -> 0 | L62: =(J62+G62)-K62 -> 850 | N62: =IF(M62>0,SUM(L62-M62)," ") | R62: =IF(O62>0,SUM(O62-(L62+P62))," ")
A63: 45161 | C63: MASSA FIXA | D63: 1 | F63: 800 | G63: =(F63*D63)+(E63*F63) -> 800 | J63: =H63*I63 -> 0 | L63: =(J63+G63)-K63 -> 800 | N63: =IF(M63>0,SUM(L63-M63)," ") | R63: =IF(O63>0,SUM(O63-(L63+P63))," ")
A64: 45161 | C64: GETULIO | D64: 3 | F64: 850 | G64: =(F64*D64)+(E64*F64) -> 2550 | J64: =H64*I64 -> 0 | L64: =(J64+G64)-K64 -> 2550 | N64: =IF(M64>0,SUM(L64-M64)," ") | R64: =IF(O64>0,SUM(O64-(L64+P64))," ")
A65: 45162 | C65: LOURIMAR | E65: 4 | F65: 840 | G65: =(F65*D65)+(E65*F65) -> 3360 | J65: =H65*I65 -> 0 | L65: =(J65+G65)-K65 -> 3360 | N65: =IF(M65>0,SUM(L65-M65)," ") | R65: =IF(O65>0,SUM(O65-(L65+P65))," ")
A66: 45162 | C66: TODA OBRA | E66: 6 | F66: 820 | G66: =(F66*D66)+(E66*F66) -> 4920 | J66: =H66*I66 -> 0 | L66: =(J66+G66)-K66 -> 4920 | N66: =IF(M66>0,SUM(L66-M66)," ") | R66: =IF(O66>0,SUM(O66-(L66+P66))," ")
A67: 45162 | C67: FELIPE | D67: 1 | F67: 850 | G67: =(F67*D67)+(E67*F67) -> 850 | J67: =H67*I67 -> 0 | L67: =(J67+G67)-K67 -> 850 | N67: =IF(M67>0,SUM(L67-M67)," ") | R67: =IF(O67>0,SUM(O67-(L67+P67))," ")
A68: 45162 | C68: FORTMASSA | D68: 1 | F68: 850 | G68: =(F68*D68)+(E68*F68) -> 850 | J68: =H68*I68 -> 0 | L68: =(J68+G68)-K68 -> 850 | N68: =IF(M68>0,SUM(L68-M68)," ") | R68: =IF(O68>0,SUM(O68-(L68+P68))," ")
A69: 45162 | C69: CLAUDIO MOSSORO | D69: 8 | F69: 830 | G69: =(F69*D69)+(E69*F69) -> 6640 | J69: =H69*I69 -> 0 | L69: =(J69+G69)-K69 -> 6640 | N69: =IF(M69>0,SUM(L69-M69)," ") | R69: =IF(O69>0,SUM(O69-(L69+P69))," ")
A70: 45162 | C70: JULIO | D70: 1 | F70: 800 | G70: =(F70*D70)+(E70*F70) -> 800 | J70: =H70*I70 -> 0 | L70: =(J70+G70)-K70 -> 800 | N70: =IF(M70>0,SUM(L70-M70)," ") | R70: =IF(O70>0,SUM(O70-(L70+P70))," ")
F71: 850 | G71: =(F71*D71)+(E71*F71) -> 0 | J71: =H71*I71 -> 0 | L71: =(J71+G71)-K71 -> 0 | N71: =IF(M71>0,SUM(L71-M71)," ") | R71: =IF(O71>0,SUM(O71-(L71+P71))," ")
C72: ARG MATEUS | E72: 3 | F72: 830 | G72: =(F72*D72)+(E72*F72) -> 2490 | J72: =H72*I72 -> 0 | L72: =(J72+G72)-K72 -> 2490 | N72: =IF(M72>0,SUM(L72-M72)," ") | R72: =IF(O72>0,SUM(O72-(L72+P72))," ")
C73: THIAGO TIANGUA | E73: 1 | F73: 850 | G73: =(F73*D73)+(E73*F73) -> 850 | J73: =H73*I73 -> 0 | L73: =(J73+G73)-K73 -> 850 | N73: =IF(M73>0,SUM(L73-M73)," ") | R73: =IF(O73>0,SUM(O73-(L73+P73))," ")
C74: MOEBIO IGUATU | E74: 1 | F74: 800 | G74: =(F74*D74)+(E74*F74) -> 800 | J74: =H74*I74 -> 0 | L74: =(J74+G74)-K74 -> 800 | N74: =IF(M74>0,SUM(L74-M74)," ") | R74: =IF(O74>0,SUM(O74-(L74+P74))," ")
C75: ROBERTO LAGOA DO BANANA | E75: 1 | F75: 850 | G75: =(F75*D75)+(E75*F75) -> 850 | J75: =H75*I75 -> 0 | L75: =(J75+G75)-K75 -> 850 | N75: =IF(M75>0,SUM(L75-M75)," ") | R75: =IF(O75>0,SUM(O75-(L75+P75))," ")
C76: LUIZ PI | E76: 2 | F76: 830 | G76: =(F76*D76)+(E76*F76) -> 1660 | J76: =H76*I76 -> 0 | L76: =(J76+G76)-K76 -> 1660 | N76: =IF(M76>0,SUM(L76-M76)," ") | R76: =IF(O76>0,SUM(O76-(L76+P76))," ")
C77: GETULIO | D77: 1 | F77: 850 | G77: =(F77*D77)+(E77*F77) -> 850 | J77: =H77*I77 -> 0 | L77: =(J77+G77)-K77 -> 850 | N77: =IF(M77>0,SUM(L77-M77)," ") | R77: =IF(O77>0,SUM(O77-(L77+P77))," ")
C78: DEMETRIU | D78: 6 | F78: 800 | G78: =(F78*D78)+(E78*F78) -> 4800 | J78: =H78*I78 -> 0 | L78: =(J78+G78)-K78 -> 4800 | N78: =IF(M78>0,SUM(L78-M78)," ") | R78: =IF(O78>0,SUM(O78-(L78+P78))," ")
C79: IRINEU | D79: 1 | F79: 850 | G79: =(F79*D79)+(E79*F79) -> 850 | J79: =H79*I79 -> 0 | L79: =(J79+G79)-K79 -> 850 | N79: =IF(M79>0,SUM(L79-M79)," ") | R79: =IF(O79>0,SUM(O79-(L79+P79))," ")
A80: 45168 | C80: FORTMASSA | D80: 1 | F80: 850 | G80: =(F80*D80)+(E80*F80) -> 850 | J80: =H80*I80 -> 0 | L80: =(J80+G80)-K80 -> 850 | N80: =IF(M80>0,SUM(L80-M80)," ") | R80: =IF(O80>0,SUM(O80-(L80+P80))," ")
A81: 45168 | C81: GETULIO | D81: 3 | F81: 850 | G81: =(F81*D81)+(E81*F81) -> 2550 | J81: =H81*I81 -> 0 | L81: =(J81+G81)-K81 -> 2550 | N81: =IF(M81>0,SUM(L81-M81)," ") | R81: =IF(O81>0,SUM(O81-(L81+P81))," ")
A82: 45168 | C82: FELIPE | D82: 1 | F82: 850 | G82: =(F82*D82)+(E82*F82) -> 850 | J82: =H82*I82 -> 0 | L82: =(J82+G82)-K82 -> 850 | N82: =IF(M82>0,SUM(L82-M82)," ") | R82: =IF(O82>0,SUM(O82-(L82+P82))," ")
A83: 45168 | C83: LOURIMAR | D83: 4 | F83: 840 | G83: =(F83*D83)+(E83*F83) -> 3360 | J83: =H83*I83 -> 0 | L83: =(J83+G83)-K83 -> 3360 | N83: =IF(M83>0,SUM(L83-M83)," ") | R83: =IF(O83>0,SUM(O83-(L83+P83))," ")
A84: 45169 | C84: TODA OBRA | E84: 6 | F84: 820 | G84: =(F84*D84)+(E84*F84) -> 4920 | J84: =H84*I84 -> 0 | L84: =(J84+G84)-K84 -> 4920 | N84: =IF(M84>0,SUM(L84-M84)," ") | R84: =IF(O84>0,SUM(O84-(L84+P84))," ")
A85: 45169 | C85: AREMIX | D85: 10 | F85: 820 | G85: =(F85*D85)+(E85*F85) -> 8200 | J85: =H85*I85 -> 0 | L85: =(J85+G85)-K85 -> 8200 | N85: =IF(M85>0,SUM(L85-M85)," ") | R85: =IF(O85>0,SUM(O85-(L85+P85))," ")
A86: 45173 | C86: FORTMASSA | D86: 1 | F86: 850 | G86: =(F86*D86)+(E86*F86) -> 850 | J86: =H86*I86 -> 0 | L86: =(J86+G86)-K86 -> 850 | N86: =IF(M86>0,SUM(L86-M86)," ") | R86: =IF(O86>0,SUM(O86-(L86+P86))," ")
A87: 45173 | C87: IRINEU | D87: 1 | F87: 850 | G87: =(F87*D87)+(E87*F87) -> 850 | J87: =H87*I87 -> 0 | L87: =(J87+G87)-K87 -> 850 | N87: =IF(M87>0,SUM(L87-M87)," ") | R87: =IF(O87>0,SUM(O87-(L87+P87))," ")
F88: 850 | G88: =(F88*D88)+(E88*F88) -> 0 | J88: =H88*I88 -> 0 | L88: =(J88+G88)-K88 -> 0 | N88: =IF(M88>0,SUM(L88-M88)," ") | R88: =IF(O88>0,SUM(O88-(L88+P88))," ")
F89: 820 | G89: =(F89*D89)+(E89*F89) -> 0 | J89: =H89*I89 -> 0 | L89: =(J89+G89)-K89 -> 0 | N89: =IF(M89>0,SUM(L89-M89)," ") | R89: =IF(O89>0,SUM(O89-(L89+P89))," ")
F90: 850 | G90: =(F90*D90)+(E90*F90) -> 0 | J90: =H90*I90 -> 0 | L90: =(J90+G90)-K90 -> 0 | N90: =IF(M90>0,SUM(L90-M90)," ") | R90: =IF(O90>0,SUM(O90-(L90+P90))," ")
F91: 820 | G91: =(F91*D91)+(E91*F91) -> 0 | J91: =H91*I91 -> 0 | L91: =(J91+G91)-K91 -> 0 | N91: =IF(M91>0,SUM(L91-M91)," ") | R91: =IF(O91>0,SUM(O91-(L91+P91))," ")
F92: 800 | G92: =(F92*D92)+(E92*F92) -> 0 | J92: =H92*I92 -> 0 | L92: =(J92+G92)-K92 -> 0 | N92: =IF(M92>0,SUM(L92-M92)," ") | R92: =IF(O92>0,SUM(O92-(L92+P92))," ")
F93: 830 | G93: =(F93*D93)+(E93*F93) -> 0 | J93: =H93*I93 -> 0 | L93: =(J93+G93)-K93 -> 0 | N93: =IF(M93>0,SUM(L93-M93)," ") | R93: =IF(O93>0,SUM(O93-(L93+P93))," ")
F94: 850 | G94: =(F94*D94)+(E94*F94) -> 0 | J94: =H94*I94 -> 0 | L94: =(J94+G94)-K94 -> 0 | N94: =IF(M94>0,SUM(L94-M94)," ") | R94: =IF(O94>0,SUM(O94-(L94+P94))," ")
F95: 800 | G95: =(F95*D95)+(E95*F95) -> 0 | J95: =H95*I95 -> 0 | L95: =(J95+G95)-K95 -> 0 | N95: =IF(M95>0,SUM(L95-M95)," ") | R95: =IF(O95>0,SUM(O95-(L95+P95))," ")
F96: 800 | G96: =(F96*D96)+(E96*F96) -> 0 | J96: =H96*I96 -> 0 | L96: =(J96+G96)-K96 -> 0 | N96: =IF(M96>0,SUM(L96-M96)," ") | R96: =IF(O96>0,SUM(O96-(L96+P96))," ")
F97: 800 | G97: =(F97*D97)+(E97*F97) -> 0 | J97: =H97*I97 -> 0 | L97: =(J97+G97)-K97 -> 0 | N97: =IF(M97>0,SUM(L97-M97)," ") | R97: =IF(O97>0,SUM(O97-(L97+P97))," ")
F98: 800 | G98: =(F98*D98)+(E98*F98) -> 0 | J98: =H98*I98 -> 0 | L98: =(J98+G98)-K98 -> 0 | N98: =IF(M98>0,SUM(L98-M98)," ") | R98: =IF(O98>0,SUM(O98-(L98+P98))," ")
F99: 800 | G99: =(F99*D99)+(E99*F99) -> 0 | J99: =H99*I99 -> 0 | L99: =(J99+G99)-K99 -> 0 | N99: =IF(M99>0,SUM(L99-M99)," ") | R99: =IF(O99>0,SUM(O99-(L99+P99))," ")
F100: 800 | G100: =(F100*D100)+(E100*F100) -> 0 | J100: =H100*I100 -> 0 | L100: =(J100+G100)-K100 -> 0 | N100: =IF(M100>0,SUM(L100-M100)," ") | R100: =IF(O100>0,SUM(O100-(L100+P100))," ")
...

Sheet Vendas - SET
A1: VENDAS | B1: VENDAS | D1: =D102 -> 150 | F1: =AA13 -> 123550
A2: DATA | B2: VENDEDOR | C2: Clientes | D2: CELULOSE | H2: POLÍMERO | K2: DESCONTO CHEQUE | L2: TOTAL | M2: PARCIAL | N2: DEVENDO | O2: CHEQUES / PAGAMENTOS A MAIS OU A MENOS | T2: Forma de Pagamento | U2: Prazo | V2: Frete CIF / FOB | W2: OBSERVAÇÃO | X2: OBSERVAÇÃO
D3: PALOMA | E3: UCHOA | F3: PREÇO | G3: TOTAL | H3: QTD | I3: PREÇO TAB | J3: TOTAL | O3: VALOR VENDA | P3: COBRAMOS % | Q3: PAGAMOS % | R3: SALDO/DEBITO CLIENTE | S3: LUCRO/PREJ JUROS
A4: 45174 | C4: MASSA FIXA | D4: 1 | F4: 800 | G4: =(F4*D4)+(E4*F4) -> 800 | J4: =H4*I4 -> 0 | L4: =(J4+G4)-K4 -> 800 | N4: =IF(M4>0,SUM(L4-M4)," ") | R4: =IF(O4>0,SUM(O4-(L4+P4))," ") | T4: A VISTA | U4: 0 | V4: FOB
A5: 45174 | C5: DEMETRIU | E5: 8 | F5: 800 | G5: =(F5*D5)+(E5*F5) -> 6400 | J5: =H5*I5 -> 0 | L5: =(J5+G5)-K5 -> 6400 | N5: =IF(M5>0,SUM(L5-M5)," ") | R5: =IF(O5>0,SUM(O5-(L5+P5))," ") | T5: A VISTA | U5: 0 | V5: FOB
A6: 45174 | C6: CHICO PEREIRA | E6: 2 | F6: 830 | G6: =(F6*D6)+(E6*F6) -> 1660 | J6: =H6*I6 -> 0 | L6: =(J6+G6)-K6 -> 1660 | N6: =IF(M6>0,SUM(L6-M6)," ") | R6: =IF(O6>0,SUM(O6-(L6+P6))," ") | T6: A VISTA | U6: 0 | V6: FOB
A7: 45175 | C7: MOEBIO | E7: 1 | F7: 800 | G7: =(F7*D7)+(E7*F7) -> 800 | J7: =H7*I7 -> 0 | L7: =(J7+G7)-K7 -> 800 | N7: =IF(M7>0,SUM(L7-M7)," ") | R7: =IF(O7>0,SUM(O7-(L7+P7))," ") | T7: A VISTA | U7: 0 | V7: FOB
A8: 45175 | C8: LOURIMAR | E8: 4 | F8: 840 | G8: =(F8*D8)+(E8*F8) -> 3360 | J8: =H8*I8 -> 0 | L8: =(J8+G8)-K8 -> 3360 | N8: =IF(M8>0,SUM(L8-M8)," ") | O8: 1400 | R8: =IF(O8>0,SUM(O8-(L8+P8))," ") -> -1960 | T8: CHEQUE/R$ | U8: 0 | V8: FOB | W8: 1100 + 300 | Y8: VALOR | Z8: QTD | AA8: =G101 -> 123550
A9: 45175 | C9: GETULIO | D9: 3 | F9: 850 | G9: =(F9*D9)+(E9*F9) -> 2550 | J9: =H9*I9 -> 0 | L9: =(J9+G9)-K9 -> 2550 | N9: =IF(M9>0,SUM(L9-M9)," ") | R9: =IF(O9>0,SUM(O9-(L9+P9))," ") | T9: A VISTA | U9: 0 | V9: FOB | Y9: 720 | AA9: =Y9*Z9 -> 0
A10: 45175 | C10: ARG MATEUS | D10: 2 | F10: 830 | G10: =(F10*D10)+(E10*F10) -> 1660 | J10: =H10*I10 -> 0 | L10: =(J10+G10)-K10 -> 1660 | N10: =IF(M10>0,SUM(L10-M10)," ") | R10: =IF(O10>0,SUM(O10-(L10+P10))," ") | T10: A VISTA | U10: 0 | V10: FOB | Y10: 750 | AA10: =Y10*Z10 -> 0
A11: 45175 | C11: IRINEU | D11: 1 | F11: 850 | G11: =(F11*D11)+(E11*F11) -> 850 | J11: =H11*I11 -> 0 | L11: =(J11+G11)-K11 -> 850 | N11: =IF(M11>0,SUM(L11-M11)," ") | R11: =IF(O11>0,SUM(O11-(L11+P11))," ") | T11: A VISTA | U11: 0 | V11: FOB | Y11: 780 | AA11: =Y11*Z11 -> 0
A12: 45175 | C12: FELIPE | D12: 1 | F12: 850 | G12: =(F12*D12)+(E12*F12) -> 850 | J12: =H12*I12 -> 0 | L12: =(J12+G12)-K12 -> 850 | N12: =IF(M12>0,SUM(L12-M12)," ") | R12: =IF(O12>0,SUM(O12-(L12+P12))," ") | T12: A VISTA | U12: 0 | V12: FOB | Y12: 800 | AA12: =Y12*Z12 -> 0
A13: 45177 | C13: MULTCOLA | E13: 4 | F13: 800 | G13: =(F13*D13)+(E13*F13) -> 3200 | J13: =H13*I13 -> 0 | L13: =(J13+G13)-K13 -> 3200 | N13: =IF(M13>0,SUM(L13-M13)," ") | O13: 440 | R13: =IF(O13>0,SUM(O13-(L13+P13))," ") -> -2760 | S13: =P13-Q13 -> 0 | T13: A VISTA | U13: 30 | V13: FOB | W13: QUITACAO CREDITO | AA13: =AA8-(SUM(AA9:AA12)) -> 123550
A14: 45177 | C14: TODA OBRA | E14: 4 | F14: 820 | G14: =(F14*D14)+(E14*F14) -> 3280 | J14: =H14*I14 -> 0 | L14: =(J14+G14)-K14 -> 3280 | N14: =IF(M14>0,SUM(L14-M14)," ") | R14: =IF(O14>0,SUM(O14-(L14+P14))," ")
A15: 45177 | C15: FORTMASSA | D15: 1 | F15: 850 | G15: =(F15*D15)+(E15*F15) -> 850 | J15: =H15*I15 -> 0 | L15: =(J15+G15)-K15 -> 850 | N15: =IF(M15>0,SUM(L15-M15)," ") | R15: =IF(O15>0,SUM(O15-(L15+P15))," ")
A16: 45177 | C16: ANDRE | D16: 1 | F16: 850 | G16: =(F16*D16)+(E16*F16) -> 850 | J16: =H16*I16 -> 0 | L16: =(J16+G16)-K16 -> 850 | N16: =IF(M16>0,SUM(L16-M16)," ") | R16: =IF(O16>0,SUM(O16-(L16+P16))," ")
A17: 45178 | C17: FELIPE | D17: 2 | F17: 850 | G17: =(F17*D17)+(E17*F17) -> 1700 | J17: =H17*I17 -> 0 | L17: =(J17+G17)-K17 -> 1700 | N17: =IF(M17>0,SUM(L17-M17)," ") | R17: =IF(O17>0,SUM(O17-(L17+P17))," ")
A18: 45180 | C18: DEMETRIU | E18: 6 | F18: 780 | G18: =(F18*D18)+(E18*F18) -> 4680 | J18: =H18*I18 -> 0 | L18: =(J18+G18)-K18 -> 4680 | N18: =IF(M18>0,SUM(L18-M18)," ") | R18: =IF(O18>0,SUM(O18-(L18+P18))," ")
A19: 45180 | C19: ROBERTO LAGOA DO BANANA | E19: 1 | F19: 840 | G19: =(F19*D19)+(E19*F19) -> 840 | J19: =H19*I19 -> 0 | L19: =(J19+G19)-K19 -> 840 | N19: =IF(M19>0,SUM(L19-M19)," ") | R19: =IF(O19>0,SUM(O19-(L19+P19))," ")
A20: 45180 | C20: IRINEU | D20: 1 | F20: 850 | G20: =(F20*D20)+(E20*F20) -> 850 | J20: =H20*I20 -> 0 | L20: =(J20+G20)-K20 -> 850 | N20: =IF(M20>0,SUM(L20-M20)," ") | R20: =IF(O20>0,SUM(O20-(L20+P20))," ")
A21: 45181 | C21: GETULIO | D21: 1 | F21: 850 | G21: =(F21*D21)+(E21*F21) -> 850 | J21: =H21*I21 -> 0 | L21: =(J21+G21)-K21 -> 850 | N21: =IF(M21>0,SUM(L21-M21)," ") | R21: =IF(O21>0,SUM(O21-(L21+P21))," ")
A22: 45181 | C22: FORTMASSA | D22: 1 | F22: 850 | G22: =(F22*D22)+(E22*F22) -> 850 | J22: =H22*I22 -> 0 | L22: =(J22+G22)-K22 -> 850 | N22: =IF(M22>0,SUM(L22-M22)," ") | R22: =IF(O22>0,SUM(O22-(L22+P22))," ")
A23: 45181 | C23: CONSTRUMIX | E23: 8 | F23: 820 | G23: =(F23*D23)+(E23*F23) -> 6560 | J23: =H23*I23 -> 0 | L23: =(J23+G23)-K23 -> 6560 | N23: =IF(M23>0,SUM(L23-M23)," ") | R23: =IF(O23>0,SUM(O23-(L23+P23))," ")
A24: 45182 | C24: CLAUDIO MOSSORO | D24: 8 | F24: 830 | G24: =(F24*D24)+(E24*F24) -> 6640 | J24: =H24*I24 -> 0 | L24: =(J24+G24)-K24 -> 6640 | N24: =IF(M24>0,SUM(L24-M24)," ") | R24: =IF(O24>0,SUM(O24-(L24+P24))," ")
A25: 45182 | C25: GETULIO | D25: 3 | F25: 850 | G25: =(F25*D25)+(E25*F25) -> 2550 | J25: =H25*I25 -> 0 | L25: =(J25+G25)-K25 -> 2550 | N25: =IF(M25>0,SUM(L25-M25)," ") | R25: =IF(O25>0,SUM(O25-(L25+P25))," ")
A26: 45183 | C26: MOEBIO | E26: 1 | F26: 800 | G26: =(F26*D26)+(E26*F26) -> 800 | J26: =H26*I26 -> 0 | L26: =(J26+G26)-K26 -> 800 | N26: =IF(M26>0,SUM(L26-M26)," ") | R26: =IF(O26>0,SUM(O26-(L26+P26))," ")
A27: 45183 | C27: LOURIMAR | E27: 4 | F27: 840 | G27: =(F27*D27)+(E27*F27) -> 3360 | J27: =H27*I27 -> 0 | L27: =(J27+G27)-K27 -> 3360 | N27: =IF(M27>0,SUM(L27-M27)," ") | R27: =IF(O27>0,SUM(O27-(L27+P27))," ")
A28: 45183 | C28: FELIPE | D28: 1 | F28: 850 | G28: =(F28*D28)+(E28*F28) -> 850 | J28: =H28*I28 -> 0 | L28: =(J28+G28)-K28 -> 850 | N28: =IF(M28>0,SUM(L28-M28)," ") | R28: =IF(O28>0,SUM(O28-(L28+P28))," ")
A29: 45184 | C29: FORTMASSA | D29: 1 | F29: 850 | G29: =(F29*D29)+(E29*F29) -> 850 | J29: =H29*I29 -> 0 | L29: =(J29+G29)-K29 -> 850 | N29: =IF(M29>0,SUM(L29-M29)," ") | R29: =IF(O29>0,SUM(O29-(L29+P29))," ")
A30: 45187 | C30: IRINEU | D30: 1 | F30: 850 | G30: =(F30*D30)+(E30*F30) -> 850 | J30: =H30*I30 -> 0 | L30: =(J30+G30)-K30 -> 850 | N30: =IF(M30>0,SUM(L30-M30)," ") | R30: =IF(O30>0,SUM(O30-(L30+P30))," ")
A31: 45187 | C31: DEMETRIU | E31: 6 | F31: 780 | G31: =(F31*D31)+(E31*F31) -> 4680 | J31: =H31*I31 -> 0 | L31: =(J31+G31)-K31 -> 4680 | N31: =IF(M31>0,SUM(L31-M31)," ") | R31: =IF(O31>0,SUM(O31-(L31+P31))," ")
A32: 45187 | C32: THIAGO TIANGUA | E32: 1 | F32: 850 | G32: =(F32*D32)+(E32*F32) -> 850 | J32: =H32*I32 -> 0 | L32: =(J32+G32)-K32 -> 850 | N32: =IF(M32>0,SUM(L32-M32)," ") | R32: =IF(O32>0,SUM(O32-(L32+P32))," ")
A33: 45187 | C33: CHICO PEREIRA | E33: 2 | F33: 830 | G33: =(F33*D33)+(E33*F33) -> 1660 | J33: =H33*I33 -> 0 | L33: =(J33+G33)-K33 -> 1660 | N33: =IF(M33>0,SUM(L33-M33)," ") | R33: =IF(O33>0,SUM(O33-(L33+P33))," ")
A34: 45187 | C34: FELIPE | D34: 1 | F34: 850 | G34: =(F34*D34)+(E34*F34) -> 850 | J34: =H34*I34 -> 0 | L34: =(J34+G34)-K34 -> 850 | N34: =IF(M34>0,SUM(L34-M34)," ") | R34: =IF(O34>0,SUM(O34-(L34+P34))," ")
A35: 45188 | C35: MASSA FIXA | D35: 1 | F35: 800 | G35: =(F35*D35)+(E35*F35) -> 800 | J35: =H35*I35 -> 0 | L35: =(J35+G35)-K35 -> 800 | N35: =IF(M35>0,SUM(L35-M35)," ") | R35: =IF(O35>0,SUM(O35-(L35+P35))," ")
A36: 45189 | C36: JOSIEL | D36: 1 | F36: 850 | G36: =(F36*D36)+(E36*F36) -> 850 | J36: =H36*I36 -> 0 | L36: =(J36+G36)-K36 -> 850 | N36: =IF(M36>0,SUM(L36-M36)," ") | R36: =IF(O36>0,SUM(O36-(L36+P36))," ")
A37: 45189 | C37: FORTMASSA | D37: 1 | F37: 850 | G37: =(F37*D37)+(E37*F37) -> 850 | J37: =H37*I37 -> 0 | L37: =(J37+G37)-K37 -> 850 | N37: =IF(M37>0,SUM(L37-M37)," ") | R37: =IF(O37>0,SUM(O37-(L37+P37))," ")
A38: 45189 | C38: LOURIMAR | E38: 6 | F38: 840 | G38: =(F38*D38)+(E38*F38) -> 5040 | J38: =H38*I38 -> 0 | L38: =(J38+G38)-K38 -> 5040 | N38: =IF(M38>0,SUM(L38-M38)," ") | R38: =IF(O38>0,SUM(O38-(L38+P38))," ")
A39: 45189 | C39: TODA OBRA | E39: 10 | F39: 820 | G39: =(F39*D39)+(E39*F39) -> 8200 | J39: =H39*I39 -> 0 | L39: =(J39+G39)-K39 -> 8200 | N39: =IF(M39>0,SUM(L39-M39)," ") | R39: =IF(O39>0,SUM(O39-(L39+P39))," ")
A40: 45189 | C40: AREMIX | D40: 10 | F40: 820 | G40: =(F40*D40)+(E40*F40) -> 8200 | J40: =H40*I40 -> 0 | L40: =(J40+G40)-K40 -> 8200 | N40: =IF(M40>0,SUM(L40-M40)," ") | R40: =IF(O40>0,SUM(O40-(L40+P40))," ")
A41: 45190 | C41: ARG ROMA | D41: 4 | F41: 810 | G41: =(F41*D41)+(E41*F41) -> 3240 | J41: =H41*I41 -> 0 | L41: =(J41+G41)-K41 -> 3240 | N41: =IF(M41>0,SUM(L41-M41)," ") | R41: =IF(O41>0,SUM(O41-(L41+P41))," ")
A42: 45190 | C42: IRINEU | D42: 1 | F42: 850 | G42: =(F42*D42)+(E42*F42) -> 850 | J42: =H42*I42 -> 0 | L42: =(J42+G42)-K42 -> 850 | N42: =IF(M42>0,SUM(L42-M42)," ") | R42: =IF(O42>0,SUM(O42-(L42+P42))," ")
A43: 45194 | C43: FELIPE | D43: 1 | F43: 850 | G43: =(F43*D43)+(E43*F43) -> 850 | J43: =H43*I43 -> 0 | L43: =(J43+G43)-K43 -> 850 | N43: =IF(M43>0,SUM(L43-M43)," ") | R43: =IF(O43>0,SUM(O43-(L43+P43))," ")
A44: 45194 | C44: FORTMASSA | D44: 1 | F44: 850 | G44: =(F44*D44)+(E44*F44) -> 850 | J44: =H44*I44 -> 0 | L44: =(J44+G44)-K44 -> 850 | N44: =IF(M44>0,SUM(L44-M44)," ") | R44: =IF(O44>0,SUM(O44-(L44+P44))," ")
A45: 45194 | C45: MASSA FIXA | D45: 1 | F45: 800 | G45: =(F45*D45)+(E45*F45) -> 800 | J45: =H45*I45 -> 0 | L45: =(J45+G45)-K45 -> 800 | N45: =IF(M45>0,SUM(L45-M45)," ") | R45: =IF(O45>0,SUM(O45-(L45+P45))," ")
A46: 45194 | C46: DEMETRIU | E46: 6 | F46: 780 | G46: =(F46*D46)+(E46*F46) -> 4680 | J46: =H46*I46 -> 0 | L46: =(J46+G46)-K46 -> 4680 | N46: =IF(M46>0,SUM(L46-M46)," ") | R46: =IF(O46>0,SUM(O46-(L46+P46))," ")
A47: 45194 | C47: ROBERTO LAGOA DO BANANA | E47: 1 | F47: 850 | G47: =(F47*D47)+(E47*F47) -> 850 | J47: =H47*I47 -> 0 | L47: =(J47+G47)-K47 -> 850 | N47: =IF(M47>0,SUM(L47-M47)," ") | R47: =IF(O47>0,SUM(O47-(L47+P47))," ")
A48: 45196 | C48: ARG LUZ E COLA | D48: 1 | F48: 800 | G48: =(F48*D48)+(E48*F48) -> 800 | J48: =H48*I48 -> 0 | L48: =(J48+G48)-K48 -> 800 | N48: =IF(M48>0,SUM(L48-M48)," ") | R48: =IF(O48>0,SUM(O48-(L48+P48))," ")
A49: 45196 | C49: GETULIO | D49: 3 | F49: 850 | G49: =(F49*D49)+(E49*F49) -> 2550 | J49: =H49*I49 -> 0 | L49: =(J49+G49)-K49 -> 2550 | N49: =IF(M49>0,SUM(L49-M49)," ") | R49: =IF(O49>0,SUM(O49-(L49+P49))," ")
A50: 45196 | C50: FORTMASSA | D50: 1 | F50: 850 | G50: =(F50*D50)+(E50*F50) -> 850 | J50: =H50*I50 -> 0 | L50: =(J50+G50)-K50 -> 850 | N50: =IF(M50>0,SUM(L50-M50)," ") | R50: =IF(O50>0,SUM(O50-(L50+P50))," ")
A51: 45196 | C51: CLAUDIO MOSSORO | D51: 8 | F51: 830 | G51: =(F51*D51)+(E51*F51) -> 6640 | J51: =H51*I51 -> 0 | L51: =(J51+G51)-K51 -> 6640 | N51: =IF(M51>0,SUM(L51-M51)," ") | R51: =IF(O51>0,SUM(O51-(L51+P51))," ")
A52: 45197 | C52: IRINEU | D52: 1 | F52: 850 | G52: =(F52*D52)+(E52*F52) -> 850 | J52: =H52*I52 -> 0 | L52: =(J52+G52)-K52 -> 850 | N52: =IF(M52>0,SUM(L52-M52)," ") | R52: =IF(O52>0,SUM(O52-(L52+P52))," ")
A53: 45197 | C53: LOURIMAR | E53: 4 | F53: 840 | G53: =(F53*D53)+(E53*F53) -> 3360 | J53: =H53*I53 -> 0 | L53: =(J53+G53)-K53 -> 3360 | N53: =IF(M53>0,SUM(L53-M53)," ") | R53: =IF(O53>0,SUM(O53-(L53+P53))," ")
A54: 45198 | C54: FELIPE | D54: 1 | F54: 850 | G54: =(F54*D54)+(E54*F54) -> 850 | J54: =H54*I54 -> 0 | L54: =(J54+G54)-K54 -> 850 | N54: =IF(M54>0,SUM(L54-M54)," ") | R54: =IF(O54>0,SUM(O54-(L54+P54))," ")
A55: 45201 | C55: FORTMASSA | E55: 1 | F55: 850 | G55: =(F55*D55)+(E55*F55) -> 850 | J55: =H55*I55 -> 0 | L55: =(J55+G55)-K55 -> 850 | N55: =IF(M55>0,SUM(L55-M55)," ") | R55: =IF(O55>0,SUM(O55-(L55+P55))," ")
G56: =(F56*D56)+(E56*F56) -> 0 | J56: =H56*I56 -> 0 | L56: =(J56+G56)-K56 -> 0 | N56: =IF(M56>0,SUM(L56-M56)," ") | R56: =IF(O56>0,SUM(O56-(L56+P56))," ")
A57: 45201 | C57: CHICO PEREIRA | E57: 2 | F57: 830 | G57: =(F57*D57)+(E57*F57) -> 1660 | J57: =H57*I57 -> 0 | L57: =(J57+G57)-K57 -> 1660 | N57: =IF(M57>0,SUM(L57-M57)," ") | R57: =IF(O57>0,SUM(O57-(L57+P57))," ")
A58: 45201 | C58: CEARAMIX | E58: 1 | F58: 840 | G58: =(F58*D58)+(E58*F58) -> 840 | J58: =H58*I58 -> 0 | L58: =(J58+G58)-K58 -> 840 | N58: =IF(M58>0,SUM(L58-M58)," ") | R58: =IF(O58>0,SUM(O58-(L58+P58))," ")
A59: 45201 | C59: DEDE DO ARROZ | D59: 1 | F59: 860 | G59: =(F59*D59)+(E59*F59) -> 860 | J59: =H59*I59 -> 0 | L59: =(J59+G59)-K59 -> 860 | N59: =IF(M59>0,SUM(L59-M59)," ") | R59: =IF(O59>0,SUM(O59-(L59+P59))," ")
F60: 880 | G60: =(F60*D60)+(E60*F60) -> 0 | J60: =H60*I60 -> 0 | L60: =(J60+G60)-K60 -> 0 | N60: =IF(M60>0,SUM(L60-M60)," ") | R60: =IF(O60>0,SUM(O60-(L60+P60))," ")
